Workbook
Name SOFR: '01_Params'!$D$5
Name TSOFR1M: '01_Params'!$D$6
Name TSOFR3M: '01_Params'!$D$7
Name CD91D: '01_Params'!$D$8
Name BOK_Base: '01_Params'!$D$9
Name USDKRW: '01_Params'!$D$10
Name Hana31: '01_Params'!$D$11
Name Hana92: '01_Params'!$D$12
Name Hana184: '01_Params'!$D$13
Name ImplSpread31: '01_Params'!$D$14
Name ImplSpread92: '01_Params'!$D$15
Name DayBasis: '01_Params'!$D$16
Name DayBasisKRW: '01_Params'!$D$17
Name Fee_KRW: '01_Params'!$D$18
Name CollectFee: '01_Params'!$D$19
Name FactoringFee: '01_Params'!$D$20
Name KS_Direct_AC: '01_Params'!$D$21
Name KS_Direct_Oth: '01_Params'!$D$22
Name KS_Direct_Gen: '01_Params'!$D$23
Name KS_PlusLo: '01_Params'!$D$24
Name KS_PlusHi: '01_Params'!$D$25
Name KS_PlusLC: '01_Params'!$D$26
Name KS_Forfaiting: '01_Params'!$D$27
Name KS_GuarLo: '01_Params'!$D$28
Name KS_GuarHi: '01_Params'!$D$29
Name Cov: '01_Params'!$D$30
Name Spread_S: '01_Params'!$D$31
Name Spread_A: '01_Params'!$D$32
Name Spread_B: '01_Params'!$D$33
Name Spread_C: '01_Params'!$D$34
Name Prem_S: '01_Params'!$D$35
Name Prem_A: '01_Params'!$D$36
Name Prem_B: '01_Params'!$D$37
Name Prem_C: '01_Params'!$D$38
Name PD_S: '01_Params'!$D$39
Name PD_A: '01_Params'!$D$40
Name PD_B: '01_Params'!$D$41
Name PD_C: '01_Params'!$D$42
Name LGD: '01_Params'!$D$43
Name EarlyPay_2_10_30: '01_Params'!$D$44
Name Equity_USD: '01_Params'!$D$45
Name Alpha: '01_Params'!$D$46
Name s_S: '01_Params'!$D$47
Name s_A: '01_Params'!$D$48
Name s_B: '01_Params'!$D$49
Name s_C: '01_Params'!$D$50
Name Fed_Lo: '01_Params'!$D$51
Name Fed_Hi: '01_Params'!$D$52
Name Tenor: '01_Params'!$D$53
Name Grace: '01_Params'!$D$54
Name Cap_A: '01_Params'!$D$55
Name Cap_B: '01_Params'!$D$56
Name Cap_C_OA: '01_Params'!$D$57
Name ShareCap_B: '01_Params'!$D$58
Name CtryCap_02: '01_Params'!$D$59
Name CtryCap_3: '01_Params'!$D$60
Name CtryCap_45: '01_Params'!$D$61
Name CtryCap_67: '01_Params'!$D$62
Name TotalCapShare: '01_Params'!$D$63
Name Util: '01_Params'!$D$64

Sheet 00_README
A1: d4_limit_model.xlsx — Day4 한도 최적화·할인율·시나리오·조기경보 워크북 (가상 한빛정밀(주) 교육용)
A3: 파일 | B3: 빈 틀(공개 저장소 labs/day4) — 02_Buyers에 d4_start_scored.csv를 붙여 넣어 시작
A4: 목적 | B4: 등급(PD)·보험·금융비용을 반영해 바이어별 신용한도를 선형계획(LP)으로 배분하고, 할인율·NPV, 4단계 충격·몬테카를로, 충당금, 조기경보를 한 파일에서 계산한다.
A5: 기준일 | B5: 2026-09-30(01_Params AsOf) · 금리 2026-09-23(Term SOFR 3M 4.047%, 하나은행 환가료) · 원/달러 1,360.0(ECOS 매매기준율 09-23)
A6: 색 규칙 | B6: 파랑 = 공시·규정값 · 노랑 = [가정]·[교육용 가정](바꿔 볼 수 있음) · 회색 = 수식(수정 금지) · 주황 = 결정변수(해 찾기가 채움) · 연두 = 붙여넣기 칸
A7: 시작(Lab 1) | B7: ① 01_Params 노랑 칸 확인 ② d4_start_scored.csv 전체(머리글 포함)를 복사 → 02_Buyers A1에 '값 붙여넣기'(Ctrl+Alt+V → 값) — 회색 열이 150행 채워지는지 확인 ③ 03_RateBuild 검산표 ✔ ④ 05_NPV 은행 견적 1,669.54달러·6.59%
A8: 한도 LP(Lab 2) | B8: 10_LimitLP → 데이터 → 해 찾기: 목표 $C$2(Obj) 최대 · 변수 $F$5:$F$154 · 제약 6줄(시트 오른쪽 '해 찾기 입력표') · '제한되지 않는 변수를 음이 아닌 수로' ✔ · 해법 '단순 LP' → 해 찾기 → 보고서 '해답'·'민감도'
A9: 해 찾기 켜기 | B9: 파일 → 옵션 → 추가 기능 → 관리: Excel 추가 기능 → 이동 → '해 찾기 추가 기능' ✔. 웹 Excel에는 없다(Frontline Solver App·Google Sheets+OpenSolver)
A10: 시나리오(Lab 3) | B10: 11_Scenario: S0~S4 결과표 · 실제 충격 재현(R2026) · 몬테카를로(드롭다운에서 시나리오 선택 → F9). 계산 옵션은 '데이터 표를 제외하고 자동'으로 저장돼 있다 — 데이터 표 1,000회는 F9를 눌러야 갱신
A11: 조기경보 | B11: 13_EarlyWarning: open_inv(기준일 미결 인보이스 ≤300행) → 단계(D-3/D+7/D+15/D+30)·K-SURE 사고발생통지 기한(결제기일 + 1개월)·선적 보류. 선적 보류 바이어는 02_Buyers UB가 0이 된다
A12: 리포트(Lab 4) | B12: 14_ReportInput 표 5개 → 프롬프트 P4-1(바이어 실명 없이 ID만). 한도 변경·선적 보류·K-SURE 통지는 사람이 승인한다
A13: 🔵 선택 | B13: 06_WeeklyGap·07_Solver(유동성 갭 최소비용 매각) · 08_Sensitivity · 12_ECL(충당금 3종) · 15_Bond(공공조달 보증 EAD) · 01_Params GradeRule = quantile(분위수 등급 비교)
A14: 🟣 Challenge | B14: labs/day4/d4_challenge.ipynb(PuLP 3.3.2 · scipy linprog · 몬테카를로 1-요인) → 16_Compare에 PuLP 해를 붙여 비교
... A18: 데이터 | B18: (가상) 한빛정밀(주) 합성 데이터 — 실존 기업·인물과 무관. 회사 실데이터는 익명화 템플릿을 거친 뒤에만 넣는다
A20: 색 견본 | B20: 공시·규정 | C20: 가정 | D20: 수식 | E20: 결정변수 | F20: 붙여넣기
A22: 시트 | B22: 내용
A23: 00_README | B23: 이 안내
A24: 01_Params | B24: 파라미터 65개(이름 정의) + AsOf·GradeRule 등
A25: 02_Buyers | B25: d4_start_scored 붙여넣기(A~AI) + 계산 열(AK~BI): PD·r·Need·Cap·Ins·Self·UB·LB·coef
A26: 03_RateBuild | B26: 등급별 위험조정 할인율·NPV 검산(USD 100,000·90일)
A27: 04_AR_Ledger | B27: G03 예제 원장 R1~R7(🔵)
A28: 05_NPV | B28: 은행 견적 대조 + 바이어별 채권 NPV·부보 판정
A29: 06_WeeklyGap | B29: 8주 유동성 갭(🔵)
A30: 07_Solver | B30: 최소비용 매각 LP(🔵, 해 찾기 모델 저장됨)
A31: 08_Sensitivity | B31: TSOFR ±100bp·PD×2·LGD 40/80%
A32: 09_Chart | B32: 누적현금·할인율 구성·등급별 한도 차트
A33: 10_LimitLP | B33: 한도 배분 LP(해 찾기 모델 저장됨) + 국가 한도 블록
... A39: 16_Compare | B39: Excel vs PuLP(🟣)

Sheet 01_Params
A1: 01_Params — 파라미터(셀마다 이름 정의, d4_params.csv와 같은 값)
A2: 값은 소수로 넣는다(4.047% = 0.04047, 백분율 서식). 파랑 = 공시·규정 · 노랑 = [가정]·[교육용 가정](🔵 바꿔 보기) · 회색 = 계산
A4: param_id | B4: 이름(Excel) | C4: 항목 | D4: 값 | E4: 단위 | F4: 구분 | G4: 출처 | H4: 기준일 | I4: 메모 | J4: URL
A5: P1 | B5: SOFR | C5: SOFR(익일물 담보 기준금리) | D5: 0.0388 | E5: 연율 | F5: 확인 | G5: NY Fed SOFR API [G03 1] | H5: 2026-09-24 | I5: 09-16 3.62% → 09-17 3.85%(FOMC 인상 다음 날) | J5: https://markets.newyorkfed.org/api/rates/secured/sofr/last/10.json
A6: P2 | B6: TSOFR1M | C6: Term SOFR 1개월 | D6: 0.03901 | E6: 연율 | F6: 확인 | G6: CME Term SOFR(Chatham 재배포) [G03 5] | H6: 2026-09-23 | I6: CME 원 페이지는 자동 조회 차단 — 수업 당일 브라우저로 확인 | J6: https://cf.com/rates/us
A7: P3 | B7: TSOFR3M | C7: Term SOFR 3개월 | D7: 0.04047 | E7: 연율 | F7: 확인 | G7: CME Term SOFR(Chatham 재배포) [G03 5] | H7: 2026-09-23 | I7: 할인율·LP 금리의 기준 B(t) | J7: https://cf.com/rates/us
A8: P4 | B8: CD91D | C8: CD 91일물 | D8: 0.0321 | E8: 연율 | F8: 확인 | G8: 한국은행 ECOS 817Y002/010502000 [G03 7] | H8: 2026-09-23 | I8: 원화 대안 비교용 | J8: https://ecos.bok.or.kr/
A9: P5 | B9: BOK_Base | C9: 한국은행 기준금리 | D9: 0.03 | E9: 연율 | F9: 확인 | G9: 한국은행 기준금리 추이 [G03 6] | H9: 2026-08-27 | I9: 2.50%(2025-05-29) → 2.75%(2026-07-16) → 3.00%(2026-08-27 인상) | J9: https://www.bok.or.kr/portal/singl/baseRate/list.do?dataSeCd=01&menuNo=200643
A10: P6 | B10: USDKRW | C10: 원/달러 매매기준율 | D10: 1360 | E10: 원 | F10: 확인 | G10: 한국은행 ECOS 731Y001/0000001 [G03 9] | H10: 2026-09-23 | I10: FRED 뉴욕 정오율과 기준·시각이 다르다 — 11_Scenario S0 원/달러 | J10: https://ecos.bok.or.kr/
A11: P7_31D | B11: Hana31 | C11: 하나은행 USD 기한부 환가료율 31일(일괄선취) | D11: 0.0574851 | E11: 연율 | F11: 확인 | G11: 하나은행 기한부환가료율 [G03 10] | H11: 2026-09-23 | I11: 고시 = 기준금리(Term SOFR) + 가산금리, 우대 전 | J11: https://www.kebhana.com/cms/rate/index.do?contentUrl=/cms/rate/wpfxd652_01i.do
A12: P7_92D | B12: Hana92 | C12: 하나은행 USD 기한부 환가료율 92일(일괄선취) | D12: 0.0653297 | E12: 연율 | F12: 확인 | G12: 하나은행 기한부환가료율 [G03 10] | H12: 2026-09-23 | I12: 05_NPV 은행 견적 대조(USD 100,000·92일 → 환가료 USD 1,669.54) | J12: https://www.kebhana.com/cms/rate/index.do?contentUrl=/cms/rate/wpfxd652_01i.do
A13: P7_184D | B13: Hana184 | C13: 하나은행 USD 기한부 환가료율 184일(일괄선취) | D13: 0.0690141 | E13: 연율 | F13: 확인 | G13: 하나은행 기한부환가료율 [G03 10] | H13: 2026-09-23 | I13: 123·184일 같은 구간 | J13: https://www.kebhana.com/cms/rate/index.do?contentUrl=/cms/rate/wpfxd652_01i.do
A14: P8_31D | B14: ImplSpread31 | C14: 암묵 가산금리 31일(고시 − Term SOFR 1M) | D14: =Hana31-TSOFR1M | E14: %p | F14: 계산 | G14: P7_31D − P2 [G03 §2.2.3] | H14: 2026-09-23 | I14: 우대 전 고시 기준 상한 성격
A15: P8_92D | B15: ImplSpread92 | C15: 암묵 가산금리 92일(고시 − Term SOFR 3M) | D15: =Hana92-TSOFR3M | E15: %p | F15: 계산 | G15: P7_92D − P3 [G03 §2.2.3] | H15: 2026-09-23 | I15: C등급 은행 가산(P19_C 2.5%p)의 상한 근거
A16: P9_USD | B16: DayBasis | C16: 일수 기준(USD) | D16: 360 | E16: 일 | F16: 확인 | G16: 하나은행 환가료 공시 [G03 10] | H16: 2026-09-23 | I16: KRW·GBP·JPY 등은 365 | J16: https://www.kebhana.com/cms/rate/index.do?contentUrl=/cms/rate/wpfxd652_01i.do
A17: P9_KRW | B17: DayBasisKRW | C17: 일수 기준(KRW) | D17: 365 | E17: 일 | F17: 확인 | G17: 하나은행 환가료 공시 [G03 10] | H17: 2026-09-23 | J17: https://www.kebhana.com/cms/rate/index.do?contentUrl=/cms/rate/wpfxd652_01i.do
A18: P10 | B18: Fee_KRW | C18: 수출환어음 매입취급수수료 | D18: 20000 | E18: 원/건 | F18: 확인 | G18: 은행연합회 수출입수수료 비교공시 [G03 14] | H18: 2026-09-26 | I18: 하나·우리·KB(외화) 2만 원, IBK 면제 | J18: https://portal.kfb.or.kr/compare/commission_exchange_2.php
A19: P11 | B19: CollectFee | C19: 수출환어음 추심수수료 | D19: 0.001 | E19: 건당 비율 | F19: 확인 | G19: 은행연합회 수출입수수료 비교공시 [G03 14] | H19: 2026-09-26 | I19: 최저 1~2만·최고 3만 원(하나는 건당 2만 원) | J19: https://portal.kfb.or.kr/compare/commission_exchange_2.php
A20: P12 | B20: FactoringFee | C20: 국제팩토링 취급수수료(IBK) | D20: 0.004 | E20: 건당 비율 | F20: 확인 | G20: IBK 수출입 이용수수료 [G03 16] | H20: 2026-06-01 | I20: 추심 0.2%, 신용조회 건당 1만 원 | J20: https://www.ibk.co.kr/inform/detailFee.ibk?category=E&pageId=FM04010200
A21: P13_AC | B21: KS_Direct_AC | C21: K-SURE 다이렉트 선적후 수입자 지정형 A~C급 요율 | D21: 0.004 | E21: 건당 비율 | F21: 확인 | G21: 무역보험 제도안내 2026.8 PDF 23쪽 [G03 19] | H21: 2026-09-09 | I21: 수입자별 U$20만, 보상비율 95% | J21: https://www.ksure.or.kr/rh-kr/bbs/i-329/down.do?bbs_id=1014&atfile_sn=1&data_ty_cd=A&ntt_sn=38033
A22: P13_OTH | B22: KS_Direct_Oth | C22: K-SURE 다이렉트 선적후 수입자 지정형 그 외 등급 요율 | D22: 0.005 | E22: 건당 비율 | F22: 확인 | G22: 무역보험 제도안내 2026.8 PDF 23쪽 [G03 19] | H22: 2026-09-09 | I22: 수입자별 U$10만 | J22: https://www.ksure.or.kr/rh-kr/bbs/i-329/down.do?bbs_id=1014&atfile_sn=1&data_ty_cd=A&ntt_sn=38033
A23: P13_GEN | B23: KS_Direct_Gen | C23: K-SURE 다이렉트 선적후 일반형 요율 | D23: 0.006 | E23: 건당 비율 | F23: 확인 | G23: 무역보험 제도안내 2026.8 PDF 23쪽 [G03 19] | H23: 2026-09-09 | I23: 건별 U$5만·수출자별 U$10만 | J23: https://www.ksure.or.kr/rh-kr/bbs/i-329/down.do?bbs_id=1014&atfile_sn=1&data_ty_cd=A&ntt_sn=38033
A24: P14_LO | B24: KS_PlusLo | C24: K-SURE 중소중견Plus+ 무신용장(중소) 하한 | D24: 0.0082 | E24: 연율 | F24: 확인 | G24: 무역보험 제도안내 2026.8 PDF 26쪽 [G03 19] | H24: 2026-09-09 | I24: 책임금액 구간별 누진 | J24: https://www.ksure.or.kr/rh-kr/bbs/i-329/down.do?bbs_id=1014&atfile_sn=1&data_ty_cd=A&ntt_sn=38033
A25: P14_HI | B25: KS_PlusHi | C25: K-SURE 중소중견Plus+ 무신용장(중소) 상한 | D25: 0.0162 | E25: 연율 | F25: 확인 | G25: 무역보험 제도안내 2026.8 PDF 26쪽 [G03 19] | H25: 2026-09-09 | I25: 중견 1.020~2.520% | J25: https://www.ksure.or.kr/rh-kr/bbs/i-329/down.do?bbs_id=1014&atfile_sn=1&data_ty_cd=A&ntt_sn=38033
A26: P15 | B26: KS_PlusLC | C26: K-SURE 중소중견Plus+ 신용장 | D26: 0.0022 | E26: 연율 | F26: 확인 | G26: 무역보험 제도안내 2026.8 PDF 26쪽 [G03 19] | H26: 2026-09-09 | J26: https://www.ksure.or.kr/rh-kr/bbs/i-329/down.do?bbs_id=1014&atfile_sn=1&data_ty_cd=A&ntt_sn=38033
A27: P16 | B27: KS_Forfaiting | C27: 포페이팅 보험 | D27: 0.004 | E27: 연율 | F27: 확인 | G27: 무역보험 제도안내 2026.8 PDF 33쪽 [G03 19] | H27: 2026-09-09 | I27: 국가등급이 높을수록·개설은행 순자산이 클수록 저렴 | J27: https://www.ksure.or.kr/rh-kr/bbs/i-329/down.do?bbs_id=1014&atfile_sn=1&data_ty_cd=A&ntt_sn=38033
A28: P17_LO | B28: KS_GuarLo | C28: 수출신용보증(매입) 하한 | D28: 0.005 | E28: 연율 | F28: 확인 | G28: 무역보험 제도안내 2026.8 PDF 46쪽 [G03 19] | H28: 2026-09-09 | I28: 포괄매입 0.25~0.85%(48쪽) | J28: https://www.ksure.or.kr/rh-kr/bbs/i-329/down.do?bbs_id=1014&atfile_sn=1&data_ty_cd=A&ntt_sn=38033
A29: P17_HI | B29: KS_GuarHi | C29: 수출신용보증(매입) 상한 | D29: 0.025 | E29: 연율 | F29: 확인 | G29: 무역보험 제도안내 2026.8 PDF 46쪽 [G03 19] | H29: 2026-09-09 | J29: https://www.ksure.or.kr/rh-kr/bbs/i-329/down.do?bbs_id=1014&atfile_sn=1&data_ty_cd=A&ntt_sn=38033
A30: P18 | B30: Cov | C30: 보상비율(다이렉트 선적후) | D30: 0.95 | E30: 비율 | F30: 확인 | G30: 무역보험 제도안내 2026.8 PDF 23쪽 [G03 19] | H30: 2026-09-09 | I30: 단기수출보험 중소기업 부보율은 100% — 실습은 보수적으로 95% | J30: https://www.ksure.or.kr/rh-kr/bbs/i-329/down.do?bbs_id=1014&atfile_sn=1&data_ty_cd=A&ntt_sn=38033
A31: P19_S | B31: Spread_S | C31: 은행 가산금리 S | D31: 0.01 | E31: %p | F31: 가정 | G31: G03 P19 [가정] | I31: C는 P8 92일(2.49%p) 상한
A32: P19_A | B32: Spread_A | C32: 은행 가산금리 A | D32: 0.015 | E32: %p | F32: 가정 | G32: G03 P19 [가정]
A33: P19_B | B33: Spread_B | C33: 은행 가산금리 B | D33: 0.02 | E33: %p | F33: 가정 | G33: G03 P19 [가정]
A34: P19_C | B34: Spread_C | C34: 은행 가산금리 C | D34: 0.025 | E34: %p | F34: 가정 | G34: G03 P19 [가정]
A35: P20_S | B35: Prem_S | C35: K-SURE 보험료 S(90일 건당) | D35: 0.003 | E35: 건당 비율 | F35: 가정 | G35: G03 P20 [가정] — 요율표 비공개, P13~P15 앵커 | I35: 연환산 = 요율 × 365 ÷ 결제기간
A36: P20_A | B36: Prem_A | C36: K-SURE 보험료 A(90일 건당) | D36: 0.004 | E36: 건당 비율 | F36: 가정 | G36: G03 P20 [가정]
A37: P20_B | B37: Prem_B | C37: K-SURE 보험료 B(90일 건당) | D37: 0.005 | E37: 건당 비율 | F37: 가정 | G37: G03 P20 [가정]
A38: P20_C | B38: Prem_C | C38: K-SURE 보험료 C(90일 건당) | D38: 0.01 | E38: 건당 비율 | F38: 가정 | G38: G03 P20 [가정]
A39: P21_S | B39: PD_S | C39: 연 부도확률 S | D39: 0.005 | E39: 연율 | F39: 가정 | G39: G03 P21 [가정] — ICC 무역금융 부도율 참조
A40: P21_A | B40: PD_A | C40: 연 부도확률 A | D40: 0.015 | E40: 연율 | F40: 가정 | G40: G03 P21 [가정]
A41: P21_B | B41: PD_B | C41: 연 부도확률 B | D41: 0.04 | E41: 연율 | F41: 가정 | G41: G03 P21 [가정]
A42: P21_C | B42: PD_C | C42: 연 부도확률 C | D42: 0.1 | E42: 연율 | F42: 가정 | G42: G03 P21 [가정] — Atradius 아시아 B2B 대손 약 5% 참조
A43: P22 | B43: LGD | C43: 부도 시 손실률(무보험) | D43: 0.6 | E43: 비율 | F43: 가정 | G43: G03 P22 [가정] — K-SURE 추심수수료 10~20%·1년 후 회수율 급감
A44: P23 | B44: EarlyPay_2_10_30 | C44: 조기결제 할인 2/10 net 30 연환산 | D44: =0.02/0.98*360/20 | E44: 연율 | F44: 계산 | G44: 0.02 ÷ 0.98 × 360 ÷ 20 [G03 §2.5] | I44: 365일 기준 37.24% · 복리 44.59% | J44: https://taulia.com/glossary/what-is-dynamic-discounting/
A45: P24 | B45: Equity_USD | C45: 자기자본(가상 회사) | D45: 10000000 | E45: USD | F45: 교육용 가정 | G45: 03 Part2 §4.5 예시값(03 Part1 부록 B6 확정 필요) | I45: 🔵 자사 값으로 바꿔 해 찾기 다시 실행
A46: P25 | B46: Alpha | C46: 미부보 EL 예산 비율 α | D46: 0.03 | E46: 비율 | F46: 가정 | G46: G01 §2.5.1 방식⑦ · 여신관리규정 제16조 | I46: EL 예산 = 자기자본 × α
A47: P26_S | B47: s_S | C47: 자기 감당 한도 비율 S | D47: 0.05 | E47: 비율 | F47: 가정 | G47: G01 §2.5.1(방식⑧ 25%를 보수적으로 축소) | I47: Self = 자기자본 × s(g)
A48: P26_A | B48: s_A | C48: 자기 감당 한도 비율 A | D48: 0.03 | E48: 비율 | F48: 가정 | G48: G01 §2.5.1
A49: P26_B | B49: s_B | C49: 자기 감당 한도 비율 B | D49: 0.01 | E49: 비율 | F49: 가정 | G49: G01 §2.5.1
A50: P26_C | B50: s_C | C50: 자기 감당 한도 비율 C | D50: 0 | E50: 비율 | F50: 가정 | G50: G01 §2.5.1
A51: P27 | B51: Fed_Lo | C51: 연준 목표범위 하단 | D51: 0.0375 | E51: 연율 | F51: 확인 | G51: FOMC 성명 2026-09-16 [G03 4] | H51: 2026-09-16 | I51: +25bp(12:0) — 3.50~3.75% → 3.75~4.00% | J51: https://www.federalreserve.gov/newsevents/pressreleases/monetary20260916a.htm
A52: P28 | B52: Fed_Hi | C52: 연준 목표범위 상단 | D52: 0.04 | E52: 연율 | F52: 확인 | G52: FOMC 성명 2026-09-16 [G03 4] | H52: 2026-09-16 | J52: https://www.federalreserve.gov/newsevents/pressreleases/monetary20260916a.htm
A53: P29 | B53: Tenor | C53: 할인율 표 기준 기간 | D53: 90 | E53: 일 | F53: 교육용 가정 | G53: G03 §2.8 예제 | I53: 03_RateBuild 검산표(USD 100,000·90일)
A54: P30 | B54: Grace | C54: 필요한도 유예일 | D54: 15 | E54: 일 | F54: 가정 | G54: G01 방식⑤ · 여신관리규정 제13조 | I54: Need = 월평균 매출 × (결제기간 + 15) ÷ 30
A55: P31_A | B55: Cap_A | C55: 등급 상한 A | D55: 200000 | E55: USD | F55: 가정 | G55: K-SURE 다이렉트 A~C U$20만 앵커 [R01][spine §6] | I55: S는 상한 없이 Need
A56: P31_B | B56: Cap_B | C56: 등급 상한 B | D56: 100000 | E56: USD | F56: 가정 | G56: K-SURE 다이렉트 그 외 U$10만 앵커
A57: P31_C | B57: Cap_C_OA | C57: 등급 상한 C(외상) | D57: 0 | E57: USD | F57: 가정 | G57: G01 방식⑩ · 여신관리규정 제10조·제13조② — C는 선수금·L/C만
A58: P32 | B58: ShareCap_B | C58: B등급 한도 합 상한(총허용익스포저 대비) | D58: 0.3 | E58: 비율 | F58: 교육용 가정 | G58: 03 Part2 §4.5
A59: P33_02 | B59: CtryCap_02 | C59: 국가 한도율: OECD CRC 미분류·0~2 | D59: 0.2 | E59: 비율 | F59: 교육용 가정 | G59: 03 Part2 §4.5 · OECD CRC 2026-06-26 | I59: 총허용익스포저 대비
A60: P33_3 | B60: CtryCap_3 | C60: 국가 한도율: CRC 3 | D60: 0.12 | E60: 비율 | F60: 교육용 가정 | G60: 03 Part2 §4.5
A61: P33_45 | B61: CtryCap_45 | C61: 국가 한도율: CRC 4~5 | D61: 0.06 | E61: 비율 | F61: 교육용 가정 | G61: 03 Part2 §4.5
A62: P33_67 | B62: CtryCap_67 | C62: 국가 한도율: CRC 6~7 | D62: 0.03 | E62: 비율 | F62: 교육용 가정 | G62: 03 Part2 §4.5
A63: P34 | B63: TotalCapShare | C63: 총허용익스포저 = 상한 합 × 이 비율(10만 단위 반올림) | D63: 0.7 | E63: 비율 | F63: 교육용 가정 | G63: 03 Part2 §4.5 · G01 방식⑦ | I63: 70% → 총량 제약이 반드시 걸린다(우선순위가 생긴다)
A64: P35 | B64: Util | C64: 평균 한도 사용률 | D64: 0.7 | E64: 비율 | F64: 교육용 가정 | G64: 03 Part2 §4.5
A65: P36 | B65: GM | C65: 매출총이익률 | D65: 0.25 | E65: 비율 | F65: 교육용 가정 | G65: 03 Part2 §4.5
A66: P37 | B66: StratMin | C66: 전략 바이어 최소 한도(현행 한도 대비) | D66: 0.5 | E66: 비율 | F66: 교육용 가정 | G66: 03 Part2 §4.5
A67: P38 | B67: NoticeWarnDays | C67: K-SURE 통지 기한 임박 경보 일수 | D67: 10 | E67: 일 | F67: 교육용 가정 | G67: 03 Part2 §4.5
A68: P39 | B68: LGD_LC | C68: 신용장 거래 LGD | D68: 0.1 | E68: 비율 | F68: 교육용 가정 | G68: 은행 지급확약 — 서류 하자 등 잔여 위험만
A69: P40 | B69: Rho | C69: 몬테카를로 공통요인 상관 ρ | D69: 0 | E69: 비율 | F69: 교육용 가정 | G69: 03 Part2 §4.11 — 0 = 독립(Excel 기본) | I69: 🟣 0.2로 바꿔 꼬리위험 비교
A71: 워크북 전용(파일에 없는 값)
A72: W1 | B72: AsOf | C72: 기준일(조기경보·연체일 계산) | D72: 46295 | F72: 교육용 가정 | I72: 데이터 기준일
A73: W2 | B73: GradeRule | C73: 한도·PD에 쓰는 등급 규칙(t = Day3 정본 · quantile = 분위수 15/35/35/15) | D73: t | F73: 교육용 가정 | I73: 🔵 quantile로 바꿔 해 찾기 다시 실행 → 결과 비교
A74: W3 | B74: InsuranceType | C74: 수출통지 기한 기본 보험 유형(개별 / 포괄) | D74: 개별 | F74: 교육용 가정 | I74: 약관 제16조 — 회사별 설정
A75: W4 | B75: SaleWeek | C75: 매입 의뢰 주(07_Solver) | D75: 3 | F75: 교육용 가정 | I75: G03 §2.8 Step 4
A76: W5 | B76: Cash0 | C76: 기초현금(USD천, 06_WeeklyGap) | D76: 80 | F76: 교육용 가정 | I76: G03 §2.8 Step 4
A77: W6 | B77: CheckAmt | C77: 검산 채권 금액(USD, 03_RateBuild·05_NPV) | D77: 100000 | F77: 교육용 가정 | I77: G03 §2.8 Step 2

Sheet 02_Buyers
A1: buyer_id | B1: ref_date | C1: pd_30d | D1: pred_late | E1: threshold_used | F1: grade | G1: grade_rule | H1: rank_pct | I1: grade_quantile | J1: top_feature_1 | K1: top_contrib_1 | L1: top_feature_2 | M1: top_contrib_2 | N1: top_feature_3 | O1: top_contrib_3 | P1: top_reasons_ko | Q1: model_version | R1: buyer_name | S1: country_code | T1: currency | U1: payment_method | V1: terms_days | W1: ksure_insured | X1: ksure_limit_usd | Y1: monthly_sales_usd | Z1: open_ar_usd | AA1: overdue_amount_usd | AB1: current_limit_usd | AC1: oecd_crc | AD1: pd_annual_assumed | AE1: lgd_assumed | AF1: coverage_ratio | AG1: strategic_flag | AH1: bankruptcy_flag | AI1: buyer_type | AJ1: ▶ 계산 | AK1: grade_used | AL1: PD_g | AM1: PD_eff | AN1: LGD_i | AO1: cov_i | AP1: spread_g | AQ1: prem_g | AR1: r_unins | AS1: r_ins | AT1: r_i | AU1: ins_decision | AV1: need | AW1: cap | AX1: ins | AY1: self | AZ1: ship_hold | BA1: limit_scope | BB1: UB | BC1: LB | BD1: coef | BE1: elc | BF1: crc_band | BG1: el_now | BH1: fin_cost_now | BI1: risk_key
AK2: =IF($A2="","",IF(GradeRule="quantile",$I2,$F2)) | AL2: =IF($A2="","",CHOOSE(MATCH($AK2,{"S","A","B","C"},0),PD_S,PD_A,PD_B,PD_C)) | AM2: =IF($A2="","",IF($AH2=1,1,$AL2)) | AN2: =IF($A2="","",IF(OR($U2="LC_SIGHT",$U2="LC_USANCE"),LGD_LC,LGD)) | AO2: =IF($A2="","",IF($W2="Y",Cov,0)) | AP2: =IF($A2="","",CHOOSE(MATCH($AK2,{"S","A","B","C"},0),Spread_S,Spread_A,Spread_B,Spread_C)) | AQ2: =IF($A2="","",CHOOSE(MATCH($AK2,{"S","A","B","C"},0),Prem_S,Prem_A,Prem_B,Prem_C)) | AR2: =IF(OR($A2="",$V2<=0),"",TSOFR3M+$AP2+$AL2*$AN2) | AS2: =IF(OR($A2="",$V2<=0),"",TSOFR3M+$AP2+$AQ2*365/$V2+$AL2*$AN2*(1-Cov)) | AT2: =IF(OR($A2="",$V2<=0),"",IF($W2="Y",$AS2,$AR2)) | AU2: =IF(OR($A2="",$V2<=0),"",IF($AS2<$AR2,"부보 유리","무보험 유리")) | AV2: =IF($A2="","",$Y2*($V2+Grace)/30) | AW2: =IF($A2="","",CHOOSE(MATCH($AK2,{"S","A","B","C"},0),$AV2,Cap_A,Cap_B,Cap_C_OA)) | AX2: =IF($A2="","",IF($W2="Y",$X2,0)) | AY2: =IF($A2="","",Equity_USD*CHOOSE(MATCH($AK2,{"S","A","B","C"},0),s_S,s_A,s_B,s_C)) | AZ2: =IF($A2="","",'13_EarlyWarning'!$AH5) | BA2: =IF($A2="","",IF(OR($U2="LC_SIGHT",$U2="LC_USANCE",$U2="TT_ADV"),"대상 아님","대상")) | BB2: =IF($A2="","",IF(OR($BA2="대상 아님",$AZ2<>"",$AH2=1),0,MIN($AV2,$AW2,$AX2+$AY2))) | BC2: =IF($A2="","",IF($AG2=1,MIN(StratMin*$AB2,$BB2),0)) | BD2: =IF($A2="","",IF(OR($V2<=0,$BB2<=0),0,Util*(GM*365/$V2-$AT2))) | BE2: =IF($A2="","",Util*$AL2*$AN2*(1-$AO2)) | BF2: =IF($A2="","",IF($AC2="","0-2",IF($AC2<=2,"0-2",IF($AC2=3,"3",IF($AC2<=5,"4-5","6-7"))))) | BG2: =IF($A2="","",$Z2*$AM2*$AN2*(1-$AO2)) | BH2: =IF($A2="","",$Z2*(TSOFR3M+$AP2)*$V2/DayBasis) | BI2: =IF($A2="","",$C2+$Z2*1E-13)
AK3: =IF($A3="","",IF(GradeRule="quantile",$I3,$F3)) | AL3: =IF($A3="","",CHOOSE(MATCH($AK3,{"S","A","B","C"},0),PD_S,PD_A,PD_B,PD_C)) | AM3: =IF($A3="","",IF($AH3=1,1,$AL3)) | AN3: =IF($A3="","",IF(OR($U3="LC_SIGHT",$U3="LC_USANCE"),LGD_LC,LGD)) | AO3: =IF($A3="","",IF($W3="Y",Cov,0)) | AP3: =IF($A3="","",CHOOSE(MATCH($AK3,{"S","A","B","C"},0),Spread_S,Spread_A,Spread_B,Spread_C)) | AQ3: =IF($A3="","",CHOOSE(MATCH($AK3,{"S","A","B","C"},0),Prem_S,Prem_A,Prem_B,Prem_C)) | AR3: =IF(OR($A3="",$V3<=0),"",TSOFR3M+$AP3+$AL3*$AN3) | AS3: =IF(OR($A3="",$V3<=0),"",TSOFR3M+$AP3+$AQ3*365/$V3+$AL3*$AN3*(1-Cov)) | AT3: =IF(OR($A3="",$V3<=0),"",IF($W3="Y",$AS3,$AR3)) | AU3: =IF(OR($A3="",$V3<=0),"",IF($AS3<$AR3,"부보 유리","무보험 유리")) | AV3: =IF($A3="","",$Y3*($V3+Grace)/30) | AW3: =IF($A3="","",CHOOSE(MATCH($AK3,{"S","A","B","C"},0),$AV3,Cap_A,Cap_B,Cap_C_OA)) | AX3: =IF($A3="","",IF($W3="Y",$X3,0)) | AY3: =IF($A3="","",Equity_USD*CHOOSE(MATCH($AK3,{"S","A","B","C"},0),s_S,s_A,s_B,s_C)) | AZ3: =IF($A3="","",'13_EarlyWarning'!$AH6) | BA3: =IF($A3="","",IF(OR($U3="LC_SIGHT",$U3="LC_USANCE",$U3="TT_ADV"),"대상 아님","대상")) | BB3: =IF($A3="","",IF(OR($BA3="대상 아님",$AZ3<>"",$AH3=1),0,MIN($AV3,$AW3,$AX3+$AY3))) | BC3: =IF($A3="","",IF($AG3=1,MIN(StratMin*$AB3,$BB3),0)) | BD3: =IF($A3="","",IF(OR($V3<=0,$BB3<=0),0,Util*(GM*365/$V3-$AT3))) | BE3: =IF($A3="","",Util*$AL3*$AN3*(1-$AO3)) | BF3: =IF($A3="","",IF($AC3="","0-2",IF($AC3<=2,"0-2",IF($AC3=3,"3",IF($AC3<=5,"4-5","6-7"))))) | BG3: =IF($A3="","",$Z3*$AM3*$AN3*(1-$AO3)) | BH3: =IF($A3="","",$Z3*(TSOFR3M+$AP3)*$V3/DayBasis) | BI3: =IF($A3="","",$C3+$Z3*1E-13)
AK4: =IF($A4="","",IF(GradeRule="quantile",$I4,$F4)) | AL4: =IF($A4="","",CHOOSE(MATCH($AK4,{"S","A","B","C"},0),PD_S,PD_A,PD_B,PD_C)) | AM4: =IF($A4="","",IF($AH4=1,1,$AL4)) | AN4: =IF($A4="","",IF(OR($U4="LC_SIGHT",$U4="LC_USANCE"),LGD_LC,LGD)) | AO4: =IF($A4="","",IF($W4="Y",Cov,0)) | AP4: =IF($A4="","",CHOOSE(MATCH($AK4,{"S","A","B","C"},0),Spread_S,Spread_A,Spread_B,Spread_C)) | AQ4: =IF($A4="","",CHOOSE(MATCH($AK4,{"S","A","B","C"},0),Prem_S,Prem_A,Prem_B,Prem_C)) | AR4: =IF(OR($A4="",$V4<=0),"",TSOFR3M+$AP4+$AL4*$AN4) | AS4: =IF(OR($A4="",$V4<=0),"",TSOFR3M+$AP4+$AQ4*365/$V4+$AL4*$AN4*(1-Cov)) | AT4: =IF(OR($A4="",$V4<=0),"",IF($W4="Y",$AS4,$AR4)) | AU4: =IF(OR($A4="",$V4<=0),"",IF($AS4<$AR4,"부보 유리","무보험 유리")) | AV4: =IF($A4="","",$Y4*($V4+Grace)/30) | AW4: =IF($A4="","",CHOOSE(MATCH($AK4,{"S","A","B","C"},0),$AV4,Cap_A,Cap_B,Cap_C_OA)) | AX4: =IF($A4="","",IF($W4="Y",$X4,0)) | AY4: =IF($A4="","",Equity_USD*CHOOSE(MATCH($AK4,{"S","A","B","C"},0),s_S,s_A,s_B,s_C)) | AZ4: =IF($A4="","",'13_EarlyWarning'!$AH7) | BA4: =IF($A4="","",IF(OR($U4="LC_SIGHT",$U4="LC_USANCE",$U4="TT_ADV"),"대상 아님","대상")) | BB4: =IF($A4="","",IF(OR($BA4="대상 아님",$AZ4<>"",$AH4=1),0,MIN($AV4,$AW4,$AX4+$AY4))) | BC4: =IF($A4="","",IF($AG4=1,MIN(StratMin*$AB4,$BB4),0)) | BD4: =IF($A4="","",IF(OR($V4<=0,$BB4<=0),0,Util*(GM*365/$V4-$AT4))) | BE4: =IF($A4="","",Util*$AL4*$AN4*(1-$AO4)) | BF4: =IF($A4="","",IF($AC4="","0-2",IF($AC4<=2,"0-2",IF($AC4=3,"3",IF($AC4<=5,"4-5","6-7"))))) | BG4: =IF($A4="","",$Z4*$AM4*$AN4*(1-$AO4)) | BH4: =IF($A4="","",$Z4*(TSOFR3M+$AP4)*$V4/DayBasis) | BI4: =IF($A4="","",$C4+$Z4*1E-13)
AK5: =IF($A5="","",IF(GradeRule="quantile",$I5,$F5)) | AL5: =IF($A5="","",CHOOSE(MATCH($AK5,{"S","A","B","C"},0),PD_S,PD_A,PD_B,PD_C)) | AM5: =IF($A5="","",IF($AH5=1,1,$AL5)) | AN5: =IF($A5="","",IF(OR($U5="LC_SIGHT",$U5="LC_USANCE"),LGD_LC,LGD)) | AO5: =IF($A5="","",IF($W5="Y",Cov,0)) | AP5: =IF($A5="","",CHOOSE(MATCH($AK5,{"S","A","B","C"},0),Spread_S,Spread_A,Spread_B,Spread_C)) | AQ5: =IF($A5="","",CHOOSE(MATCH($AK5,{"S","A","B","C"},0),Prem_S,Prem_A,Prem_B,Prem_C)) | AR5: =IF(OR($A5="",$V5<=0),"",TSOFR3M+$AP5+$AL5*$AN5) | AS5: =IF(OR($A5="",$V5<=0),"",TSOFR3M+$AP5+$AQ5*365/$V5+$AL5*$AN5*(1-Cov)) | AT5: =IF(OR($A5="",$V5<=0),"",IF($W5="Y",$AS5,$AR5)) | AU5: =IF(OR($A5="",$V5<=0),"",IF($AS5<$AR5,"부보 유리","무보험 유리")) | AV5: =IF($A5="","",$Y5*($V5+Grace)/30) | AW5: =IF($A5="","",CHOOSE(MATCH($AK5,{"S","A","B","C"},0),$AV5,Cap_A,Cap_B,Cap_C_OA)) | AX5: =IF($A5="","",IF($W5="Y",$X5,0)) | AY5: =IF($A5="","",Equity_USD*CHOOSE(MATCH($AK5,{"S","A","B","C"},0),s_S,s_A,s_B,s_C)) | AZ5: =IF($A5="","",'13_EarlyWarning'!$AH8) | BA5: =IF($A5="","",IF(OR($U5="LC_SIGHT",$U5="LC_USANCE",$U5="TT_ADV"),"대상 아님","대상")) | BB5: =IF($A5="","",IF(OR($BA5="대상 아님",$AZ5<>"",$AH5=1),0,MIN($AV5,$AW5,$AX5+$AY5))) | BC5: =IF($A5="","",IF($AG5=1,MIN(StratMin*$AB5,$BB5),0)) | BD5: =IF($A5="","",IF(OR($V5<=0,$BB5<=0),0,Util*(GM*365/$V5-$AT5))) | BE5: =IF($A5="","",Util*$AL5*$AN5*(1-$AO5)) | BF5: =IF($A5="","",IF($AC5="","0-2",IF($AC5<=2,"0-2",IF($AC5=3,"3",IF($AC5<=5,"4-5","6-7"))))) | BG5: =IF($A5="","",$Z5*$AM5*$AN5*(1-$AO5)) | BH5: =IF($A5="","",$Z5*(TSOFR3M+$AP5)*$V5/DayBasis) | BI5: =IF($A5="","",$C5+$Z5*1E-13)
AK6: =IF($A6="","",IF(GradeRule="quantile",$I6,$F6)) | AL6: =IF($A6="","",CHOOSE(MATCH($AK6,{"S","A","B","C"},0),PD_S,PD_A,PD_B,PD_C)) | AM6: =IF($A6="","",IF($AH6=1,1,$AL6)) | AN6: =IF($A6="","",IF(OR($U6="LC_SIGHT",$U6="LC_USANCE"),LGD_LC,LGD)) | AO6: =IF($A6="","",IF($W6="Y",Cov,0)) | AP6: =IF($A6="","",CHOOSE(MATCH($AK6,{"S","A","B","C"},0),Spread_S,Spread_A,Spread_B,Spread_C)) | AQ6: =IF($A6="","",CHOOSE(MATCH($AK6,{"S","A","B","C"},0),Prem_S,Prem_A,Prem_B,Prem_C)) | AR6: =IF(OR($A6="",$V6<=0),"",TSOFR3M+$AP6+$AL6*$AN6) | AS6: =IF(OR($A6="",$V6<=0),"",TSOFR3M+$AP6+$AQ6*365/$V6+$AL6*$AN6*(1-Cov)) | AT6: =IF(OR($A6="",$V6<=0),"",IF($W6="Y",$AS6,$AR6)) | AU6: =IF(OR($A6="",$V6<=0),"",IF($AS6<$AR6,"부보 유리","무보험 유리")) | AV6: =IF($A6="","",$Y6*($V6+Grace)/30) | AW6: =IF($A6="","",CHOOSE(MATCH($AK6,{"S","A","B","C"},0),$AV6,Cap_A,Cap_B,Cap_C_OA)) | AX6: =IF($A6="","",IF($W6="Y",$X6,0)) | AY6: =IF($A6="","",Equity_USD*CHOOSE(MATCH($AK6,{"S","A","B","C"},0),s_S,s_A,s_B,s_C)) | AZ6: =IF($A6="","",'13_EarlyWarning'!$AH9) | BA6: =IF($A6="","",IF(OR($U6="LC_SIGHT",$U6="LC_USANCE",$U6="TT_ADV"),"대상 아님","대상")) | BB6: =IF($A6="","",IF(OR($BA6="대상 아님",$AZ6<>"",$AH6=1),0,MIN($AV6,$AW6,$AX6+$AY6))) | BC6: =IF($A6="","",IF($AG6=1,MIN(StratMin*$AB6,$BB6),0)) | BD6: =IF($A6="","",IF(OR($V6<=0,$BB6<=0),0,Util*(GM*365/$V6-$AT6))) | BE6: =IF($A6="","",Util*$AL6*$AN6*(1-$AO6)) | BF6: =IF($A6="","",IF($AC6="","0-2",IF($AC6<=2,"0-2",IF($AC6=3,"3",IF($AC6<=5,"4-5","6-7"))))) | BG6: =IF($A6="","",$Z6*$AM6*$AN6*(1-$AO6)) | BH6: =IF($A6="","",$Z6*(TSOFR3M+$AP6)*$V6/DayBasis) | BI6: =IF($A6="","",$C6+$Z6*1E-13)
AK7: =IF($A7="","",IF(GradeRule="quantile",$I7,$F7)) | AL7: =IF($A7="","",CHOOSE(MATCH($AK7,{"S","A","B","C"},0),PD_S,PD_A,PD_B,PD_C)) | AM7: =IF($A7="","",IF($AH7=1,1,$AL7)) | AN7: =IF($A7="","",IF(OR($U7="LC_SIGHT",$U7="LC_USANCE"),LGD_LC,LGD)) | AO7: =IF($A7="","",IF($W7="Y",Cov,0)) | AP7: =IF($A7="","",CHOOSE(MATCH($AK7,{"S","A","B","C"},0),Spread_S,Spread_A,Spread_B,Spread_C)) | AQ7: =IF($A7="","",CHOOSE(MATCH($AK7,{"S","A","B","C"},0),Prem_S,Prem_A,Prem_B,Prem_C)) | AR7: =IF(OR($A7="",$V7<=0),"",TSOFR3M+$AP7+$AL7*$AN7) | AS7: =IF(OR($A7="",$V7<=0),"",TSOFR3M+$AP7+$AQ7*365/$V7+$AL7*$AN7*(1-Cov)) | AT7: =IF(OR($A7="",$V7<=0),"",IF($W7="Y",$AS7,$AR7)) | AU7: =IF(OR($A7="",$V7<=0),"",IF($AS7<$AR7,"부보 유리","무보험 유리")) | AV7: =IF($A7="","",$Y7*($V7+Grace)/30) | AW7: =IF($A7="","",CHOOSE(MATCH($AK7,{"S","A","B","C"},0),$AV7,Cap_A,Cap_B,Cap_C_OA)) | AX7: =IF($A7="","",IF($W7="Y",$X7,0)) | AY7: =IF($A7="","",Equity_USD*CHOOSE(MATCH($AK7,{"S","A","B","C"},0),s_S,s_A,s_B,s_C)) | AZ7: =IF($A7="","",'13_EarlyWarning'!$AH10) | BA7: =IF($A7="","",IF(OR($U7="LC_SIGHT",$U7="LC_USANCE",$U7="TT_ADV"),"대상 아님","대상")) | BB7: =IF($A7="","",IF(OR($BA7="대상 아님",$AZ7<>"",$AH7=1),0,MIN($AV7,$AW7,$AX7+$AY7))) | BC7: =IF($A7="","",IF($AG7=1,MIN(StratMin*$AB7,$BB7),0)) | BD7: =IF($A7="","",IF(OR($V7<=0,$BB7<=0),0,Util*(GM*365/$V7-$AT7))) | BE7: =IF($A7="","",Util*$AL7*$AN7*(1-$AO7)) | BF7: =IF($A7="","",IF($AC7="","0-2",IF($AC7<=2,"0-2",IF($AC7=3,"3",IF($AC7<=5,"4-5","6-7"))))) | BG7: =IF($A7="","",$Z7*$AM7*$AN7*(1-$AO7)) | BH7: =IF($A7="","",$Z7*(TSOFR3M+$AP7)*$V7/DayBasis) | BI7: =IF($A7="","",$C7+$Z7*1E-13)
AK8: =IF($A8="","",IF(GradeRule="quantile",$I8,$F8)) | AL8: =IF($A8="","",CHOOSE(MATCH($AK8,{"S","A","B","C"},0),PD_S,PD_A,PD_B,PD_C)) | AM8: =IF($A8="","",IF($AH8=1,1,$AL8)) | AN8: =IF($A8="","",IF(OR($U8="LC_SIGHT",$U8="LC_USANCE"),LGD_LC,LGD)) | AO8: =IF($A8="","",IF($W8="Y",Cov,0)) | AP8: =IF($A8="","",CHOOSE(MATCH($AK8,{"S","A","B","C"},0),Spread_S,Spread_A,Spread_B,Spread_C)) | AQ8: =IF($A8="","",CHOOSE(MATCH($AK8,{"S","A","B","C"},0),Prem_S,Prem_A,Prem_B,Prem_C)) | AR8: =IF(OR($A8="",$V8<=0),"",TSOFR3M+$AP8+$AL8*$AN8) | AS8: =IF(OR($A8="",$V8<=0),"",TSOFR3M+$AP8+$AQ8*365/$V8+$AL8*$AN8*(1-Cov)) | AT8: =IF(OR($A8="",$V8<=0),"",IF($W8="Y",$AS8,$AR8)) | AU8: =IF(OR($A8="",$V8<=0),"",IF($AS8<$AR8,"부보 유리","무보험 유리")) | AV8: =IF($A8="","",$Y8*($V8+Grace)/30) | AW8: =IF($A8="","",CHOOSE(MATCH($AK8,{"S","A","B","C"},0),$AV8,Cap_A,Cap_B,Cap_C_OA)) | AX8: =IF($A8="","",IF($W8="Y",$X8,0)) | AY8: =IF($A8="","",Equity_USD*CHOOSE(MATCH($AK8,{"S","A","B","C"},0),s_S,s_A,s_B,s_C)) | AZ8: =IF($A8="","",'13_EarlyWarning'!$AH11) | BA8: =IF($A8="","",IF(OR($U8="LC_SIGHT",$U8="LC_USANCE",$U8="TT_ADV"),"대상 아님","대상")) | BB8: =IF($A8="","",IF(OR($BA8="대상 아님",$AZ8<>"",$AH8=1),0,MIN($AV8,$AW8,$AX8+$AY8))) | BC8: =IF($A8="","",IF($AG8=1,MIN(StratMin*$AB8,$BB8),0)) | BD8: =IF($A8="","",IF(OR($V8<=0,$BB8<=0),0,Util*(GM*365/$V8-$AT8))) | BE8: =IF($A8="","",Util*$AL8*$AN8*(1-$AO8)) | BF8: =IF($A8="","",IF($AC8="","0-2",IF($AC8<=2,"0-2",IF($AC8=3,"3",IF($AC8<=5,"4-5","6-7"))))) | BG8: =IF($A8="","",$Z8*$AM8*$AN8*(1-$AO8)) | BH8: =IF($A8="","",$Z8*(TSOFR3M+$AP8)*$V8/DayBasis) | BI8: =IF($A8="","",$C8+$Z8*1E-13)
AK9: =IF($A9="","",IF(GradeRule="quantile",$I9,$F9)) | AL9: =IF($A9="","",CHOOSE(MATCH($AK9,{"S","A","B","C"},0),PD_S,PD_A,PD_B,PD_C)) | AM9: =IF($A9="","",IF($AH9=1,1,$AL9)) | AN9: =IF($A9="","",IF(OR($U9="LC_SIGHT",$U9="LC_USANCE"),LGD_LC,LGD)) | AO9: =IF($A9="","",IF($W9="Y",Cov,0)) | AP9: =IF($A9="","",CHOOSE(MATCH($AK9,{"S","A","B","C"},0),Spread_S,Spread_A,Spread_B,Spread_C)) | AQ9: =IF($A9="","",CHOOSE(MATCH($AK9,{"S","A","B","C"},0),Prem_S,Prem_A,Prem_B,Prem_C)) | AR9: =IF(OR($A9="",$V9<=0),"",TSOFR3M+$AP9+$AL9*$AN9) | AS9: =IF(OR($A9="",$V9<=0),"",TSOFR3M+$AP9+$AQ9*365/$V9+$AL9*$AN9*(1-Cov)) | AT9: =IF(OR($A9="",$V9<=0),"",IF($W9="Y",$AS9,$AR9)) | AU9: =IF(OR($A9="",$V9<=0),"",IF($AS9<$AR9,"부보 유리","무보험 유리")) | AV9: =IF($A9="","",$Y9*($V9+Grace)/30) | AW9: =IF($A9="","",CHOOSE(MATCH($AK9,{"S","A","B","C"},0),$AV9,Cap_A,Cap_B,Cap_C_OA)) | AX9: =IF($A9="","",IF($W9="Y",$X9,0)) | AY9: =IF($A9="","",Equity_USD*CHOOSE(MATCH($AK9,{"S","A","B","C"},0),s_S,s_A,s_B,s_C)) | AZ9: =IF($A9="","",'13_EarlyWarning'!$AH12) | BA9: =IF($A9="","",IF(OR($U9="LC_SIGHT",$U9="LC_USANCE",$U9="TT_ADV"),"대상 아님","대상")) | BB9: =IF($A9="","",IF(OR($BA9="대상 아님",$AZ9<>"",$AH9=1),0,MIN($AV9,$AW9,$AX9+$AY9))) | BC9: =IF($A9="","",IF($AG9=1,MIN(StratMin*$AB9,$BB9),0)) | BD9: =IF($A9="","",IF(OR($V9<=0,$BB9<=0),0,Util*(GM*365/$V9-$AT9))) | BE9: =IF($A9="","",Util*$AL9*$AN9*(1-$AO9)) | BF9: =IF($A9="","",IF($AC9="","0-2",IF($AC9<=2,"0-2",IF($AC9=3,"3",IF($AC9<=5,"4-5","6-7"))))) | BG9: =IF($A9="","",$Z9*$AM9*$AN9*(1-$AO9)) | BH9: =IF($A9="","",$Z9*(TSOFR3M+$AP9)*$V9/DayBasis) | BI9: =IF($A9="","",$C9+$Z9*1E-13)
AK10: =IF($A10="","",IF(GradeRule="quantile",$I10,$F10)) | AL10: =IF($A10="","",CHOOSE(MATCH($AK10,{"S","A","B","C"},0),PD_S,PD_A,PD_B,PD_C)) | AM10: =IF($A10="","",IF($AH10=1,1,$AL10)) | AN10: =IF($A10="","",IF(OR($U10="LC_SIGHT",$U10="LC_USANCE"),LGD_LC,LGD)) | AO10: =IF($A10="","",IF($W10="Y",Cov,0)) | AP10: =IF($A10="","",CHOOSE(MATCH($AK10,{"S","A","B","C"},0),Spread_S,Spread_A,Spread_B,Spread_C)) | AQ10: =IF($A10="","",CHOOSE(MATCH($AK10,{"S","A","B","C"},0),Prem_S,Prem_A,Prem_B,Prem_C)) | AR10: =IF(OR($A10="",$V10<=0),"",TSOFR3M+$AP10+$AL10*$AN10) | AS10: =IF(OR($A10="",$V10<=0),"",TSOFR3M+$AP10+$AQ10*365/$V10+$AL10*$AN10*(1-Cov)) | AT10: =IF(OR($A10="",$V10<=0),"",IF($W10="Y",$AS10,$AR10)) | AU10: =IF(OR($A10="",$V10<=0),"",IF($AS10<$AR10,"부보 유리","무보험 유리")) | AV10: =IF($A10="","",$Y10*($V10+Grace)/30) | AW10: =IF($A10="","",CHOOSE(MATCH($AK10,{"S","A","B","C"},0),$AV10,Cap_A,Cap_B,Cap_C_OA)) | AX10: =IF($A10="","",IF($W10="Y",$X10,0)) | AY10: =IF($A10="","",Equity_USD*CHOOSE(MATCH($AK10,{"S","A","B","C"},0),s_S,s_A,s_B,s_C)) | AZ10: =IF($A10="","",'13_EarlyWarning'!$AH13) | BA10: =IF($A10="","",IF(OR($U10="LC_SIGHT",$U10="LC_USANCE",$U10="TT_ADV"),"대상 아님","대상")) | BB10: =IF($A10="","",IF(OR($BA10="대상 아님",$AZ10<>"",$AH10=1),0,MIN($AV10,$AW10,$AX10+$AY10))) | BC10: =IF($A10="","",IF($AG10=1,MIN(StratMin*$AB10,$BB10),0)) | BD10: =IF($A10="","",IF(OR($V10<=0,$BB10<=0),0,Util*(GM*365/$V10-$AT10))) | BE10: =IF($A10="","",Util*$AL10*$AN10*(1-$AO10)) | BF10: =IF($A10="","",IF($AC10="","0-2",IF($AC10<=2,"0-2",IF($AC10=3,"3",IF($AC10<=5,"4-5","6-7"))))) | BG10: =IF($A10="","",$Z10*$AM10*$AN10*(1-$AO10)) | BH10: =IF($A10="","",$Z10*(TSOFR3M+$AP10)*$V10/DayBasis) | BI10: =IF($A10="","",$C10+$Z10*1E-13)
AK11: =IF($A11="","",IF(GradeRule="quantile",$I11,$F11)) | AL11: =IF($A11="","",CHOOSE(MATCH($AK11,{"S","A","B","C"},0),PD_S,PD_A,PD_B,PD_C)) | AM11: =IF($A11="","",IF($AH11=1,1,$AL11)) | AN11: =IF($A11="","",IF(OR($U11="LC_SIGHT",$U11="LC_USANCE"),LGD_LC,LGD)) | AO11: =IF($A11="","",IF($W11="Y",Cov,0)) | AP11: =IF($A11="","",CHOOSE(MATCH($AK11,{"S","A","B","C"},0),Spread_S,Spread_A,Spread_B,Spread_C)) | AQ11: =IF($A11="","",CHOOSE(MATCH($AK11,{"S","A","B","C"},0),Prem_S,Prem_A,Prem_B,Prem_C)) | AR11: =IF(OR($A11="",$V11<=0),"",TSOFR3M+$AP11+$AL11*$AN11) | AS11: =IF(OR($A11="",$V11<=0),"",TSOFR3M+$AP11+$AQ11*365/$V11+$AL11*$AN11*(1-Cov)) | AT11: =IF(OR($A11="",$V11<=0),"",IF($W11="Y",$AS11,$AR11)) | AU11: =IF(OR($A11="",$V11<=0),"",IF($AS11<$AR11,"부보 유리","무보험 유리")) | AV11: =IF($A11="","",$Y11*($V11+Grace)/30) | AW11: =IF($A11="","",CHOOSE(MATCH($AK11,{"S","A","B","C"},0),$AV11,Cap_A,Cap_B,Cap_C_OA)) | AX11: =IF($A11="","",IF($W11="Y",$X11,0)) | AY11: =IF($A11="","",Equity_USD*CHOOSE(MATCH($AK11,{"S","A","B","C"},0),s_S,s_A,s_B,s_C)) | AZ11: =IF($A11="","",'13_EarlyWarning'!$AH14) | BA11: =IF($A11="","",IF(OR($U11="LC_SIGHT",$U11="LC_USANCE",$U11="TT_ADV"),"대상 아님","대상")) | BB11: =IF($A11="","",IF(OR($BA11="대상 아님",$AZ11<>"",$AH11=1),0,MIN($AV11,$AW11,$AX11+$AY11))) | BC11: =IF($A11="","",IF($AG11=1,MIN(StratMin*$AB11,$BB11),0)) | BD11: =IF($A11="","",IF(OR($V11<=0,$BB11<=0),0,Util*(GM*365/$V11-$AT11))) | BE11: =IF($A11="","",Util*$AL11*$AN11*(1-$AO11)) | BF11: =IF($A11="","",IF($AC11="","0-2",IF($AC11<=2,"0-2",IF($AC11=3,"3",IF($AC11<=5,"4-5","6-7"))))) | BG11: =IF($A11="","",$Z11*$AM11*$AN11*(1-$AO11)) | BH11: =IF($A11="","",$Z11*(TSOFR3M+$AP11)*$V11/DayBasis) | BI11: =IF($A11="","",$C11+$Z11*1E-13)
AK12: =IF($A12="","",IF(GradeRule="quantile",$I12,$F12)) | AL12: =IF($A12="","",CHOOSE(MATCH($AK12,{"S","A","B","C"},0),PD_S,PD_A,PD_B,PD_C)) | AM12: =IF($A12="","",IF($AH12=1,1,$AL12)) | AN12: =IF($A12="","",IF(OR($U12="LC_SIGHT",$U12="LC_USANCE"),LGD_LC,LGD)) | AO12: =IF($A12="","",IF($W12="Y",Cov,0)) | AP12: =IF($A12="","",CHOOSE(MATCH($AK12,{"S","A","B","C"},0),Spread_S,Spread_A,Spread_B,Spread_C)) | AQ12: =IF($A12="","",CHOOSE(MATCH($AK12,{"S","A","B","C"},0),Prem_S,Prem_A,Prem_B,Prem_C)) | AR12: =IF(OR($A12="",$V12<=0),"",TSOFR3M+$AP12+$AL12*$AN12) | AS12: =IF(OR($A12="",$V12<=0),"",TSOFR3M+$AP12+$AQ12*365/$V12+$AL12*$AN12*(1-Cov)) | AT12: =IF(OR($A12="",$V12<=0),"",IF($W12="Y",$AS12,$AR12)) | AU12: =IF(OR($A12="",$V12<=0),"",IF($AS12<$AR12,"부보 유리","무보험 유리")) | AV12: =IF($A12="","",$Y12*($V12+Grace)/30) | AW12: =IF($A12="","",CHOOSE(MATCH($AK12,{"S","A","B","C"},0),$AV12,Cap_A,Cap_B,Cap_C_OA)) | AX12: =IF($A12="","",IF($W12="Y",$X12,0)) | AY12: =IF($A12="","",Equity_USD*CHOOSE(MATCH($AK12,{"S","A","B","C"},0),s_S,s_A,s_B,s_C)) | AZ12: =IF($A12="","",'13_EarlyWarning'!$AH15) | BA12: =IF($A12="","",IF(OR($U12="LC_SIGHT",$U12="LC_USANCE",$U12="TT_ADV"),"대상 아님","대상")) | BB12: =IF($A12="","",IF(OR($BA12="대상 아님",$AZ12<>"",$AH12=1),0,MIN($AV12,$AW12,$AX12+$AY12))) | BC12: =IF($A12="","",IF($AG12=1,MIN(StratMin*$AB12,$BB12),0)) | BD12: =IF($A12="","",IF(OR($V12<=0,$BB12<=0),0,Util*(GM*365/$V12-$AT12))) | BE12: =IF($A12="","",Util*$AL12*$AN12*(1-$AO12)) | BF12: =IF($A12="","",IF($AC12="","0-2",IF($AC12<=2,"0-2",IF($AC12=3,"3",IF($AC12<=5,"4-5","6-7"))))) | BG12: =IF($A12="","",$Z12*$AM12*$AN12*(1-$AO12)) | BH12: =IF($A12="","",$Z12*(TSOFR3M+$AP12)*$V12/DayBasis) | BI12: =IF($A12="","",$C12+$Z12*1E-13)
AK13: =IF($A13="","",IF(GradeRule="quantile",$I13,$F13)) | AL13: =IF($A13="","",CHOOSE(MATCH($AK13,{"S","A","B","C"},0),PD_S,PD_A,PD_B,PD_C)) | AM13: =IF($A13="","",IF($AH13=1,1,$AL13)) | AN13: =IF($A13="","",IF(OR($U13="LC_SIGHT",$U13="LC_USANCE"),LGD_LC,LGD)) | AO13: =IF($A13="","",IF($W13="Y",Cov,0)) | AP13: =IF($A13="","",CHOOSE(MATCH($AK13,{"S","A","B","C"},0),Spread_S,Spread_A,Spread_B,Spread_C)) | AQ13: =IF($A13="","",CHOOSE(MATCH($AK13,{"S","A","B","C"},0),Prem_S,Prem_A,Prem_B,Prem_C)) | AR13: =IF(OR($A13="",$V13<=0),"",TSOFR3M+$AP13+$AL13*$AN13) | AS13: =IF(OR($A13="",$V13<=0),"",TSOFR3M+$AP13+$AQ13*365/$V13+$AL13*$AN13*(1-Cov)) | AT13: =IF(OR($A13="",$V13<=0),"",IF($W13="Y",$AS13,$AR13)) | AU13: =IF(OR($A13="",$V13<=0),"",IF($AS13<$AR13,"부보 유리","무보험 유리")) | AV13: =IF($A13="","",$Y13*($V13+Grace)/30) | AW13: =IF($A13="","",CHOOSE(MATCH($AK13,{"S","A","B","C"},0),$AV13,Cap_A,Cap_B,Cap_C_OA)) | AX13: =IF($A13="","",IF($W13="Y",$X13,0)) | AY13: =IF($A13="","",Equity_USD*CHOOSE(MATCH($AK13,{"S","A","B","C"},0),s_S,s_A,s_B,s_C)) | AZ13: =IF($A13="","",'13_EarlyWarning'!$AH16) | BA13: =IF($A13="","",IF(OR($U13="LC_SIGHT",$U13="LC_USANCE",$U13="TT_ADV"),"대상 아님","대상")) | BB13: =IF($A13="","",IF(OR($BA13="대상 아님",$AZ13<>"",$AH13=1),0,MIN($AV13,$AW13,$AX13+$AY13))) | BC13: =IF($A13="","",IF($AG13=1,MIN(StratMin*$AB13,$BB13),0)) | BD13: =IF($A13="","",IF(OR($V13<=0,$BB13<=0),0,Util*(GM*365/$V13-$AT13))) | BE13: =IF($A13="","",Util*$AL13*$AN13*(1-$AO13)) | BF13: =IF($A13="","",IF($AC13="","0-2",IF($AC13<=2,"0-2",IF($AC13=3,"3",IF($AC13<=5,"4-5","6-7"))))) | BG13: =IF($A13="","",$Z13*$AM13*$AN13*(1-$AO13)) | BH13: =IF($A13="","",$Z13*(TSOFR3M+$AP13)*$V13/DayBasis) | BI13: =IF($A13="","",$C13+$Z13*1E-13)
... AK151: =IF($A151="","",IF(GradeRule="quantile",$I151,$F151)) | AL151: =IF($A151="","",CHOOSE(MATCH($AK151,{"S","A","B","C"},0),PD_S,PD_A,PD_B,PD_C)) | AM151: =IF($A151="","",IF($AH151=1,1,$AL151)) | AN151: =IF($A151="","",IF(OR($U151="LC_SIGHT",$U151="LC_USANCE"),LGD_LC,LGD)) | AO151: =IF($A151="","",IF($W151="Y",Cov,0)) | AP151: =IF($A151="","",CHOOSE(MATCH($AK151,{"S","A","B","C"},0),Spread_S,Spread_A,Spread_B,Spread_C)) | AQ151: =IF($A151="","",CHOOSE(MATCH($AK151,{"S","A","B","C"},0),Prem_S,Prem_A,Prem_B,Prem_C)) | AR151: =IF(OR($A151="",$V151<=0),"",TSOFR3M+$AP151+$AL151*$AN151) | AS151: =IF(OR($A151="",$V151<=0),"",TSOFR3M+$AP151+$AQ151*365/$V151+$AL151*$AN151*(1-Cov)) | AT151: =IF(OR($A151="",$V151<=0),"",IF($W151="Y",$AS151,$AR151)) | AU151: =IF(OR($A151="",$V151<=0),"",IF($AS151<$AR151,"부보 유리","무보험 유리")) | AV151: =IF($A151="","",$Y151*($V151+Grace)/30) | AW151: =IF($A151="","",CHOOSE(MATCH($AK151,{"S","A","B","C"},0),$AV151,Cap_A,Cap_B,Cap_C_OA)) | AX151: =IF($A151="","",IF($W151="Y",$X151,0)) | AY151: =IF($A151="","",Equity_USD*CHOOSE(MATCH($AK151,{"S","A","B","C"},0),s_S,s_A,s_B,s_C)) | AZ151: =IF($A151="","",'13_EarlyWarning'!$AH154) | BA151: =IF($A151="","",IF(OR($U151="LC_SIGHT",$U151="LC_USANCE",$U151="TT_ADV"),"대상 아님","대상")) | BB151: =IF($A151="","",IF(OR($BA151="대상 아님",$AZ151<>"",$AH151=1),0,MIN($AV151,$AW151,$AX151+$AY151))) | BC151: =IF($A151="","",IF($AG151=1,MIN(StratMin*$AB151,$BB151),0)) | BD151: =IF($A151="","",IF(OR($V151<=0,$BB151<=0),0,Util*(GM*365/$V151-$AT151))) | BE151: =IF($A151="","",Util*$AL151*$AN151*(1-$AO151)) | BF151: =IF($A151="","",IF($AC151="","0-2",IF($AC151<=2,"0-2",IF($AC151=3,"3",IF($AC151<=5,"4-5","6-7"))))) | BG151: =IF($A151="","",$Z151*$AM151*$AN151*(1-$AO151)) | BH151: =IF($A151="","",$Z151*(TSOFR3M+$AP151)*$V151/DayBasis) | BI151: =IF($A151="","",$C151+$Z151*1E-13)

Sheet 03_RateBuild
A1: 03_RateBuild — 등급별 위험조정 할인율·NPV 검산(G03 §2.8)
A2: r 무보험 = TSOFR3M + Spread_g + PD_g × LGD · r 부보 = TSOFR3M + Spread_g + Prem_g × 365 ÷ Tenor + PD_g × LGD × (1 − Cov) · NPV = 금액 ÷ (1 + r × Tenor ÷ 360)
A3: 손익분기: '보험료(연환산) < PD × LGD × 보상비율'이면 부보가 유리 → A와 B 사이(G03)
A4: 검산 금액(USD) | B4: =CheckAmt | C4: 기간(일) | D4: =Tenor
A5: 등급 | B5: 자금비용 B+s | C5: EL(연) PD×LGD | D5: r 무보험 | E5: NPV 무보험 | F5: 보험료 연환산 | G5: r 부보 | H5: NPV 부보 | I5: 판정 | J5: PD 90일 | K5: G03 r 무보험 | L5: G03 NPV 무보험 | M5: G03 r 부보 | N5: G03 NPV 부보 | O5: 일치?
A6: S | B6: =TSOFR3M+Spread_S | C6: =PD_S*LGD | D6: =B6+C6 | E6: =$B$4/(1+D6*$D$4/DayBasis) | F6: =Prem_S*365/$D$4 | G6: =B6+F6+C6*(1-Cov) | H6: =$B$4/(1+G6*$D$4/DayBasis) | I6: =IF(G6<D6,"부보 유리","무보험 유리") | J6: =1-(1-PD_S)^($D$4/365) | K6: 0.0535 | L6: 98681 | M6: 0.0628 | N6: 98455 | O6: =IF(AND(ABS(D6-K6)<=0.0001,ABS(E6-L6)<=1,ABS(G6-M6)<=0.0001,ABS(H6-N6)<=1),"✔","✘ 확인")
A7: A | B7: =TSOFR3M+Spread_A | C7: =PD_A*LGD | D7: =B7+C7 | E7: =$B$4/(1+D7*$D$4/DayBasis) | F7: =Prem_A*365/$D$4 | G7: =B7+F7+C7*(1-Cov) | H7: =$B$4/(1+G7*$D$4/DayBasis) | I7: =IF(G7<D7,"부보 유리","무보험 유리") | J7: =1-(1-PD_A)^($D$4/365) | K7: 0.0645 | L7: 98414 | M7: 0.0722 | N7: 98228 | O7: =IF(AND(ABS(D7-K7)<=0.0001,ABS(E7-L7)<=1,ABS(G7-M7)<=0.0001,ABS(H7-N7)<=1),"✔","✘ 확인")
A8: B | B8: =TSOFR3M+Spread_B | C8: =PD_B*LGD | D8: =B8+C8 | E8: =$B$4/(1+D8*$D$4/DayBasis) | F8: =Prem_B*365/$D$4 | G8: =B8+F8+C8*(1-Cov) | H8: =$B$4/(1+G8*$D$4/DayBasis) | I8: =IF(G8<D8,"부보 유리","무보험 유리") | J8: =1-(1-PD_B)^($D$4/365) | K8: 0.0845 | L8: 97932 | M8: 0.0819 | N8: 97992 | O8: =IF(AND(ABS(D8-K8)<=0.0001,ABS(E8-L8)<=1,ABS(G8-M8)<=0.0001,ABS(H8-N8)<=1),"✔","✘ 확인")
A9: C | B9: =TSOFR3M+Spread_C | C9: =PD_C*LGD | D9: =B9+C9 | E9: =$B$4/(1+D9*$D$4/DayBasis) | F9: =Prem_C*365/$D$4 | G9: =B9+F9+C9*(1-Cov) | H9: =$B$4/(1+G9*$D$4/DayBasis) | I9: =IF(G9<D9,"부보 유리","무보험 유리") | J9: =1-(1-PD_C)^($D$4/365) | K9: 0.1255 | L9: 96959 | M9: 0.109 | N9: 97347 | O9: =IF(AND(ABS(D9-K9)<=0.0001,ABS(E9-L9)<=1,ABS(G9-M9)<=0.0001,ABS(H9-N9)<=1),"✔","✘ 확인")
A11: 메모 | B11: G03 표의 A등급 r 부보 7.22%는 반올림 차이(정확히 7.214%) — NPV 98,228달러는 일치. 일치 판정 허용폭: 금리 0.01%p · NPV 1달러
A13: 차트용 구성(%)
A14: 등급 | B14: ① Term SOFR 3M | C14: ② 은행 가산 | D14: ③ 보험료(연환산) | E14: ④ EL(PD×LGD×(1−Cov))
A15: S | B15: =TSOFR3M | C15: =Spread_S | D15: =F6 | E15: =C6*(1-Cov)
A16: A | B16: =TSOFR3M | C16: =Spread_A | D16: =F7 | E16: =C7*(1-Cov)
A17: B | B17: =TSOFR3M | C17: =Spread_B | D17: =F8 | E17: =C8*(1-Cov)
A18: C | B18: =TSOFR3M | C18: =Spread_C | D18: =F9 | E18: =C9*(1-Cov)

Sheet 04_AR_Ledger
A1: 04_AR_Ledger — G03 예제 원장 R1~R7(🔵 유동성 갭 입력, 금액 USD천)
A2: 기대입금 주 = 만기 주 + ROUNDUP(평균지연 ÷ 7) · 기대입금액 = 금액 × (1 − PD 90일) · 매각 단위비용 = r 부보 × (만기 주 − 매입 주) × 7 + 지연일) ÷ 360
A4: 채권ID | B4: 등급 | C4: 금액(USD천) | D4: 만기 주 | E4: 평균지연(일) | F4: PD 연 | G4: PD 90일 | H4: 기대입금 주 | I4: 기대입금액 | J4: r 부보 | K4: 매각 시 잔존일 | L4: 단위비용 | M4: 매각 가능(1)
A5: R1 | B5: S | C5: 120 | D5: 2 | E5: 0 | F5: =CHOOSE(MATCH(B5,{"S","A","B","C"},0),PD_S,PD_A,PD_B,PD_C) | G5: =1-(1-F5)^(Tenor/365) | H5: =D5+ROUNDUP(E5/7,0) | I5: =C5*(1-G5) | J5: =INDEX('03_RateBuild'!$G$6:$G$9,MATCH(B5,'03_RateBuild'!$A$6:$A$9,0)) | K5: =(D5-SaleWeek)*7+E5 | L5: =J5*K5/DayBasis | M5: =IF(H5>SaleWeek,1,0)
A6: R2 | B6: A | C6: 100 | D6: 3 | E6: 3 | F6: =CHOOSE(MATCH(B6,{"S","A","B","C"},0),PD_S,PD_A,PD_B,PD_C) | G6: =1-(1-F6)^(Tenor/365) | H6: =D6+ROUNDUP(E6/7,0) | I6: =C6*(1-G6) | J6: =INDEX('03_RateBuild'!$G$6:$G$9,MATCH(B6,'03_RateBuild'!$A$6:$A$9,0)) | K6: =(D6-SaleWeek)*7+E6 | L6: =J6*K6/DayBasis | M6: =IF(H6>SaleWeek,1,0)
A7: R3 | B7: B | C7: 90 | D7: 4 | E7: 10 | F7: =CHOOSE(MATCH(B7,{"S","A","B","C"},0),PD_S,PD_A,PD_B,PD_C) | G7: =1-(1-F7)^(Tenor/365) | H7: =D7+ROUNDUP(E7/7,0) | I7: =C7*(1-G7) | J7: =INDEX('03_RateBuild'!$G$6:$G$9,MATCH(B7,'03_RateBuild'!$A$6:$A$9,0)) | K7: =(D7-SaleWeek)*7+E7 | L7: =J7*K7/DayBasis | M7: =IF(H7>SaleWeek,1,0)
A8: R4 | B8: C | C8: 80 | D8: 5 | E8: 25 | F8: =CHOOSE(MATCH(B8,{"S","A","B","C"},0),PD_S,PD_A,PD_B,PD_C) | G8: =1-(1-F8)^(Tenor/365) | H8: =D8+ROUNDUP(E8/7,0) | I8: =C8*(1-G8) | J8: =INDEX('03_RateBuild'!$G$6:$G$9,MATCH(B8,'03_RateBuild'!$A$6:$A$9,0)) | K8: =(D8-SaleWeek)*7+E8 | L8: =J8*K8/DayBasis | M8: =IF(H8>SaleWeek,1,0)
A9: R5 | B9: A | C9: 110 | D9: 6 | E9: 3 | F9: =CHOOSE(MATCH(B9,{"S","A","B","C"},0),PD_S,PD_A,PD_B,PD_C) | G9: =1-(1-F9)^(Tenor/365) | H9: =D9+ROUNDUP(E9/7,0) | I9: =C9*(1-G9) | J9: =INDEX('03_RateBuild'!$G$6:$G$9,MATCH(B9,'03_RateBuild'!$A$6:$A$9,0)) | K9: =(D9-SaleWeek)*7+E9 | L9: =J9*K9/DayBasis | M9: =IF(H9>SaleWeek,1,0)
A10: R6 | B10: S | C10: 130 | D10: 7 | E10: 0 | F10: =CHOOSE(MATCH(B10,{"S","A","B","C"},0),PD_S,PD_A,PD_B,PD_C) | G10: =1-(1-F10)^(Tenor/365) | H10: =D10+ROUNDUP(E10/7,0) | I10: =C10*(1-G10) | J10: =INDEX('03_RateBuild'!$G$6:$G$9,MATCH(B10,'03_RateBuild'!$A$6:$A$9,0)) | K10: =(D10-SaleWeek)*7+E10 | L10: =J10*K10/DayBasis | M10: =IF(H10>SaleWeek,1,0)
A11: R7 | B11: B | C11: 70 | D11: 8 | E11: 10 | F11: =CHOOSE(MATCH(B11,{"S","A","B","C"},0),PD_S,PD_A,PD_B,PD_C) | G11: =1-(1-F11)^(Tenor/365) | H11: =D11+ROUNDUP(E11/7,0) | I11: =C11*(1-G11) | J11: =INDEX('03_RateBuild'!$G$6:$G$9,MATCH(B11,'03_RateBuild'!$A$6:$A$9,0)) | K11: =(D11-SaleWeek)*7+E11 | L11: =J11*K11/DayBasis | M11: =IF(H11>SaleWeek,1,0)

Sheet 05_NPV
A1: 05_NPV — 은행 견적 대조(하나은행 고시) + 바이어별 채권 NPV
A2: 환가료 = 금액 × 환가료율 × 일수 ÷ 360(USD) · 실효 = (환가료 + 수수료) ÷ 금액 × 360 ÷ 일수 [G03 §2.8 Step 3]
A4: 매입 금액(USD) | B4: =CheckAmt
A5: 일수 | B5: 92
A6: 환가료율(하나 92일) | B6: =Hana92
A7: 환가료(USD) | B7: =B4*B6*B5/DayBasis | C7: 1669.54 | D7: =IF(ABS(B7-C7)<0.01,"✔ G03 일치","✘")
A8: 매입수수료(USD) = ₩20,000 ÷ 원/달러 | B8: =Fee_KRW/USDKRW
A9: 합계(USD) | B9: =B7+B8
A10: 연환산 실효비용 | B10: =B9/B4*DayBasis/B5 | C10: 0.0659 | D10: =IF(ABS(B10-C10)<0.00005,"✔ G03 일치","✘")
A11: 31일이면 환가료(USD) | B11: =B4*Hana31*31/DayBasis | C11: 495.01 | D11: =IF(ABS(B11-C11)<0.01,"✔ G03 일치","✘")
A12: 읽는 법 | B12: 실효 6.59%는 A~B등급 '자금비용 + EL' 구간(6.45~8.45%) 안 → 은행 고시 환가료 = 우대 전 상한
A14: buyer_id | B14: 등급 | C14: 미결 잔액(USD) | D14: 결제기간(일) | E14: r 무보험 | F14: r 부보 | G14: NPV 무보험 | H14: NPV 부보 | I14: 부보 판정 | J14: 현재 부보 | K14: 판정과 다름
A15: =IF('02_Buyers'!$A2="","",'02_Buyers'!$A2) | B15: =IF($A15="","",'02_Buyers'!$AK2) | C15: =IF($A15="","",'02_Buyers'!$Z2) | D15: =IF($A15="","",'02_Buyers'!$V2) | E15: =IF($A15="","",'02_Buyers'!$AR2) | F15: =IF($A15="","",'02_Buyers'!$AS2) | G15: =IF(OR($A15="",$E15=""),"",$C15/(1+$E15*$D15/DayBasis)) | H15: =IF(OR($A15="",$F15=""),"",$C15/(1+$F15*$D15/DayBasis)) | I15: =IF($A15="","",'02_Buyers'!$AU2) | J15: =IF($A15="","",'02_Buyers'!$W2) | K15: =IF(OR($A15="",$I15=""),"",IF(OR(AND($I15="부보 유리",$J15="N"),AND($I15="무보험 유리",$J15="Y")),"검토",""))
A16: =IF('02_Buyers'!$A3="","",'02_Buyers'!$A3) | B16: =IF($A16="","",'02_Buyers'!$AK3) | C16: =IF($A16="","",'02_Buyers'!$Z3) | D16: =IF($A16="","",'02_Buyers'!$V3) | E16: =IF($A16="","",'02_Buyers'!$AR3) | F16: =IF($A16="","",'02_Buyers'!$AS3) | G16: =IF(OR($A16="",$E16=""),"",$C16/(1+$E16*$D16/DayBasis)) | H16: =IF(OR($A16="",$F16=""),"",$C16/(1+$F16*$D16/DayBasis)) | I16: =IF($A16="","",'02_Buyers'!$AU3) | J16: =IF($A16="","",'02_Buyers'!$W3) | K16: =IF(OR($A16="",$I16=""),"",IF(OR(AND($I16="부보 유리",$J16="N"),AND($I16="무보험 유리",$J16="Y")),"검토",""))
A17: =IF('02_Buyers'!$A4="","",'02_Buyers'!$A4) | B17: =IF($A17="","",'02_Buyers'!$AK4) | C17: =IF($A17="","",'02_Buyers'!$Z4) | D17: =IF($A17="","",'02_Buyers'!$V4) | E17: =IF($A17="","",'02_Buyers'!$AR4) | F17: =IF($A17="","",'02_Buyers'!$AS4) | G17: =IF(OR($A17="",$E17=""),"",$C17/(1+$E17*$D17/DayBasis)) | H17: =IF(OR($A17="",$F17=""),"",$C17/(1+$F17*$D17/DayBasis)) | I17: =IF($A17="","",'02_Buyers'!$AU4) | J17: =IF($A17="","",'02_Buyers'!$W4) | K17: =IF(OR($A17="",$I17=""),"",IF(OR(AND($I17="부보 유리",$J17="N"),AND($I17="무보험 유리",$J17="Y")),"검토",""))
A18: =IF('02_Buyers'!$A5="","",'02_Buyers'!$A5) | B18: =IF($A18="","",'02_Buyers'!$AK5) | C18: =IF($A18="","",'02_Buyers'!$Z5) | D18: =IF($A18="","",'02_Buyers'!$V5) | E18: =IF($A18="","",'02_Buyers'!$AR5) | F18: =IF($A18="","",'02_Buyers'!$AS5) | G18: =IF(OR($A18="",$E18=""),"",$C18/(1+$E18*$D18/DayBasis)) | H18: =IF(OR($A18="",$F18=""),"",$C18/(1+$F18*$D18/DayBasis)) | I18: =IF($A18="","",'02_Buyers'!$AU5) | J18: =IF($A18="","",'02_Buyers'!$W5) | K18: =IF(OR($A18="",$I18=""),"",IF(OR(AND($I18="부보 유리",$J18="N"),AND($I18="무보험 유리",$J18="Y")),"검토",""))
A19: =IF('02_Buyers'!$A6="","",'02_Buyers'!$A6) | B19: =IF($A19="","",'02_Buyers'!$AK6) | C19: =IF($A19="","",'02_Buyers'!$Z6) | D19: =IF($A19="","",'02_Buyers'!$V6) | E19: =IF($A19="","",'02_Buyers'!$AR6) | F19: =IF($A19="","",'02_Buyers'!$AS6) | G19: =IF(OR($A19="",$E19=""),"",$C19/(1+$E19*$D19/DayBasis)) | H19: =IF(OR($A19="",$F19=""),"",$C19/(1+$F19*$D19/DayBasis)) | I19: =IF($A19="","",'02_Buyers'!$AU6) | J19: =IF($A19="","",'02_Buyers'!$W6) | K19: =IF(OR($A19="",$I19=""),"",IF(OR(AND($I19="부보 유리",$J19="N"),AND($I19="무보험 유리",$J19="Y")),"검토",""))
A20: =IF('02_Buyers'!$A7="","",'02_Buyers'!$A7) | B20: =IF($A20="","",'02_Buyers'!$AK7) | C20: =IF($A20="","",'02_Buyers'!$Z7) | D20: =IF($A20="","",'02_Buyers'!$V7) | E20: =IF($A20="","",'02_Buyers'!$AR7) | F20: =IF($A20="","",'02_Buyers'!$AS7) | G20: =IF(OR($A20="",$E20=""),"",$C20/(1+$E20*$D20/DayBasis)) | H20: =IF(OR($A20="",$F20=""),"",$C20/(1+$F20*$D20/DayBasis)) | I20: =IF($A20="","",'02_Buyers'!$AU7) | J20: =IF($A20="","",'02_Buyers'!$W7) | K20: =IF(OR($A20="",$I20=""),"",IF(OR(AND($I20="부보 유리",$J20="N"),AND($I20="무보험 유리",$J20="Y")),"검토",""))
A21: =IF('02_Buyers'!$A8="","",'02_Buyers'!$A8) | B21: =IF($A21="","",'02_Buyers'!$AK8) | C21: =IF($A21="","",'02_Buyers'!$Z8) | D21: =IF($A21="","",'02_Buyers'!$V8) | E21: =IF($A21="","",'02_Buyers'!$AR8) | F21: =IF($A21="","",'02_Buyers'!$AS8) | G21: =IF(OR($A21="",$E21=""),"",$C21/(1+$E21*$D21/DayBasis)) | H21: =IF(OR($A21="",$F21=""),"",$C21/(1+$F21*$D21/DayBasis)) | I21: =IF($A21="","",'02_Buyers'!$AU8) | J21: =IF($A21="","",'02_Buyers'!$W8) | K21: =IF(OR($A21="",$I21=""),"",IF(OR(AND($I21="부보 유리",$J21="N"),AND($I21="무보험 유리",$J21="Y")),"검토",""))
A22: =IF('02_Buyers'!$A9="","",'02_Buyers'!$A9) | B22: =IF($A22="","",'02_Buyers'!$AK9) | C22: =IF($A22="","",'02_Buyers'!$Z9) | D22: =IF($A22="","",'02_Buyers'!$V9) | E22: =IF($A22="","",'02_Buyers'!$AR9) | F22: =IF($A22="","",'02_Buyers'!$AS9) | G22: =IF(OR($A22="",$E22=""),"",$C22/(1+$E22*$D22/DayBasis)) | H22: =IF(OR($A22="",$F22=""),"",$C22/(1+$F22*$D22/DayBasis)) | I22: =IF($A22="","",'02_Buyers'!$AU9) | J22: =IF($A22="","",'02_Buyers'!$W9) | K22: =IF(OR($A22="",$I22=""),"",IF(OR(AND($I22="부보 유리",$J22="N"),AND($I22="무보험 유리",$J22="Y")),"검토",""))
A23: =IF('02_Buyers'!$A10="","",'02_Buyers'!$A10) | B23: =IF($A23="","",'02_Buyers'!$AK10) | C23: =IF($A23="","",'02_Buyers'!$Z10) | D23: =IF($A23="","",'02_Buyers'!$V10) | E23: =IF($A23="","",'02_Buyers'!$AR10) | F23: =IF($A23="","",'02_Buyers'!$AS10) | G23: =IF(OR($A23="",$E23=""),"",$C23/(1+$E23*$D23/DayBasis)) | H23: =IF(OR($A23="",$F23=""),"",$C23/(1+$F23*$D23/DayBasis)) | I23: =IF($A23="","",'02_Buyers'!$AU10) | J23: =IF($A23="","",'02_Buyers'!$W10) | K23: =IF(OR($A23="",$I23=""),"",IF(OR(AND($I23="부보 유리",$J23="N"),AND($I23="무보험 유리",$J23="Y")),"검토",""))
A24: =IF('02_Buyers'!$A11="","",'02_Buyers'!$A11) | B24: =IF($A24="","",'02_Buyers'!$AK11) | C24: =IF($A24="","",'02_Buyers'!$Z11) | D24: =IF($A24="","",'02_Buyers'!$V11) | E24: =IF($A24="","",'02_Buyers'!$AR11) | F24: =IF($A24="","",'02_Buyers'!$AS11) | G24: =IF(OR($A24="",$E24=""),"",$C24/(1+$E24*$D24/DayBasis)) | H24: =IF(OR($A24="",$F24=""),"",$C24/(1+$F24*$D24/DayBasis)) | I24: =IF($A24="","",'02_Buyers'!$AU11) | J24: =IF($A24="","",'02_Buyers'!$W11) | K24: =IF(OR($A24="",$I24=""),"",IF(OR(AND($I24="부보 유리",$J24="N"),AND($I24="무보험 유리",$J24="Y")),"검토",""))
A25: =IF('02_Buyers'!$A12="","",'02_Buyers'!$A12) | B25: =IF($A25="","",'02_Buyers'!$AK12) | C25: =IF($A25="","",'02_Buyers'!$Z12) | D25: =IF($A25="","",'02_Buyers'!$V12) | E25: =IF($A25="","",'02_Buyers'!$AR12) | F25: =IF($A25="","",'02_Buyers'!$AS12) | G25: =IF(OR($A25="",$E25=""),"",$C25/(1+$E25*$D25/DayBasis)) | H25: =IF(OR($A25="",$F25=""),"",$C25/(1+$F25*$D25/DayBasis)) | I25: =IF($A25="","",'02_Buyers'!$AU12) | J25: =IF($A25="","",'02_Buyers'!$W12) | K25: =IF(OR($A25="",$I25=""),"",IF(OR(AND($I25="부보 유리",$J25="N"),AND($I25="무보험 유리",$J25="Y")),"검토",""))
A26: =IF('02_Buyers'!$A13="","",'02_Buyers'!$A13) | B26: =IF($A26="","",'02_Buyers'!$AK13) | C26: =IF($A26="","",'02_Buyers'!$Z13) | D26: =IF($A26="","",'02_Buyers'!$V13) | E26: =IF($A26="","",'02_Buyers'!$AR13) | F26: =IF($A26="","",'02_Buyers'!$AS13) | G26: =IF(OR($A26="",$E26=""),"",$C26/(1+$E26*$D26/DayBasis)) | H26: =IF(OR($A26="",$F26=""),"",$C26/(1+$F26*$D26/DayBasis)) | I26: =IF($A26="","",'02_Buyers'!$AU13) | J26: =IF($A26="","",'02_Buyers'!$W13) | K26: =IF(OR($A26="",$I26=""),"",IF(OR(AND($I26="부보 유리",$J26="N"),AND($I26="무보험 유리",$J26="Y")),"검토",""))
... A164: =IF('02_Buyers'!$A151="","",'02_Buyers'!$A151) | B164: =IF($A164="","",'02_Buyers'!$AK151) | C164: =IF($A164="","",'02_Buyers'!$Z151) | D164: =IF($A164="","",'02_Buyers'!$V151) | E164: =IF($A164="","",'02_Buyers'!$AR151) | F164: =IF($A164="","",'02_Buyers'!$AS151) | G164: =IF(OR($A164="",$E164=""),"",$C164/(1+$E164*$D164/DayBasis)) | H164: =IF(OR($A164="",$F164=""),"",$C164/(1+$F164*$D164/DayBasis)) | I164: =IF($A164="","",'02_Buyers'!$AU151) | J164: =IF($A164="","",'02_Buyers'!$W151) | K164: =IF(OR($A164="",$I164=""),"",IF(OR(AND($I164="부보 유리",$J164="N"),AND($I164="무보험 유리",$J164="Y")),"검토",""))

Sheet 06_WeeklyGap
A1: 06_WeeklyGap — 8주 유동성 갭(USD천, G03 §2.8 Step 4)
A2: 누적현금(조치 전) = 기초현금 + Σ(기대입금 − 지출) · 조치 후 = 조치 전 + 매각 대금(매입 주부터) − 매각으로 빠진 기대입금 · 정답 체크: W5 최저 −150.5
A4: 주 | B4: 1 | C4: 2 | D4: 3 | E4: 4 | F4: 5 | G4: 6 | H4: 7 | I4: 8
A5: 기대입금 | B5: =SUMIFS('04_AR_Ledger'!$I$5:$I$11,'04_AR_Ledger'!$H$5:$H$11,B$4) | C5: =SUMIFS('04_AR_Ledger'!$I$5:$I$11,'04_AR_Ledger'!$H$5:$H$11,C$4) | D5: =SUMIFS('04_AR_Ledger'!$I$5:$I$11,'04_AR_Ledger'!$H$5:$H$11,D$4) | E5: =SUMIFS('04_AR_Ledger'!$I$5:$I$11,'04_AR_Ledger'!$H$5:$H$11,E$4) | F5: =SUMIFS('04_AR_Ledger'!$I$5:$I$11,'04_AR_Ledger'!$H$5:$H$11,F$4) | G5: =SUMIFS('04_AR_Ledger'!$I$5:$I$11,'04_AR_Ledger'!$H$5:$H$11,G$4) | H5: =SUMIFS('04_AR_Ledger'!$I$5:$I$11,'04_AR_Ledger'!$H$5:$H$11,H$4) | I5: =SUMIFS('04_AR_Ledger'!$I$5:$I$11,'04_AR_Ledger'!$H$5:$H$11,I$4)
A6: 지출 | B6: 70 | C6: 70 | D6: 70 | E6: 170 | F6: 70 | G6: 70 | H6: 70 | I6: 70
A7: 순현금 | B7: =B5-B6 | C7: =C5-C6 | D7: =D5-D6 | E7: =E5-E6 | F7: =F5-F6 | G7: =G5-G6 | H7: =H5-H6 | I7: =I5-I6
A8: 누적현금(조치 전) | B8: =Cash0+B7 | C8: =B8+C7 | D8: =C8+D7 | E8: =D8+E7 | F8: =E8+F7 | G8: =F8+G7 | H8: =G8+H7 | I8: =H8+I7
A9: 매각 대금(07) | B9: =IF(B$4>=SaleWeek,SUMPRODUCT('07_Solver'!$H$6:$H$12,'04_AR_Ledger'!$C$5:$C$11,1-'04_AR_Ledger'!$L$5:$L$11),0) | C9: =IF(C$4>=SaleWeek,SUMPRODUCT('07_Solver'!$H$6:$H$12,'04_AR_Ledger'!$C$5:$C$11,1-'04_AR_Ledger'!$L$5:$L$11),0) | D9: =IF(D$4>=SaleWeek,SUMPRODUCT('07_Solver'!$H$6:$H$12,'04_AR_Ledger'!$C$5:$C$11,1-'04_AR_Ledger'!$L$5:$L$11),0) | E9: =IF(E$4>=SaleWeek,SUMPRODUCT('07_Solver'!$H$6:$H$12,'04_AR_Ledger'!$C$5:$C$11,1-'04_AR_Ledger'!$L$5:$L$11),0) | F9: =IF(F$4>=SaleWeek,SUMPRODUCT('07_Solver'!$H$6:$H$12,'04_AR_Ledger'!$C$5:$C$11,1-'04_AR_Ledger'!$L$5:$L$11),0) | G9: =IF(G$4>=SaleWeek,SUMPRODUCT('07_Solver'!$H$6:$H$12,'04_AR_Ledger'!$C$5:$C$11,1-'04_AR_Ledger'!$L$5:$L$11),0) | H9: =IF(H$4>=SaleWeek,SUMPRODUCT('07_Solver'!$H$6:$H$12,'04_AR_Ledger'!$C$5:$C$11,1-'04_AR_Ledger'!$L$5:$L$11),0) | I9: =IF(I$4>=SaleWeek,SUMPRODUCT('07_Solver'!$H$6:$H$12,'04_AR_Ledger'!$C$5:$C$11,1-'04_AR_Ledger'!$L$5:$L$11),0)
A10: 빠진 기대입금(07) | B10: =SUMPRODUCT('07_Solver'!$H$6:$H$12,'04_AR_Ledger'!$C$5:$C$11,1-'04_AR_Ledger'!$G$5:$G$11,('04_AR_Ledger'!$H$5:$H$11<=B$4)*1) | C10: =SUMPRODUCT('07_Solver'!$H$6:$H$12,'04_AR_Ledger'!$C$5:$C$11,1-'04_AR_Ledger'!$G$5:$G$11,('04_AR_Ledger'!$H$5:$H$11<=C$4)*1) | D10: =SUMPRODUCT('07_Solver'!$H$6:$H$12,'04_AR_Ledger'!$C$5:$C$11,1-'04_AR_Ledger'!$G$5:$G$11,('04_AR_Ledger'!$H$5:$H$11<=D$4)*1) | E10: =SUMPRODUCT('07_Solver'!$H$6:$H$12,'04_AR_Ledger'!$C$5:$C$11,1-'04_AR_Ledger'!$G$5:$G$11,('04_AR_Ledger'!$H$5:$H$11<=E$4)*1) | F10: =SUMPRODUCT('07_Solver'!$H$6:$H$12,'04_AR_Ledger'!$C$5:$C$11,1-'04_AR_Ledger'!$G$5:$G$11,('04_AR_Ledger'!$H$5:$H$11<=F$4)*1) | G10: =SUMPRODUCT('07_Solver'!$H$6:$H$12,'04_AR_Ledger'!$C$5:$C$11,1-'04_AR_Ledger'!$G$5:$G$11,('04_AR_Ledger'!$H$5:$H$11<=G$4)*1) | H10: =SUMPRODUCT('07_Solver'!$H$6:$H$12,'04_AR_Ledger'!$C$5:$C$11,1-'04_AR_Ledger'!$G$5:$G$11,('04_AR_Ledger'!$H$5:$H$11<=H$4)*1) | I10: =SUMPRODUCT('07_Solver'!$H$6:$H$12,'04_AR_Ledger'!$C$5:$C$11,1-'04_AR_Ledger'!$G$5:$G$11,('04_AR_Ledger'!$H$5:$H$11<=I$4)*1)
A11: 누적현금(조치 후) | B11: =B8+B9-B10 | C11: =C8+C9-C10 | D11: =D8+D9-D10 | E11: =E8+E9-E10 | F11: =F8+F9-F10 | G11: =G8+G9-G10 | H11: =H8+H9-H10 | I11: =I8+I9-I10
A13: 최저 누적현금(조치 전) | B13: =MIN(B8:I8) | C13: -150.5 | D13: =IF(ABS(B13-C13)<0.05,"✔ G03 일치","✘")
A14: 최저 누적현금(조치 후) | B14: =MIN(B11:I11)
A15: 호라이즌 밖 기대입금(W9·W10) | B15: =SUMIFS('04_AR_Ledger'!$I$5:$I$11,'04_AR_Ledger'!$H$5:$H$11,">8")

Sheet 07_Solver
A1: 07_Solver — 최소비용 매각(🔵 해 찾기 모델 저장됨: 목표 $D$15 최소 · 변수 $H$6:$H$12 · 제약 2줄)
A2: 결정변수 x = 매각 비율(0~1). 비용 = Σ x × 금액 × 단위비용(r 부보 × 잔존일 ÷ 360). 제약: x ≤ 상한(매각 가능 × C급 허용), 06 누적현금(조치 후) ≥ 0
A3: 정답 체크(G03): 최소비용 약 USD 886 — W3에 R3 19.2 · R5 99.8 · R7 32.4천 매입 의뢰. 'C급 허용' = 0으로 바꿔도 같은 해(C급 R4는 원래 안 판다)
A4: C급 매각 허용(1/0) | B4: 1
A5: 채권ID | B5: 등급 | C5: 금액(USD천) | D5: 단위비용 | E5: 매각 가능 | F5: C급 허용 | G5: x 상한 | H5: x(결정변수) | I5: 매각액(USD천) | J5: 비용(USD천)
A6: ='04_AR_Ledger'!A5 | B6: ='04_AR_Ledger'!B5 | C6: ='04_AR_Ledger'!C5 | D6: ='04_AR_Ledger'!L5 | E6: ='04_AR_Ledger'!M5 | F6: =IF(B6="C",$B$4,1) | G6: =E6*F6 | H6: 0 | I6: =H6*C6 | J6: =I6*D6
A7: ='04_AR_Ledger'!A6 | B7: ='04_AR_Ledger'!B6 | C7: ='04_AR_Ledger'!C6 | D7: ='04_AR_Ledger'!L6 | E7: ='04_AR_Ledger'!M6 | F7: =IF(B7="C",$B$4,1) | G7: =E7*F7 | H7: 0 | I7: =H7*C7 | J7: =I7*D7
A8: ='04_AR_Ledger'!A7 | B8: ='04_AR_Ledger'!B7 | C8: ='04_AR_Ledger'!C7 | D8: ='04_AR_Ledger'!L7 | E8: ='04_AR_Ledger'!M7 | F8: =IF(B8="C",$B$4,1) | G8: =E8*F8 | H8: 0 | I8: =H8*C8 | J8: =I8*D8
A9: ='04_AR_Ledger'!A8 | B9: ='04_AR_Ledger'!B8 | C9: ='04_AR_Ledger'!C8 | D9: ='04_AR_Ledger'!L8 | E9: ='04_AR_Ledger'!M8 | F9: =IF(B9="C",$B$4,1) | G9: =E9*F9 | H9: 0 | I9: =H9*C9 | J9: =I9*D9
A10: ='04_AR_Ledger'!A9 | B10: ='04_AR_Ledger'!B9 | C10: ='04_AR_Ledger'!C9 | D10: ='04_AR_Ledger'!L9 | E10: ='04_AR_Ledger'!M9 | F10: =IF(B10="C",$B$4,1) | G10: =E10*F10 | H10: 0 | I10: =H10*C10 | J10: =I10*D10
A11: ='04_AR_Ledger'!A10 | B11: ='04_AR_Ledger'!B10 | C11: ='04_AR_Ledger'!C10 | D11: ='04_AR_Ledger'!L10 | E11: ='04_AR_Ledger'!M10 | F11: =IF(B11="C",$B$4,1) | G11: =E11*F11 | H11: 0 | I11: =H11*C11 | J11: =I11*D11
A12: ='04_AR_Ledger'!A11 | B12: ='04_AR_Ledger'!B11 | C12: ='04_AR_Ledger'!C11 | D12: ='04_AR_Ledger'!L11 | E12: ='04_AR_Ledger'!M11 | F12: =IF(B12="C",$B$4,1) | G12: =E12*F12 | H12: 0 | I12: =H12*C12 | J12: =I12*D12
A14: 제약: 누적현금(조치 후) W1~W8 ≥ 0 | B14: ='06_WeeklyGap'!B11 | C14: ='06_WeeklyGap'!C11 | D14: ='06_WeeklyGap'!D11 | E14: ='06_WeeklyGap'!E11 | F14: ='06_WeeklyGap'!F11 | G14: ='06_WeeklyGap'!G11 | H14: ='06_WeeklyGap'!H11 | I14: ='06_WeeklyGap'!I11
A15: 총 할인비용(USD천) — 목표(최소) | D15: =SUMPRODUCT(H6:H12,C6:C12,D6:D12)
A16: 총 할인비용(USD) | D16: =D15*1000 | E16: 886 | F16: =IF(ABS(D16-E16)<1,"✔ G03 일치(약 886)","해 찾기 실행 전/확인")
A18: 해 찾기 입력표
A19: 목표 설정: $D$15 → 최소값
A20: 변수 셀 변경: $H$6:$H$12
A21: 제약 1: $H$6:$H$12 <= $G$6:$G$12
A22: 제약 2: $B$14:$I$14 >= 0
A23: '제한되지 않는 변수를 음이 아닌 수로' ✔ · 해법: 단순 LP

Sheet 08_Sensitivity
A1: 08_Sensitivity — 할인율·매각비용 민감도(현재 07 매각안 기준)
A2: 케이스별 r 부보 = (TSOFR3M + Δ) + Spread_g + Prem_g × 365 ÷ Tenor + MIN(1, PD_g × 배수) × LGD × (1 − Cov)
A3: 매각 조합은 07의 x 그대로(케이스마다 해 찾기를 다시 돌리면 조합이 바뀔 수 있다 — 🔵 실험). PD 배수는 할인율에만 반영(기대입금은 기준 PD)
A4: 등급별 x·금액·잔존일 합(07)
A5: 등급 | B5: Σ x·금액·잔존일
A6: S | B6: =SUMPRODUCT(('04_AR_Ledger'!$B$5:$B$11="S")*'07_Solver'!$H$6:$H$12*'04_AR_Ledger'!$C$5:$C$11*'04_AR_Ledger'!$K$5:$K$11)
A7: A | B7: =SUMPRODUCT(('04_AR_Ledger'!$B$5:$B$11="A")*'07_Solver'!$H$6:$H$12*'04_AR_Ledger'!$C$5:$C$11*'04_AR_Ledger'!$K$5:$K$11)
A8: B | B8: =SUMPRODUCT(('04_AR_Ledger'!$B$5:$B$11="B")*'07_Solver'!$H$6:$H$12*'04_AR_Ledger'!$C$5:$C$11*'04_AR_Ledger'!$K$5:$K$11)
A9: C | B9: =SUMPRODUCT(('04_AR_Ledger'!$B$5:$B$11="C")*'07_Solver'!$H$6:$H$12*'04_AR_Ledger'!$C$5:$C$11*'04_AR_Ledger'!$K$5:$K$11)
A11: 케이스 | B11: ΔTSOFR | C11: PD 배수 | D11: LGD | E11: r 부보 S | F11: r 부보 A | G11: r 부보 B | H11: r 부보 C | I11: 매각비용(USD) | J11: 기준 대비(USD) | K11: W5 누적현금(조치 후)
A12: 기준 | B12: 0 | C12: 1 | D12: =LGD | E12: =TSOFR3M+$B12+Spread_S+Prem_S*365/Tenor+MIN(1,PD_S*$C12)*$D12*(1-Cov) | F12: =TSOFR3M+$B12+Spread_A+Prem_A*365/Tenor+MIN(1,PD_A*$C12)*$D12*(1-Cov) | G12: =TSOFR3M+$B12+Spread_B+Prem_B*365/Tenor+MIN(1,PD_B*$C12)*$D12*(1-Cov) | H12: =TSOFR3M+$B12+Spread_C+Prem_C*365/Tenor+MIN(1,PD_C*$C12)*$D12*(1-Cov) | I12: =($E12*$B$6+$F12*$B$7+$G12*$B$8+$H12*$B$9)/DayBasis*1000 | J12: =I12-$I$12 | K12: ='06_WeeklyGap'!$F$11+($I$12-I12)/1000
A13: TSOFR +100bp | B13: 0.01 | C13: 1 | D13: =LGD | E13: =TSOFR3M+$B13+Spread_S+Prem_S*365/Tenor+MIN(1,PD_S*$C13)*$D13*(1-Cov) | F13: =TSOFR3M+$B13+Spread_A+Prem_A*365/Tenor+MIN(1,PD_A*$C13)*$D13*(1-Cov) | G13: =TSOFR3M+$B13+Spread_B+Prem_B*365/Tenor+MIN(1,PD_B*$C13)*$D13*(1-Cov) | H13: =TSOFR3M+$B13+Spread_C+Prem_C*365/Tenor+MIN(1,PD_C*$C13)*$D13*(1-Cov) | I13: =($E13*$B$6+$F13*$B$7+$G13*$B$8+$H13*$B$9)/DayBasis*1000 | J13: =I13-$I$12 | K13: ='06_WeeklyGap'!$F$11+($I$12-I13)/1000
A14: TSOFR −100bp | B14: -0.01 | C14: 1 | D14: =LGD | E14: =TSOFR3M+$B14+Spread_S+Prem_S*365/Tenor+MIN(1,PD_S*$C14)*$D14*(1-Cov) | F14: =TSOFR3M+$B14+Spread_A+Prem_A*365/Tenor+MIN(1,PD_A*$C14)*$D14*(1-Cov) | G14: =TSOFR3M+$B14+Spread_B+Prem_B*365/Tenor+MIN(1,PD_B*$C14)*$D14*(1-Cov) | H14: =TSOFR3M+$B14+Spread_C+Prem_C*365/Tenor+MIN(1,PD_C*$C14)*$D14*(1-Cov) | I14: =($E14*$B$6+$F14*$B$7+$G14*$B$8+$H14*$B$9)/DayBasis*1000 | J14: =I14-$I$12 | K14: ='06_WeeklyGap'!$F$11+($I$12-I14)/1000
A15: PD × 2 | B15: 0 | C15: 2 | D15: =LGD | E15: =TSOFR3M+$B15+Spread_S+Prem_S*365/Tenor+MIN(1,PD_S*$C15)*$D15*(1-Cov) | F15: =TSOFR3M+$B15+Spread_A+Prem_A*365/Tenor+MIN(1,PD_A*$C15)*$D15*(1-Cov) | G15: =TSOFR3M+$B15+Spread_B+Prem_B*365/Tenor+MIN(1,PD_B*$C15)*$D15*(1-Cov) | H15: =TSOFR3M+$B15+Spread_C+Prem_C*365/Tenor+MIN(1,PD_C*$C15)*$D15*(1-Cov) | I15: =($E15*$B$6+$F15*$B$7+$G15*$B$8+$H15*$B$9)/DayBasis*1000 | J15: =I15-$I$12 | K15: ='06_WeeklyGap'!$F$11+($I$12-I15)/1000
A16: LGD 40% | B16: 0 | C16: 1 | D16: 0.4 | E16: =TSOFR3M+$B16+Spread_S+Prem_S*365/Tenor+MIN(1,PD_S*$C16)*$D16*(1-Cov) | F16: =TSOFR3M+$B16+Spread_A+Prem_A*365/Tenor+MIN(1,PD_A*$C16)*$D16*(1-Cov) | G16: =TSOFR3M+$B16+Spread_B+Prem_B*365/Tenor+MIN(1,PD_B*$C16)*$D16*(1-Cov) | H16: =TSOFR3M+$B16+Spread_C+Prem_C*365/Tenor+MIN(1,PD_C*$C16)*$D16*(1-Cov) | I16: =($E16*$B$6+$F16*$B$7+$G16*$B$8+$H16*$B$9)/DayBasis*1000 | J16: =I16-$I$12 | K16: ='06_WeeklyGap'!$F$11+($I$12-I16)/1000
A17: LGD 80% | B17: 0 | C17: 1 | D17: 0.8 | E17: =TSOFR3M+$B17+Spread_S+Prem_S*365/Tenor+MIN(1,PD_S*$C17)*$D17*(1-Cov) | F17: =TSOFR3M+$B17+Spread_A+Prem_A*365/Tenor+MIN(1,PD_A*$C17)*$D17*(1-Cov) | G17: =TSOFR3M+$B17+Spread_B+Prem_B*365/Tenor+MIN(1,PD_B*$C17)*$D17*(1-Cov) | H17: =TSOFR3M+$B17+Spread_C+Prem_C*365/Tenor+MIN(1,PD_C*$C17)*$D17*(1-Cov) | I17: =($E17*$B$6+$F17*$B$7+$G17*$B$8+$H17*$B$9)/DayBasis*1000 | J17: =I17-$I$12 | K17: ='06_WeeklyGap'!$F$11+($I$12-I17)/1000

Sheet 09_Chart
A1: 09_Chart — 누적현금(06) · 할인율 구성(03) · 등급별 한도(10)

Sheet 10_LimitLP
A1: 10_LimitLP — 바이어별 신용한도 배분 LP(해 찾기: 단순 LP · 모델 저장됨)
A2: 목적함수 Obj(최대화) | C2: =SUMPRODUCT(coef,L) | D2: ← 해 찾기 '목표 설정'
T3: 제약(해 찾기 입력표 ①②④ · ③은 아래 국가 블록)
A4: buyer_id | B4: country | C4: 등급 | D4: UB 상한 | E4: LB 하한 | F4: L 한도(결정변수) | G4: coef | H4: elc | I4: 현행 한도 | J4: 변경(L−현행) | K4: 변경률 | L4: 승인 표시 | M4: 한도 대상 | N4: 전결권자 | O4: 전략 | P4: L_ref(PuLP 참고해) | Q4: L − L_ref | R4: 동점 그룹(같은 coef 수) | T4: 제약 | U4: LHS | V4: 관계 | W4: RHS | X4: 여유 | Y4: 걸림? | Z4: 잠재가격(민감도 보고서에서 입력) | AA4: PuLP 참고
A5: =IF('02_Buyers'!$A2="","",'02_Buyers'!$A2) | B5: =IF($A5="","",'02_Buyers'!$S2) | C5: =IF($A5="","",'02_Buyers'!$AK2) | D5: =IF($A5="",0,'02_Buyers'!$BB2) | E5: =IF($A5="",0,'02_Buyers'!$BC2) | F5: 0 | G5: =IF($A5="",0,'02_Buyers'!$BD2) | H5: =IF($A5="",0,'02_Buyers'!$BE2) | I5: =IF($A5="",0,'02_Buyers'!$AB2) | J5: =IF($A5="","",F5-I5) | K5: =IF(OR($A5="",I5<=0),"",J5/I5) | L5: =IF($A5="","",IF(M5="대상 아님","대상 아님(L/C·선수금)",IF(AND(I5>0,K5<=-0.3),"감액 30%↑ — 사람 승인 필요",IF(J5>0,"증액 — 전결권자 승인","유지·소폭 감액")))) | M5: =IF($A5="","",'02_Buyers'!$BA2) | N5: =IF(OR($A5="",M5="대상 아님"),"",IF(F5<=50000,"채권관리팀장",IF(F5<=200000,"영업본부장","대표이사"))) | O5: =IF($A5="","",'02_Buyers'!$AG2) | Q5: =IF(OR($A5="",P5=""),"",F5-P5) | R5: =IF(OR($A5="",D5<=0),"",COUNTIFS($G$5:$G$154,G5,$D$5:$D$154,">0")) | T5: ① 총허용익스포저 Σ L ≤ TotalCap | U5: =SUM(L) | V5: ≤ | W5: =ROUND(TotalCapShare*SUM(UB),-5) | X5: =W5-U5 | Y5: =IF(X5<=0.5,"걸림","")
A6: =IF('02_Buyers'!$A3="","",'02_Buyers'!$A3) | B6: =IF($A6="","",'02_Buyers'!$S3) | C6: =IF($A6="","",'02_Buyers'!$AK3) | D6: =IF($A6="",0,'02_Buyers'!$BB3) | E6: =IF($A6="",0,'02_Buyers'!$BC3) | F6: 0 | G6: =IF($A6="",0,'02_Buyers'!$BD3) | H6: =IF($A6="",0,'02_Buyers'!$BE3) | I6: =IF($A6="",0,'02_Buyers'!$AB3) | J6: =IF($A6="","",F6-I6) | K6: =IF(OR($A6="",I6<=0),"",J6/I6) | L6: =IF($A6="","",IF(M6="대상 아님","대상 아님(L/C·선수금)",IF(AND(I6>0,K6<=-0.3),"감액 30%↑ — 사람 승인 필요",IF(J6>0,"증액 — 전결권자 승인","유지·소폭 감액")))) | M6: =IF($A6="","",'02_Buyers'!$BA3) | N6: =IF(OR($A6="",M6="대상 아님"),"",IF(F6<=50000,"채권관리팀장",IF(F6<=200000,"영업본부장","대표이사"))) | O6: =IF($A6="","",'02_Buyers'!$AG3) | Q6: =IF(OR($A6="",P6=""),"",F6-P6) | R6: =IF(OR($A6="",D6<=0),"",COUNTIFS($G$5:$G$154,G6,$D$5:$D$154,">0")) | T6: ② 미부보 EL 예산 Σ elc·L ≤ 자기자본 × α | U6: =SUMPRODUCT(elc,L) | V6: ≤ | W6: =Equity_USD*Alpha | X6: =W6-U6 | Y6: =IF(X6<=0.5,"걸림","")
A7: =IF('02_Buyers'!$A4="","",'02_Buyers'!$A4) | B7: =IF($A7="","",'02_Buyers'!$S4) | C7: =IF($A7="","",'02_Buyers'!$AK4) | D7: =IF($A7="",0,'02_Buyers'!$BB4) | E7: =IF($A7="",0,'02_Buyers'!$BC4) | F7: 0 | G7: =IF($A7="",0,'02_Buyers'!$BD4) | H7: =IF($A7="",0,'02_Buyers'!$BE4) | I7: =IF($A7="",0,'02_Buyers'!$AB4) | J7: =IF($A7="","",F7-I7) | K7: =IF(OR($A7="",I7<=0),"",J7/I7) | L7: =IF($A7="","",IF(M7="대상 아님","대상 아님(L/C·선수금)",IF(AND(I7>0,K7<=-0.3),"감액 30%↑ — 사람 승인 필요",IF(J7>0,"증액 — 전결권자 승인","유지·소폭 감액")))) | M7: =IF($A7="","",'02_Buyers'!$BA4) | N7: =IF(OR($A7="",M7="대상 아님"),"",IF(F7<=50000,"채권관리팀장",IF(F7<=200000,"영업본부장","대표이사"))) | O7: =IF($A7="","",'02_Buyers'!$AG4) | Q7: =IF(OR($A7="",P7=""),"",F7-P7) | R7: =IF(OR($A7="",D7<=0),"",COUNTIFS($G$5:$G$154,G7,$D$5:$D$154,">0")) | T7: ④ B등급 Σ L ≤ 30% × TotalCap | U7: =SUMPRODUCT((grade_lp="B")*L) | V7: ≤ | W7: =ShareCap_B*TotalCap | X7: =W7-U7 | Y7: =IF(X7<=0.5,"걸림","")
A8: =IF('02_Buyers'!$A5="","",'02_Buyers'!$A5) | B8: =IF($A8="","",'02_Buyers'!$S5) | C8: =IF($A8="","",'02_Buyers'!$AK5) | D8: =IF($A8="",0,'02_Buyers'!$BB5) | E8: =IF($A8="",0,'02_Buyers'!$BC5) | F8: 0 | G8: =IF($A8="",0,'02_Buyers'!$BD5) | H8: =IF($A8="",0,'02_Buyers'!$BE5) | I8: =IF($A8="",0,'02_Buyers'!$AB5) | J8: =IF($A8="","",F8-I8) | K8: =IF(OR($A8="",I8<=0),"",J8/I8) | L8: =IF($A8="","",IF(M8="대상 아님","대상 아님(L/C·선수금)",IF(AND(I8>0,K8<=-0.3),"감액 30%↑ — 사람 승인 필요",IF(J8>0,"증액 — 전결권자 승인","유지·소폭 감액")))) | M8: =IF($A8="","",'02_Buyers'!$BA5) | N8: =IF(OR($A8="",M8="대상 아님"),"",IF(F8<=50000,"채권관리팀장",IF(F8<=200000,"영업본부장","대표이사"))) | O8: =IF($A8="","",'02_Buyers'!$AG5) | Q8: =IF(OR($A8="",P8=""),"",F8-P8) | R8: =IF(OR($A8="",D8<=0),"",COUNTIFS($G$5:$G$154,G8,$D$5:$D$154,">0"))
A9: =IF('02_Buyers'!$A6="","",'02_Buyers'!$A6) | B9: =IF($A9="","",'02_Buyers'!$S6) | C9: =IF($A9="","",'02_Buyers'!$AK6) | D9: =IF($A9="",0,'02_Buyers'!$BB6) | E9: =IF($A9="",0,'02_Buyers'!$BC6) | F9: 0 | G9: =IF($A9="",0,'02_Buyers'!$BD6) | H9: =IF($A9="",0,'02_Buyers'!$BE6) | I9: =IF($A9="",0,'02_Buyers'!$AB6) | J9: =IF($A9="","",F9-I9) | K9: =IF(OR($A9="",I9<=0),"",J9/I9) | L9: =IF($A9="","",IF(M9="대상 아님","대상 아님(L/C·선수금)",IF(AND(I9>0,K9<=-0.3),"감액 30%↑ — 사람 승인 필요",IF(J9>0,"증액 — 전결권자 승인","유지·소폭 감액")))) | M9: =IF($A9="","",'02_Buyers'!$BA6) | N9: =IF(OR($A9="",M9="대상 아님"),"",IF(F9<=50000,"채권관리팀장",IF(F9<=200000,"영업본부장","대표이사"))) | O9: =IF($A9="","",'02_Buyers'!$AG6) | Q9: =IF(OR($A9="",P9=""),"",F9-P9) | R9: =IF(OR($A9="",D9<=0),"",COUNTIFS($G$5:$G$154,G9,$D$5:$D$154,">0"))
A10: =IF('02_Buyers'!$A7="","",'02_Buyers'!$A7) | B10: =IF($A10="","",'02_Buyers'!$S7) | C10: =IF($A10="","",'02_Buyers'!$AK7) | D10: =IF($A10="",0,'02_Buyers'!$BB7) | E10: =IF($A10="",0,'02_Buyers'!$BC7) | F10: 0 | G10: =IF($A10="",0,'02_Buyers'!$BD7) | H10: =IF($A10="",0,'02_Buyers'!$BE7) | I10: =IF($A10="",0,'02_Buyers'!$AB7) | J10: =IF($A10="","",F10-I10) | K10: =IF(OR($A10="",I10<=0),"",J10/I10) | L10: =IF($A10="","",IF(M10="대상 아님","대상 아님(L/C·선수금)",IF(AND(I10>0,K10<=-0.3),"감액 30%↑ — 사람 승인 필요",IF(J10>0,"증액 — 전결권자 승인","유지·소폭 감액")))) | M10: =IF($A10="","",'02_Buyers'!$BA7) | N10: =IF(OR($A10="",M10="대상 아님"),"",IF(F10<=50000,"채권관리팀장",IF(F10<=200000,"영업본부장","대표이사"))) | O10: =IF($A10="","",'02_Buyers'!$AG7) | Q10: =IF(OR($A10="",P10=""),"",F10-P10) | R10: =IF(OR($A10="",D10<=0),"",COUNTIFS($G$5:$G$154,G10,$D$5:$D$154,">0")) | T10: ③ 국가 한도 Σ_{국가} L ≤ 한도율(CRC) × TotalCap — 20개 제약을 한 줄로: CtryUsed ≤ CtryCap
A11: =IF('02_Buyers'!$A8="","",'02_Buyers'!$A8) | B11: =IF($A11="","",'02_Buyers'!$S8) | C11: =IF($A11="","",'02_Buyers'!$AK8) | D11: =IF($A11="",0,'02_Buyers'!$BB8) | E11: =IF($A11="",0,'02_Buyers'!$BC8) | F11: 0 | G11: =IF($A11="",0,'02_Buyers'!$BD8) | H11: =IF($A11="",0,'02_Buyers'!$BE8) | I11: =IF($A11="",0,'02_Buyers'!$AB8) | J11: =IF($A11="","",F11-I11) | K11: =IF(OR($A11="",I11<=0),"",J11/I11) | L11: =IF($A11="","",IF(M11="대상 아님","대상 아님(L/C·선수금)",IF(AND(I11>0,K11<=-0.3),"감액 30%↑ — 사람 승인 필요",IF(J11>0,"증액 — 전결권자 승인","유지·소폭 감액")))) | M11: =IF($A11="","",'02_Buyers'!$BA8) | N11: =IF(OR($A11="",M11="대상 아님"),"",IF(F11<=50000,"채권관리팀장",IF(F11<=200000,"영업본부장","대표이사"))) | O11: =IF($A11="","",'02_Buyers'!$AG8) | Q11: =IF(OR($A11="",P11=""),"",F11-P11) | R11: =IF(OR($A11="",D11<=0),"",COUNTIFS($G$5:$G$154,G11,$D$5:$D$154,">0")) | T11: 국가 | U11: 국가명 | V11: OECD CRC | W11: 구간 | X11: 한도율 | Y11: CtryCap(USD) | Z11: CtryUsed | AA11: 여유 | AB11: 걸림? | AC11: 잠재가격(입력) | AD11: PuLP 참고
A12: =IF('02_Buyers'!$A9="","",'02_Buyers'!$A9) | B12: =IF($A12="","",'02_Buyers'!$S9) | C12: =IF($A12="","",'02_Buyers'!$AK9) | D12: =IF($A12="",0,'02_Buyers'!$BB9) | E12: =IF($A12="",0,'02_Buyers'!$BC9) | F12: 0 | G12: =IF($A12="",0,'02_Buyers'!$BD9) | H12: =IF($A12="",0,'02_Buyers'!$BE9) | I12: =IF($A12="",0,'02_Buyers'!$AB9) | J12: =IF($A12="","",F12-I12) | K12: =IF(OR($A12="",I12<=0),"",J12/I12) | L12: =IF($A12="","",IF(M12="대상 아님","대상 아님(L/C·선수금)",IF(AND(I12>0,K12<=-0.3),"감액 30%↑ — 사람 승인 필요",IF(J12>0,"증액 — 전결권자 승인","유지·소폭 감액")))) | M12: =IF($A12="","",'02_Buyers'!$BA9) | N12: =IF(OR($A12="",M12="대상 아님"),"",IF(F12<=50000,"채권관리팀장",IF(F12<=200000,"영업본부장","대표이사"))) | O12: =IF($A12="","",'02_Buyers'!$AG9) | Q12: =IF(OR($A12="",P12=""),"",F12-P12) | R12: =IF(OR($A12="",D12<=0),"",COUNTIFS($G$5:$G$154,G12,$D$5:$D$154,">0")) | T12: USA | U12: 미국 | W12: =IF(V12="","0-2",IF(V12<=2,"0-2",IF(V12=3,"3",IF(V12<=5,"4-5","6-7")))) | X12: =CHOOSE(MATCH(W12,{"0-2","3","4-5","6-7"},0),CtryCap_02,CtryCap_3,CtryCap_45,CtryCap_67) | Y12: =X12*TotalCap | Z12: =SUMPRODUCT((ctry=T12)*L) | AA12: =Y12-Z12 | AB12: =IF(AA12<=0.5,"걸림","")
A13: =IF('02_Buyers'!$A10="","",'02_Buyers'!$A10) | B13: =IF($A13="","",'02_Buyers'!$S10) | C13: =IF($A13="","",'02_Buyers'!$AK10) | D13: =IF($A13="",0,'02_Buyers'!$BB10) | E13: =IF($A13="",0,'02_Buyers'!$BC10) | F13: 0 | G13: =IF($A13="",0,'02_Buyers'!$BD10) | H13: =IF($A13="",0,'02_Buyers'!$BE10) | I13: =IF($A13="",0,'02_Buyers'!$AB10) | J13: =IF($A13="","",F13-I13) | K13: =IF(OR($A13="",I13<=0),"",J13/I13) | L13: =IF($A13="","",IF(M13="대상 아님","대상 아님(L/C·선수금)",IF(AND(I13>0,K13<=-0.3),"감액 30%↑ — 사람 승인 필요",IF(J13>0,"증액 — 전결권자 승인","유지·소폭 감액")))) | M13: =IF($A13="","",'02_Buyers'!$BA10) | N13: =IF(OR($A13="",M13="대상 아님"),"",IF(F13<=50000,"채권관리팀장",IF(F13<=200000,"영업본부장","대표이사"))) | O13: =IF($A13="","",'02_Buyers'!$AG10) | Q13: =IF(OR($A13="",P13=""),"",F13-P13) | R13: =IF(OR($A13="",D13<=0),"",COUNTIFS($G$5:$G$154,G13,$D$5:$D$154,">0")) | T13: MEX | U13: 멕시코 | V13: 3 | W13: =IF(V13="","0-2",IF(V13<=2,"0-2",IF(V13=3,"3",IF(V13<=5,"4-5","6-7")))) | X13: =CHOOSE(MATCH(W13,{"0-2","3","4-5","6-7"},0),CtryCap_02,CtryCap_3,CtryCap_45,CtryCap_67) | Y13: =X13*TotalCap | Z13: =SUMPRODUCT((ctry=T13)*L) | AA13: =Y13-Z13 | AB13: =IF(AA13<=0.5,"걸림","")
A14: =IF('02_Buyers'!$A11="","",'02_Buyers'!$A11) | B14: =IF($A14="","",'02_Buyers'!$S11) | C14: =IF($A14="","",'02_Buyers'!$AK11) | D14: =IF($A14="",0,'02_Buyers'!$BB11) | E14: =IF($A14="",0,'02_Buyers'!$BC11) | F14: 0 | G14: =IF($A14="",0,'02_Buyers'!$BD11) | H14: =IF($A14="",0,'02_Buyers'!$BE11) | I14: =IF($A14="",0,'02_Buyers'!$AB11) | J14: =IF($A14="","",F14-I14) | K14: =IF(OR($A14="",I14<=0),"",J14/I14) | L14: =IF($A14="","",IF(M14="대상 아님","대상 아님(L/C·선수금)",IF(AND(I14>0,K14<=-0.3),"감액 30%↑ — 사람 승인 필요",IF(J14>0,"증액 — 전결권자 승인","유지·소폭 감액")))) | M14: =IF($A14="","",'02_Buyers'!$BA11) | N14: =IF(OR($A14="",M14="대상 아님"),"",IF(F14<=50000,"채권관리팀장",IF(F14<=200000,"영업본부장","대표이사"))) | O14: =IF($A14="","",'02_Buyers'!$AG11) | Q14: =IF(OR($A14="",P14=""),"",F14-P14) | R14: =IF(OR($A14="",D14<=0),"",COUNTIFS($G$5:$G$154,G14,$D$5:$D$154,">0")) | T14: BRA | U14: 브라질 | V14: 4 | W14: =IF(V14="","0-2",IF(V14<=2,"0-2",IF(V14=3,"3",IF(V14<=5,"4-5","6-7")))) | X14: =CHOOSE(MATCH(W14,{"0-2","3","4-5","6-7"},0),CtryCap_02,CtryCap_3,CtryCap_45,CtryCap_67) | Y14: =X14*TotalCap | Z14: =SUMPRODUCT((ctry=T14)*L) | AA14: =Y14-Z14 | AB14: =IF(AA14<=0.5,"걸림","")
A15: =IF('02_Buyers'!$A12="","",'02_Buyers'!$A12) | B15: =IF($A15="","",'02_Buyers'!$S12) | C15: =IF($A15="","",'02_Buyers'!$AK12) | D15: =IF($A15="",0,'02_Buyers'!$BB12) | E15: =IF($A15="",0,'02_Buyers'!$BC12) | F15: 0 | G15: =IF($A15="",0,'02_Buyers'!$BD12) | H15: =IF($A15="",0,'02_Buyers'!$BE12) | I15: =IF($A15="",0,'02_Buyers'!$AB12) | J15: =IF($A15="","",F15-I15) | K15: =IF(OR($A15="",I15<=0),"",J15/I15) | L15: =IF($A15="","",IF(M15="대상 아님","대상 아님(L/C·선수금)",IF(AND(I15>0,K15<=-0.3),"감액 30%↑ — 사람 승인 필요",IF(J15>0,"증액 — 전결권자 승인","유지·소폭 감액")))) | M15: =IF($A15="","",'02_Buyers'!$BA12) | N15: =IF(OR($A15="",M15="대상 아님"),"",IF(F15<=50000,"채권관리팀장",IF(F15<=200000,"영업본부장","대표이사"))) | O15: =IF($A15="","",'02_Buyers'!$AG12) | Q15: =IF(OR($A15="",P15=""),"",F15-P15) | R15: =IF(OR($A15="",D15<=0),"",COUNTIFS($G$5:$G$154,G15,$D$5:$D$154,">0")) | T15: DEU | U15: 독일 | W15: =IF(V15="","0-2",IF(V15<=2,"0-2",IF(V15=3,"3",IF(V15<=5,"4-5","6-7")))) | X15: =CHOOSE(MATCH(W15,{"0-2","3","4-5","6-7"},0),CtryCap_02,CtryCap_3,CtryCap_45,CtryCap_67) | Y15: =X15*TotalCap | Z15: =SUMPRODUCT((ctry=T15)*L) | AA15: =Y15-Z15 | AB15: =IF(AA15<=0.5,"걸림","")
A16: =IF('02_Buyers'!$A13="","",'02_Buyers'!$A13) | B16: =IF($A16="","",'02_Buyers'!$S13) | C16: =IF($A16="","",'02_Buyers'!$AK13) | D16: =IF($A16="",0,'02_Buyers'!$BB13) | E16: =IF($A16="",0,'02_Buyers'!$BC13) | F16: 0 | G16: =IF($A16="",0,'02_Buyers'!$BD13) | H16: =IF($A16="",0,'02_Buyers'!$BE13) | I16: =IF($A16="",0,'02_Buyers'!$AB13) | J16: =IF($A16="","",F16-I16) | K16: =IF(OR($A16="",I16<=0),"",J16/I16) | L16: =IF($A16="","",IF(M16="대상 아님","대상 아님(L/C·선수금)",IF(AND(I16>0,K16<=-0.3),"감액 30%↑ — 사람 승인 필요",IF(J16>0,"증액 — 전결권자 승인","유지·소폭 감액")))) | M16: =IF($A16="","",'02_Buyers'!$BA13) | N16: =IF(OR($A16="",M16="대상 아님"),"",IF(F16<=50000,"채권관리팀장",IF(F16<=200000,"영업본부장","대표이사"))) | O16: =IF($A16="","",'02_Buyers'!$AG13) | Q16: =IF(OR($A16="",P16=""),"",F16-P16) | R16: =IF(OR($A16="",D16<=0),"",COUNTIFS($G$5:$G$154,G16,$D$5:$D$154,">0")) | T16: NLD | U16: 네덜란드 | W16: =IF(V16="","0-2",IF(V16<=2,"0-2",IF(V16=3,"3",IF(V16<=5,"4-5","6-7")))) | X16: =CHOOSE(MATCH(W16,{"0-2","3","4-5","6-7"},0),CtryCap_02,CtryCap_3,CtryCap_45,CtryCap_67) | Y16: =X16*TotalCap | Z16: =SUMPRODUCT((ctry=T16)*L) | AA16: =Y16-Z16 | AB16: =IF(AA16<=0.5,"걸림","")
A17: =IF('02_Buyers'!$A14="","",'02_Buyers'!$A14) | B17: =IF($A17="","",'02_Buyers'!$S14) | C17: =IF($A17="","",'02_Buyers'!$AK14) | D17: =IF($A17="",0,'02_Buyers'!$BB14) | E17: =IF($A17="",0,'02_Buyers'!$BC14) | F17: 0 | G17: =IF($A17="",0,'02_Buyers'!$BD14) | H17: =IF($A17="",0,'02_Buyers'!$BE14) | I17: =IF($A17="",0,'02_Buyers'!$AB14) | J17: =IF($A17="","",F17-I17) | K17: =IF(OR($A17="",I17<=0),"",J17/I17) | L17: =IF($A17="","",IF(M17="대상 아님","대상 아님(L/C·선수금)",IF(AND(I17>0,K17<=-0.3),"감액 30%↑ — 사람 승인 필요",IF(J17>0,"증액 — 전결권자 승인","유지·소폭 감액")))) | M17: =IF($A17="","",'02_Buyers'!$BA14) | N17: =IF(OR($A17="",M17="대상 아님"),"",IF(F17<=50000,"채권관리팀장",IF(F17<=200000,"영업본부장","대표이사"))) | O17: =IF($A17="","",'02_Buyers'!$AG14) | Q17: =IF(OR($A17="",P17=""),"",F17-P17) | R17: =IF(OR($A17="",D17<=0),"",COUNTIFS($G$5:$G$154,G17,$D$5:$D$154,">0")) | T17: GBR | U17: 영국 | W17: =IF(V17="","0-2",IF(V17<=2,"0-2",IF(V17=3,"3",IF(V17<=5,"4-5","6-7")))) | X17: =CHOOSE(MATCH(W17,{"0-2","3","4-5","6-7"},0),CtryCap_02,CtryCap_3,CtryCap_45,CtryCap_67) | Y17: =X17*TotalCap | Z17: =SUMPRODUCT((ctry=T17)*L) | AA17: =Y17-Z17 | AB17: =IF(AA17<=0.5,"걸림","")
A18: =IF('02_Buyers'!$A15="","",'02_Buyers'!$A15) | B18: =IF($A18="","",'02_Buyers'!$S15) | C18: =IF($A18="","",'02_Buyers'!$AK15) | D18: =IF($A18="",0,'02_Buyers'!$BB15) | E18: =IF($A18="",0,'02_Buyers'!$BC15) | F18: 0 | G18: =IF($A18="",0,'02_Buyers'!$BD15) | H18: =IF($A18="",0,'02_Buyers'!$BE15) | I18: =IF($A18="",0,'02_Buyers'!$AB15) | J18: =IF($A18="","",F18-I18) | K18: =IF(OR($A18="",I18<=0),"",J18/I18) | L18: =IF($A18="","",IF(M18="대상 아님","대상 아님(L/C·선수금)",IF(AND(I18>0,K18<=-0.3),"감액 30%↑ — 사람 승인 필요",IF(J18>0,"증액 — 전결권자 승인","유지·소폭 감액")))) | M18: =IF($A18="","",'02_Buyers'!$BA15) | N18: =IF(OR($A18="",M18="대상 아님"),"",IF(F18<=50000,"채권관리팀장",IF(F18<=200000,"영업본부장","대표이사"))) | O18: =IF($A18="","",'02_Buyers'!$AG15) | Q18: =IF(OR($A18="",P18=""),"",F18-P18) | R18: =IF(OR($A18="",D18<=0),"",COUNTIFS($G$5:$G$154,G18,$D$5:$D$154,">0")) | T18: POL | U18: 폴란드 | W18: =IF(V18="","0-2",IF(V18<=2,"0-2",IF(V18=3,"3",IF(V18<=5,"4-5","6-7")))) | X18: =CHOOSE(MATCH(W18,{"0-2","3","4-5","6-7"},0),CtryCap_02,CtryCap_3,CtryCap_45,CtryCap_67) | Y18: =X18*TotalCap | Z18: =SUMPRODUCT((ctry=T18)*L) | AA18: =Y18-Z18 | AB18: =IF(AA18<=0.5,"걸림","")
A19: =IF('02_Buyers'!$A16="","",'02_Buyers'!$A16) | B19: =IF($A19="","",'02_Buyers'!$S16) | C19: =IF($A19="","",'02_Buyers'!$AK16) | D19: =IF($A19="",0,'02_Buyers'!$BB16) | E19: =IF($A19="",0,'02_Buyers'!$BC16) | F19: 0 | G19: =IF($A19="",0,'02_Buyers'!$BD16) | H19: =IF($A19="",0,'02_Buyers'!$BE16) | I19: =IF($A19="",0,'02_Buyers'!$AB16) | J19: =IF($A19="","",F19-I19) | K19: =IF(OR($A19="",I19<=0),"",J19/I19) | L19: =IF($A19="","",IF(M19="대상 아님","대상 아님(L/C·선수금)",IF(AND(I19>0,K19<=-0.3),"감액 30%↑ — 사람 승인 필요",IF(J19>0,"증액 — 전결권자 승인","유지·소폭 감액")))) | M19: =IF($A19="","",'02_Buyers'!$BA16) | N19: =IF(OR($A19="",M19="대상 아님"),"",IF(F19<=50000,"채권관리팀장",IF(F19<=200000,"영업본부장","대표이사"))) | O19: =IF($A19="","",'02_Buyers'!$AG16) | Q19: =IF(OR($A19="",P19=""),"",F19-P19) | R19: =IF(OR($A19="",D19<=0),"",COUNTIFS($G$5:$G$154,G19,$D$5:$D$154,">0")) | T19: TUR | U19: 튀르키예 | V19: 5 | W19: =IF(V19="","0-2",IF(V19<=2,"0-2",IF(V19=3,"3",IF(V19<=5,"4-5","6-7")))) | X19: =CHOOSE(MATCH(W19,{"0-2","3","4-5","6-7"},0),CtryCap_02,CtryCap_3,CtryCap_45,CtryCap_67) | Y19: =X19*TotalCap | Z19: =SUMPRODUCT((ctry=T19)*L) | AA19: =Y19-Z19 | AB19: =IF(AA19<=0.5,"걸림","")
A20: =IF('02_Buyers'!$A17="","",'02_Buyers'!$A17) | B20: =IF($A20="","",'02_Buyers'!$S17) | C20: =IF($A20="","",'02_Buyers'!$AK17) | D20: =IF($A20="",0,'02_Buyers'!$BB17) | E20: =IF($A20="",0,'02_Buyers'!$BC17) | F20: 0 | G20: =IF($A20="",0,'02_Buyers'!$BD17) | H20: =IF($A20="",0,'02_Buyers'!$BE17) | I20: =IF($A20="",0,'02_Buyers'!$AB17) | J20: =IF($A20="","",F20-I20) | K20: =IF(OR($A20="",I20<=0),"",J20/I20) | L20: =IF($A20="","",IF(M20="대상 아님","대상 아님(L/C·선수금)",IF(AND(I20>0,K20<=-0.3),"감액 30%↑ — 사람 승인 필요",IF(J20>0,"증액 — 전결권자 승인","유지·소폭 감액")))) | M20: =IF($A20="","",'02_Buyers'!$BA17) | N20: =IF(OR($A20="",M20="대상 아님"),"",IF(F20<=50000,"채권관리팀장",IF(F20<=200000,"영업본부장","대표이사"))) | O20: =IF($A20="","",'02_Buyers'!$AG17) | Q20: =IF(OR($A20="",P20=""),"",F20-P20) | R20: =IF(OR($A20="",D20<=0),"",COUNTIFS($G$5:$G$154,G20,$D$5:$D$154,">0")) | T20: CHN | U20: 중국 | V20: 2 | W20: =IF(V20="","0-2",IF(V20<=2,"0-2",IF(V20=3,"3",IF(V20<=5,"4-5","6-7")))) | X20: =CHOOSE(MATCH(W20,{"0-2","3","4-5","6-7"},0),CtryCap_02,CtryCap_3,CtryCap_45,CtryCap_67) | Y20: =X20*TotalCap | Z20: =SUMPRODUCT((ctry=T20)*L) | AA20: =Y20-Z20 | AB20: =IF(AA20<=0.5,"걸림","")
A21: =IF('02_Buyers'!$A18="","",'02_Buyers'!$A18) | B21: =IF($A21="","",'02_Buyers'!$S18) | C21: =IF($A21="","",'02_Buyers'!$AK18) | D21: =IF($A21="",0,'02_Buyers'!$BB18) | E21: =IF($A21="",0,'02_Buyers'!$BC18) | F21: 0 | G21: =IF($A21="",0,'02_Buyers'!$BD18) | H21: =IF($A21="",0,'02_Buyers'!$BE18) | I21: =IF($A21="",0,'02_Buyers'!$AB18) | J21: =IF($A21="","",F21-I21) | K21: =IF(OR($A21="",I21<=0),"",J21/I21) | L21: =IF($A21="","",IF(M21="대상 아님","대상 아님(L/C·선수금)",IF(AND(I21>0,K21<=-0.3),"감액 30%↑ — 사람 승인 필요",IF(J21>0,"증액 — 전결권자 승인","유지·소폭 감액")))) | M21: =IF($A21="","",'02_Buyers'!$BA18) | N21: =IF(OR($A21="",M21="대상 아님"),"",IF(F21<=50000,"채권관리팀장",IF(F21<=200000,"영업본부장","대표이사"))) | O21: =IF($A21="","",'02_Buyers'!$AG18) | Q21: =IF(OR($A21="",P21=""),"",F21-P21) | R21: =IF(OR($A21="",D21<=0),"",COUNTIFS($G$5:$G$154,G21,$D$5:$D$154,">0")) | T21: JPN | U21: 일본 | W21: =IF(V21="","0-2",IF(V21<=2,"0-2",IF(V21=3,"3",IF(V21<=5,"4-5","6-7")))) | X21: =CHOOSE(MATCH(W21,{"0-2","3","4-5","6-7"},0),CtryCap_02,CtryCap_3,CtryCap_45,CtryCap_67) | Y21: =X21*TotalCap | Z21: =SUMPRODUCT((ctry=T21)*L) | AA21: =Y21-Z21 | AB21: =IF(AA21<=0.5,"걸림","")
A22: =IF('02_Buyers'!$A19="","",'02_Buyers'!$A19) | B22: =IF($A22="","",'02_Buyers'!$S19) | C22: =IF($A22="","",'02_Buyers'!$AK19) | D22: =IF($A22="",0,'02_Buyers'!$BB19) | E22: =IF($A22="",0,'02_Buyers'!$BC19) | F22: 0 | G22: =IF($A22="",0,'02_Buyers'!$BD19) | H22: =IF($A22="",0,'02_Buyers'!$BE19) | I22: =IF($A22="",0,'02_Buyers'!$AB19) | J22: =IF($A22="","",F22-I22) | K22: =IF(OR($A22="",I22<=0),"",J22/I22) | L22: =IF($A22="","",IF(M22="대상 아님","대상 아님(L/C·선수금)",IF(AND(I22>0,K22<=-0.3),"감액 30%↑ — 사람 승인 필요",IF(J22>0,"증액 — 전결권자 승인","유지·소폭 감액")))) | M22: =IF($A22="","",'02_Buyers'!$BA19) | N22: =IF(OR($A22="",M22="대상 아님"),"",IF(F22<=50000,"채권관리팀장",IF(F22<=200000,"영업본부장","대표이사"))) | O22: =IF($A22="","",'02_Buyers'!$AG19) | Q22: =IF(OR($A22="",P22=""),"",F22-P22) | R22: =IF(OR($A22="",D22<=0),"",COUNTIFS($G$5:$G$154,G22,$D$5:$D$154,">0")) | T22: TWN | U22: 대만 | V22: 2 | W22: =IF(V22="","0-2",IF(V22<=2,"0-2",IF(V22=3,"3",IF(V22<=5,"4-5","6-7")))) | X22: =CHOOSE(MATCH(W22,{"0-2","3","4-5","6-7"},0),CtryCap_02,CtryCap_3,CtryCap_45,CtryCap_67) | Y22: =X22*TotalCap | Z22: =SUMPRODUCT((ctry=T22)*L) | AA22: =Y22-Z22 | AB22: =IF(AA22<=0.5,"걸림","")
A23: =IF('02_Buyers'!$A20="","",'02_Buyers'!$A20) | B23: =IF($A23="","",'02_Buyers'!$S20) | C23: =IF($A23="","",'02_Buyers'!$AK20) | D23: =IF($A23="",0,'02_Buyers'!$BB20) | E23: =IF($A23="",0,'02_Buyers'!$BC20) | F23: 0 | G23: =IF($A23="",0,'02_Buyers'!$BD20) | H23: =IF($A23="",0,'02_Buyers'!$BE20) | I23: =IF($A23="",0,'02_Buyers'!$AB20) | J23: =IF($A23="","",F23-I23) | K23: =IF(OR($A23="",I23<=0),"",J23/I23) | L23: =IF($A23="","",IF(M23="대상 아님","대상 아님(L/C·선수금)",IF(AND(I23>0,K23<=-0.3),"감액 30%↑ — 사람 승인 필요",IF(J23>0,"증액 — 전결권자 승인","유지·소폭 감액")))) | M23: =IF($A23="","",'02_Buyers'!$BA20) | N23: =IF(OR($A23="",M23="대상 아님"),"",IF(F23<=50000,"채권관리팀장",IF(F23<=200000,"영업본부장","대표이사"))) | O23: =IF($A23="","",'02_Buyers'!$AG20) | Q23: =IF(OR($A23="",P23=""),"",F23-P23) | R23: =IF(OR($A23="",D23<=0),"",COUNTIFS($G$5:$G$154,G23,$D$5:$D$154,">0")) | T23: VNM | U23: 베트남 | V23: 3 | W23: =IF(V23="","0-2",IF(V23<=2,"0-2",IF(V23=3,"3",IF(V23<=5,"4-5","6-7")))) | X23: =CHOOSE(MATCH(W23,{"0-2","3","4-5","6-7"},0),CtryCap_02,CtryCap_3,CtryCap_45,CtryCap_67) | Y23: =X23*TotalCap | Z23: =SUMPRODUCT((ctry=T23)*L) | AA23: =Y23-Z23 | AB23: =IF(AA23<=0.5,"걸림","")
A24: =IF('02_Buyers'!$A21="","",'02_Buyers'!$A21) | B24: =IF($A24="","",'02_Buyers'!$S21) | C24: =IF($A24="","",'02_Buyers'!$AK21) | D24: =IF($A24="",0,'02_Buyers'!$BB21) | E24: =IF($A24="",0,'02_Buyers'!$BC21) | F24: 0 | G24: =IF($A24="",0,'02_Buyers'!$BD21) | H24: =IF($A24="",0,'02_Buyers'!$BE21) | I24: =IF($A24="",0,'02_Buyers'!$AB21) | J24: =IF($A24="","",F24-I24) | K24: =IF(OR($A24="",I24<=0),"",J24/I24) | L24: =IF($A24="","",IF(M24="대상 아님","대상 아님(L/C·선수금)",IF(AND(I24>0,K24<=-0.3),"감액 30%↑ — 사람 승인 필요",IF(J24>0,"증액 — 전결권자 승인","유지·소폭 감액")))) | M24: =IF($A24="","",'02_Buyers'!$BA21) | N24: =IF(OR($A24="",M24="대상 아님"),"",IF(F24<=50000,"채권관리팀장",IF(F24<=200000,"영업본부장","대표이사"))) | O24: =IF($A24="","",'02_Buyers'!$AG21) | Q24: =IF(OR($A24="",P24=""),"",F24-P24) | R24: =IF(OR($A24="",D24<=0),"",COUNTIFS($G$5:$G$154,G24,$D$5:$D$154,">0")) | T24: IND | U24: 인도 | V24: 3 | W24: =IF(V24="","0-2",IF(V24<=2,"0-2",IF(V24=3,"3",IF(V24<=5,"4-5","6-7")))) | X24: =CHOOSE(MATCH(W24,{"0-2","3","4-5","6-7"},0),CtryCap_02,CtryCap_3,CtryCap_45,CtryCap_67) | Y24: =X24*TotalCap | Z24: =SUMPRODUCT((ctry=T24)*L) | AA24: =Y24-Z24 | AB24: =IF(AA24<=0.5,"걸림","")
A25: =IF('02_Buyers'!$A22="","",'02_Buyers'!$A22) | B25: =IF($A25="","",'02_Buyers'!$S22) | C25: =IF($A25="","",'02_Buyers'!$AK22) | D25: =IF($A25="",0,'02_Buyers'!$BB22) | E25: =IF($A25="",0,'02_Buyers'!$BC22) | F25: 0 | G25: =IF($A25="",0,'02_Buyers'!$BD22) | H25: =IF($A25="",0,'02_Buyers'!$BE22) | I25: =IF($A25="",0,'02_Buyers'!$AB22) | J25: =IF($A25="","",F25-I25) | K25: =IF(OR($A25="",I25<=0),"",J25/I25) | L25: =IF($A25="","",IF(M25="대상 아님","대상 아님(L/C·선수금)",IF(AND(I25>0,K25<=-0.3),"감액 30%↑ — 사람 승인 필요",IF(J25>0,"증액 — 전결권자 승인","유지·소폭 감액")))) | M25: =IF($A25="","",'02_Buyers'!$BA22) | N25: =IF(OR($A25="",M25="대상 아님"),"",IF(F25<=50000,"채권관리팀장",IF(F25<=200000,"영업본부장","대표이사"))) | O25: =IF($A25="","",'02_Buyers'!$AG22) | Q25: =IF(OR($A25="",P25=""),"",F25-P25) | R25: =IF(OR($A25="",D25<=0),"",COUNTIFS($G$5:$G$154,G25,$D$5:$D$154,">0")) | T25: IDN | U25: 인도네시아 | V25: 3 | W25: =IF(V25="","0-2",IF(V25<=2,"0-2",IF(V25=3,"3",IF(V25<=5,"4-5","6-7")))) | X25: =CHOOSE(MATCH(W25,{"0-2","3","4-5","6-7"},0),CtryCap_02,CtryCap_3,CtryCap_45,CtryCap_67) | Y25: =X25*TotalCap | Z25: =SUMPRODUCT((ctry=T25)*L) | AA25: =Y25-Z25 | AB25: =IF(AA25<=0.5,"걸림","")
A26: =IF('02_Buyers'!$A23="","",'02_Buyers'!$A23) | B26: =IF($A26="","",'02_Buyers'!$S23) | C26: =IF($A26="","",'02_Buyers'!$AK23) | D26: =IF($A26="",0,'02_Buyers'!$BB23) | E26: =IF($A26="",0,'02_Buyers'!$BC23) | F26: 0 | G26: =IF($A26="",0,'02_Buyers'!$BD23) | H26: =IF($A26="",0,'02_Buyers'!$BE23) | I26: =IF($A26="",0,'02_Buyers'!$AB23) | J26: =IF($A26="","",F26-I26) | K26: =IF(OR($A26="",I26<=0),"",J26/I26) | L26: =IF($A26="","",IF(M26="대상 아님","대상 아님(L/C·선수금)",IF(AND(I26>0,K26<=-0.3),"감액 30%↑ — 사람 승인 필요",IF(J26>0,"증액 — 전결권자 승인","유지·소폭 감액")))) | M26: =IF($A26="","",'02_Buyers'!$BA23) | N26: =IF(OR($A26="",M26="대상 아님"),"",IF(F26<=50000,"채권관리팀장",IF(F26<=200000,"영업본부장","대표이사"))) | O26: =IF($A26="","",'02_Buyers'!$AG23) | Q26: =IF(OR($A26="",P26=""),"",F26-P26) | R26: =IF(OR($A26="",D26<=0),"",COUNTIFS($G$5:$G$154,G26,$D$5:$D$154,">0")) | T26: THA | U26: 태국 | V26: 3 | W26: =IF(V26="","0-2",IF(V26<=2,"0-2",IF(V26=3,"3",IF(V26<=5,"4-5","6-7")))) | X26: =CHOOSE(MATCH(W26,{"0-2","3","4-5","6-7"},0),CtryCap_02,CtryCap_3,CtryCap_45,CtryCap_67) | Y26: =X26*TotalCap | Z26: =SUMPRODUCT((ctry=T26)*L) | AA26: =Y26-Z26 | AB26: =IF(AA26<=0.5,"걸림","")
A27: =IF('02_Buyers'!$A24="","",'02_Buyers'!$A24) | B27: =IF($A27="","",'02_Buyers'!$S24) | C27: =IF($A27="","",'02_Buyers'!$AK24) | D27: =IF($A27="",0,'02_Buyers'!$BB24) | E27: =IF($A27="",0,'02_Buyers'!$BC24) | F27: 0 | G27: =IF($A27="",0,'02_Buyers'!$BD24) | H27: =IF($A27="",0,'02_Buyers'!$BE24) | I27: =IF($A27="",0,'02_Buyers'!$AB24) | J27: =IF($A27="","",F27-I27) | K27: =IF(OR($A27="",I27<=0),"",J27/I27) | L27: =IF($A27="","",IF(M27="대상 아님","대상 아님(L/C·선수금)",IF(AND(I27>0,K27<=-0.3),"감액 30%↑ — 사람 승인 필요",IF(J27>0,"증액 — 전결권자 승인","유지·소폭 감액")))) | M27: =IF($A27="","",'02_Buyers'!$BA24) | N27: =IF(OR($A27="",M27="대상 아님"),"",IF(F27<=50000,"채권관리팀장",IF(F27<=200000,"영업본부장","대표이사"))) | O27: =IF($A27="","",'02_Buyers'!$AG24) | Q27: =IF(OR($A27="",P27=""),"",F27-P27) | R27: =IF(OR($A27="",D27<=0),"",COUNTIFS($G$5:$G$154,G27,$D$5:$D$154,">0")) | T27: MYS | U27: 말레이시아 | V27: 2 | W27: =IF(V27="","0-2",IF(V27<=2,"0-2",IF(V27=3,"3",IF(V27<=5,"4-5","6-7")))) | X27: =CHOOSE(MATCH(W27,{"0-2","3","4-5","6-7"},0),CtryCap_02,CtryCap_3,CtryCap_45,CtryCap_67) | Y27: =X27*TotalCap | Z27: =SUMPRODUCT((ctry=T27)*L) | AA27: =Y27-Z27 | AB27: =IF(AA27<=0.5,"걸림","")
A28: =IF('02_Buyers'!$A25="","",'02_Buyers'!$A25) | B28: =IF($A28="","",'02_Buyers'!$S25) | C28: =IF($A28="","",'02_Buyers'!$AK25) | D28: =IF($A28="",0,'02_Buyers'!$BB25) | E28: =IF($A28="",0,'02_Buyers'!$BC25) | F28: 0 | G28: =IF($A28="",0,'02_Buyers'!$BD25) | H28: =IF($A28="",0,'02_Buyers'!$BE25) | I28: =IF($A28="",0,'02_Buyers'!$AB25) | J28: =IF($A28="","",F28-I28) | K28: =IF(OR($A28="",I28<=0),"",J28/I28) | L28: =IF($A28="","",IF(M28="대상 아님","대상 아님(L/C·선수금)",IF(AND(I28>0,K28<=-0.3),"감액 30%↑ — 사람 승인 필요",IF(J28>0,"증액 — 전결권자 승인","유지·소폭 감액")))) | M28: =IF($A28="","",'02_Buyers'!$BA25) | N28: =IF(OR($A28="",M28="대상 아님"),"",IF(F28<=50000,"채권관리팀장",IF(F28<=200000,"영업본부장","대표이사"))) | O28: =IF($A28="","",'02_Buyers'!$AG25) | Q28: =IF(OR($A28="",P28=""),"",F28-P28) | R28: =IF(OR($A28="",D28<=0),"",COUNTIFS($G$5:$G$154,G28,$D$5:$D$154,">0")) | T28: ARE | U28: 아랍에미리트 | V28: 2 | W28: =IF(V28="","0-2",IF(V28<=2,"0-2",IF(V28=3,"3",IF(V28<=5,"4-5","6-7")))) | X28: =CHOOSE(MATCH(W28,{"0-2","3","4-5","6-7"},0),CtryCap_02,CtryCap_3,CtryCap_45,CtryCap_67) | Y28: =X28*TotalCap | Z28: =SUMPRODUCT((ctry=T28)*L) | AA28: =Y28-Z28 | AB28: =IF(AA28<=0.5,"걸림","")
A29: =IF('02_Buyers'!$A26="","",'02_Buyers'!$A26) | B29: =IF($A29="","",'02_Buyers'!$S26) | C29: =IF($A29="","",'02_Buyers'!$AK26) | D29: =IF($A29="",0,'02_Buyers'!$BB26) | E29: =IF($A29="",0,'02_Buyers'!$BC26) | F29: 0 | G29: =IF($A29="",0,'02_Buyers'!$BD26) | H29: =IF($A29="",0,'02_Buyers'!$BE26) | I29: =IF($A29="",0,'02_Buyers'!$AB26) | J29: =IF($A29="","",F29-I29) | K29: =IF(OR($A29="",I29<=0),"",J29/I29) | L29: =IF($A29="","",IF(M29="대상 아님","대상 아님(L/C·선수금)",IF(AND(I29>0,K29<=-0.3),"감액 30%↑ — 사람 승인 필요",IF(J29>0,"증액 — 전결권자 승인","유지·소폭 감액")))) | M29: =IF($A29="","",'02_Buyers'!$BA26) | N29: =IF(OR($A29="",M29="대상 아님"),"",IF(F29<=50000,"채권관리팀장",IF(F29<=200000,"영업본부장","대표이사"))) | O29: =IF($A29="","",'02_Buyers'!$AG26) | Q29: =IF(OR($A29="",P29=""),"",F29-P29) | R29: =IF(OR($A29="",D29<=0),"",COUNTIFS($G$5:$G$154,G29,$D$5:$D$154,">0")) | T29: SAU | U29: 사우디아라비아 | V29: 2 | W29: =IF(V29="","0-2",IF(V29<=2,"0-2",IF(V29=3,"3",IF(V29<=5,"4-5","6-7")))) | X29: =CHOOSE(MATCH(W29,{"0-2","3","4-5","6-7"},0),CtryCap_02,CtryCap_3,CtryCap_45,CtryCap_67) | Y29: =X29*TotalCap | Z29: =SUMPRODUCT((ctry=T29)*L) | AA29: =Y29-Z29 | AB29: =IF(AA29<=0.5,"걸림","")
A30: =IF('02_Buyers'!$A27="","",'02_Buyers'!$A27) | B30: =IF($A30="","",'02_Buyers'!$S27) | C30: =IF($A30="","",'02_Buyers'!$AK27) | D30: =IF($A30="",0,'02_Buyers'!$BB27) | E30: =IF($A30="",0,'02_Buyers'!$BC27) | F30: 0 | G30: =IF($A30="",0,'02_Buyers'!$BD27) | H30: =IF($A30="",0,'02_Buyers'!$BE27) | I30: =IF($A30="",0,'02_Buyers'!$AB27) | J30: =IF($A30="","",F30-I30) | K30: =IF(OR($A30="",I30<=0),"",J30/I30) | L30: =IF($A30="","",IF(M30="대상 아님","대상 아님(L/C·선수금)",IF(AND(I30>0,K30<=-0.3),"감액 30%↑ — 사람 승인 필요",IF(J30>0,"증액 — 전결권자 승인","유지·소폭 감액")))) | M30: =IF($A30="","",'02_Buyers'!$BA27) | N30: =IF(OR($A30="",M30="대상 아님"),"",IF(F30<=50000,"채권관리팀장",IF(F30<=200000,"영업본부장","대표이사"))) | O30: =IF($A30="","",'02_Buyers'!$AG27) | Q30: =IF(OR($A30="",P30=""),"",F30-P30) | R30: =IF(OR($A30="",D30<=0),"",COUNTIFS($G$5:$G$154,G30,$D$5:$D$154,">0")) | T30: EGY | U30: 이집트 | V30: 6 | W30: =IF(V30="","0-2",IF(V30<=2,"0-2",IF(V30=3,"3",IF(V30<=5,"4-5","6-7")))) | X30: =CHOOSE(MATCH(W30,{"0-2","3","4-5","6-7"},0),CtryCap_02,CtryCap_3,CtryCap_45,CtryCap_67) | Y30: =X30*TotalCap | Z30: =SUMPRODUCT((ctry=T30)*L) | AA30: =Y30-Z30 | AB30: =IF(AA30<=0.5,"걸림","")
A31: =IF('02_Buyers'!$A28="","",'02_Buyers'!$A28) | B31: =IF($A31="","",'02_Buyers'!$S28) | C31: =IF($A31="","",'02_Buyers'!$AK28) | D31: =IF($A31="",0,'02_Buyers'!$BB28) | E31: =IF($A31="",0,'02_Buyers'!$BC28) | F31: 0 | G31: =IF($A31="",0,'02_Buyers'!$BD28) | H31: =IF($A31="",0,'02_Buyers'!$BE28) | I31: =IF($A31="",0,'02_Buyers'!$AB28) | J31: =IF($A31="","",F31-I31) | K31: =IF(OR($A31="",I31<=0),"",J31/I31) | L31: =IF($A31="","",IF(M31="대상 아님","대상 아님(L/C·선수금)",IF(AND(I31>0,K31<=-0.3),"감액 30%↑ — 사람 승인 필요",IF(J31>0,"증액 — 전결권자 승인","유지·소폭 감액")))) | M31: =IF($A31="","",'02_Buyers'!$BA28) | N31: =IF(OR($A31="",M31="대상 아님"),"",IF(F31<=50000,"채권관리팀장",IF(F31<=200000,"영업본부장","대표이사"))) | O31: =IF($A31="","",'02_Buyers'!$AG28) | Q31: =IF(OR($A31="",P31=""),"",F31-P31) | R31: =IF(OR($A31="",D31<=0),"",COUNTIFS($G$5:$G$154,G31,$D$5:$D$154,">0")) | T31: NGA | U31: 나이지리아 | V31: 6 | W31: =IF(V31="","0-2",IF(V31<=2,"0-2",IF(V31=3,"3",IF(V31<=5,"4-5","6-7")))) | X31: =CHOOSE(MATCH(W31,{"0-2","3","4-5","6-7"},0),CtryCap_02,CtryCap_3,CtryCap_45,CtryCap_67) | Y31: =X31*TotalCap | Z31: =SUMPRODUCT((ctry=T31)*L) | AA31: =Y31-Z31 | AB31: =IF(AA31<=0.5,"걸림","")
A32: =IF('02_Buyers'!$A29="","",'02_Buyers'!$A29) | B32: =IF($A32="","",'02_Buyers'!$S29) | C32: =IF($A32="","",'02_Buyers'!$AK29) | D32: =IF($A32="",0,'02_Buyers'!$BB29) | E32: =IF($A32="",0,'02_Buyers'!$BC29) | F32: 0 | G32: =IF($A32="",0,'02_Buyers'!$BD29) | H32: =IF($A32="",0,'02_Buyers'!$BE29) | I32: =IF($A32="",0,'02_Buyers'!$AB29) | J32: =IF($A32="","",F32-I32) | K32: =IF(OR($A32="",I32<=0),"",J32/I32) | L32: =IF($A32="","",IF(M32="대상 아님","대상 아님(L/C·선수금)",IF(AND(I32>0,K32<=-0.3),"감액 30%↑ — 사람 승인 필요",IF(J32>0,"증액 — 전결권자 승인","유지·소폭 감액")))) | M32: =IF($A32="","",'02_Buyers'!$BA29) | N32: =IF(OR($A32="",M32="대상 아님"),"",IF(F32<=50000,"채권관리팀장",IF(F32<=200000,"영업본부장","대표이사"))) | O32: =IF($A32="","",'02_Buyers'!$AG29) | Q32: =IF(OR($A32="",P32=""),"",F32-P32) | R32: =IF(OR($A32="",D32<=0),"",COUNTIFS($G$5:$G$154,G32,$D$5:$D$154,">0"))
A33: =IF('02_Buyers'!$A30="","",'02_Buyers'!$A30) | B33: =IF($A33="","",'02_Buyers'!$S30) | C33: =IF($A33="","",'02_Buyers'!$AK30) | D33: =IF($A33="",0,'02_Buyers'!$BB30) | E33: =IF($A33="",0,'02_Buyers'!$BC30) | F33: 0 | G33: =IF($A33="",0,'02_Buyers'!$BD30) | H33: =IF($A33="",0,'02_Buyers'!$BE30) | I33: =IF($A33="",0,'02_Buyers'!$AB30) | J33: =IF($A33="","",F33-I33) | K33: =IF(OR($A33="",I33<=0),"",J33/I33) | L33: =IF($A33="","",IF(M33="대상 아님","대상 아님(L/C·선수금)",IF(AND(I33>0,K33<=-0.3),"감액 30%↑ — 사람 승인 필요",IF(J33>0,"증액 — 전결권자 승인","유지·소폭 감액")))) | M33: =IF($A33="","",'02_Buyers'!$BA30) | N33: =IF(OR($A33="",M33="대상 아님"),"",IF(F33<=50000,"채권관리팀장",IF(F33<=200000,"영업본부장","대표이사"))) | O33: =IF($A33="","",'02_Buyers'!$AG30) | Q33: =IF(OR($A33="",P33=""),"",F33-P33) | R33: =IF(OR($A33="",D33<=0),"",COUNTIFS($G$5:$G$154,G33,$D$5:$D$154,">0"))
A34: =IF('02_Buyers'!$A31="","",'02_Buyers'!$A31) | B34: =IF($A34="","",'02_Buyers'!$S31) | C34: =IF($A34="","",'02_Buyers'!$AK31) | D34: =IF($A34="",0,'02_Buyers'!$BB31) | E34: =IF($A34="",0,'02_Buyers'!$BC31) | F34: 0 | G34: =IF($A34="",0,'02_Buyers'!$BD31) | H34: =IF($A34="",0,'02_Buyers'!$BE31) | I34: =IF($A34="",0,'02_Buyers'!$AB31) | J34: =IF($A34="","",F34-I34) | K34: =IF(OR($A34="",I34<=0),"",J34/I34) | L34: =IF($A34="","",IF(M34="대상 아님","대상 아님(L/C·선수금)",IF(AND(I34>0,K34<=-0.3),"감액 30%↑ — 사람 승인 필요",IF(J34>0,"증액 — 전결권자 승인","유지·소폭 감액")))) | M34: =IF($A34="","",'02_Buyers'!$BA31) | N34: =IF(OR($A34="",M34="대상 아님"),"",IF(F34<=50000,"채권관리팀장",IF(F34<=200000,"영업본부장","대표이사"))) | O34: =IF($A34="","",'02_Buyers'!$AG31) | Q34: =IF(OR($A34="",P34=""),"",F34-P34) | R34: =IF(OR($A34="",D34<=0),"",COUNTIFS($G$5:$G$154,G34,$D$5:$D$154,">0"))
A35: =IF('02_Buyers'!$A32="","",'02_Buyers'!$A32) | B35: =IF($A35="","",'02_Buyers'!$S32) | C35: =IF($A35="","",'02_Buyers'!$AK32) | D35: =IF($A35="",0,'02_Buyers'!$BB32) | E35: =IF($A35="",0,'02_Buyers'!$BC32) | F35: 0 | G35: =IF($A35="",0,'02_Buyers'!$BD32) | H35: =IF($A35="",0,'02_Buyers'!$BE32) | I35: =IF($A35="",0,'02_Buyers'!$AB32) | J35: =IF($A35="","",F35-I35) | K35: =IF(OR($A35="",I35<=0),"",J35/I35) | L35: =IF($A35="","",IF(M35="대상 아님","대상 아님(L/C·선수금)",IF(AND(I35>0,K35<=-0.3),"감액 30%↑ — 사람 승인 필요",IF(J35>0,"증액 — 전결권자 승인","유지·소폭 감액")))) | M35: =IF($A35="","",'02_Buyers'!$BA32) | N35: =IF(OR($A35="",M35="대상 아님"),"",IF(F35<=50000,"채권관리팀장",IF(F35<=200000,"영업본부장","대표이사"))) | O35: =IF($A35="","",'02_Buyers'!$AG32) | Q35: =IF(OR($A35="",P35=""),"",F35-P35) | R35: =IF(OR($A35="",D35<=0),"",COUNTIFS($G$5:$G$154,G35,$D$5:$D$154,">0"))
A36: =IF('02_Buyers'!$A33="","",'02_Buyers'!$A33) | B36: =IF($A36="","",'02_Buyers'!$S33) | C36: =IF($A36="","",'02_Buyers'!$AK33) | D36: =IF($A36="",0,'02_Buyers'!$BB33) | E36: =IF($A36="",0,'02_Buyers'!$BC33) | F36: 0 | G36: =IF($A36="",0,'02_Buyers'!$BD33) | H36: =IF($A36="",0,'02_Buyers'!$BE33) | I36: =IF($A36="",0,'02_Buyers'!$AB33) | J36: =IF($A36="","",F36-I36) | K36: =IF(OR($A36="",I36<=0),"",J36/I36) | L36: =IF($A36="","",IF(M36="대상 아님","대상 아님(L/C·선수금)",IF(AND(I36>0,K36<=-0.3),"감액 30%↑ — 사람 승인 필요",IF(J36>0,"증액 — 전결권자 승인","유지·소폭 감액")))) | M36: =IF($A36="","",'02_Buyers'!$BA33) | N36: =IF(OR($A36="",M36="대상 아님"),"",IF(F36<=50000,"채권관리팀장",IF(F36<=200000,"영업본부장","대표이사"))) | O36: =IF($A36="","",'02_Buyers'!$AG33) | Q36: =IF(OR($A36="",P36=""),"",F36-P36) | R36: =IF(OR($A36="",D36<=0),"",COUNTIFS($G$5:$G$154,G36,$D$5:$D$154,">0"))
A37: =IF('02_Buyers'!$A34="","",'02_Buyers'!$A34) | B37: =IF($A37="","",'02_Buyers'!$S34) | C37: =IF($A37="","",'02_Buyers'!$AK34) | D37: =IF($A37="",0,'02_Buyers'!$BB34) | E37: =IF($A37="",0,'02_Buyers'!$BC34) | F37: 0 | G37: =IF($A37="",0,'02_Buyers'!$BD34) | H37: =IF($A37="",0,'02_Buyers'!$BE34) | I37: =IF($A37="",0,'02_Buyers'!$AB34) | J37: =IF($A37="","",F37-I37) | K37: =IF(OR($A37="",I37<=0),"",J37/I37) | L37: =IF($A37="","",IF(M37="대상 아님","대상 아님(L/C·선수금)",IF(AND(I37>0,K37<=-0.3),"감액 30%↑ — 사람 승인 필요",IF(J37>0,"증액 — 전결권자 승인","유지·소폭 감액")))) | M37: =IF($A37="","",'02_Buyers'!$BA34) | N37: =IF(OR($A37="",M37="대상 아님"),"",IF(F37<=50000,"채권관리팀장",IF(F37<=200000,"영업본부장","대표이사"))) | O37: =IF($A37="","",'02_Buyers'!$AG34) | Q37: =IF(OR($A37="",P37=""),"",F37-P37) | R37: =IF(OR($A37="",D37<=0),"",COUNTIFS($G$5:$G$154,G37,$D$5:$D$154,">0")) | T37: 등급 | U37: 바이어 수 | V37: 현행 한도 | W37: 해 찾기 L
A38: =IF('02_Buyers'!$A35="","",'02_Buyers'!$A35) | B38: =IF($A38="","",'02_Buyers'!$S35) | C38: =IF($A38="","",'02_Buyers'!$AK35) | D38: =IF($A38="",0,'02_Buyers'!$BB35) | E38: =IF($A38="",0,'02_Buyers'!$BC35) | F38: 0 | G38: =IF($A38="",0,'02_Buyers'!$BD35) | H38: =IF($A38="",0,'02_Buyers'!$BE35) | I38: =IF($A38="",0,'02_Buyers'!$AB35) | J38: =IF($A38="","",F38-I38) | K38: =IF(OR($A38="",I38<=0),"",J38/I38) | L38: =IF($A38="","",IF(M38="대상 아님","대상 아님(L/C·선수금)",IF(AND(I38>0,K38<=-0.3),"감액 30%↑ — 사람 승인 필요",IF(J38>0,"증액 — 전결권자 승인","유지·소폭 감액")))) | M38: =IF($A38="","",'02_Buyers'!$BA35) | N38: =IF(OR($A38="",M38="대상 아님"),"",IF(F38<=50000,"채권관리팀장",IF(F38<=200000,"영업본부장","대표이사"))) | O38: =IF($A38="","",'02_Buyers'!$AG35) | Q38: =IF(OR($A38="",P38=""),"",F38-P38) | R38: =IF(OR($A38="",D38<=0),"",COUNTIFS($G$5:$G$154,G38,$D$5:$D$154,">0")) | T38: S | U38: =COUNTIF(grade_lp,"S") | V38: =SUMIFS(cur_limit,grade_lp,"S") | W38: =SUMIFS(L,grade_lp,"S")
A39: =IF('02_Buyers'!$A36="","",'02_Buyers'!$A36) | B39: =IF($A39="","",'02_Buyers'!$S36) | C39: =IF($A39="","",'02_Buyers'!$AK36) | D39: =IF($A39="",0,'02_Buyers'!$BB36) | E39: =IF($A39="",0,'02_Buyers'!$BC36) | F39: 0 | G39: =IF($A39="",0,'02_Buyers'!$BD36) | H39: =IF($A39="",0,'02_Buyers'!$BE36) | I39: =IF($A39="",0,'02_Buyers'!$AB36) | J39: =IF($A39="","",F39-I39) | K39: =IF(OR($A39="",I39<=0),"",J39/I39) | L39: =IF($A39="","",IF(M39="대상 아님","대상 아님(L/C·선수금)",IF(AND(I39>0,K39<=-0.3),"감액 30%↑ — 사람 승인 필요",IF(J39>0,"증액 — 전결권자 승인","유지·소폭 감액")))) | M39: =IF($A39="","",'02_Buyers'!$BA36) | N39: =IF(OR($A39="",M39="대상 아님"),"",IF(F39<=50000,"채권관리팀장",IF(F39<=200000,"영업본부장","대표이사"))) | O39: =IF($A39="","",'02_Buyers'!$AG36) | Q39: =IF(OR($A39="",P39=""),"",F39-P39) | R39: =IF(OR($A39="",D39<=0),"",COUNTIFS($G$5:$G$154,G39,$D$5:$D$154,">0")) | T39: A | U39: =COUNTIF(grade_lp,"A") | V39: =SUMIFS(cur_limit,grade_lp,"A") | W39: =SUMIFS(L,grade_lp,"A")
A40: =IF('02_Buyers'!$A37="","",'02_Buyers'!$A37) | B40: =IF($A40="","",'02_Buyers'!$S37) | C40: =IF($A40="","",'02_Buyers'!$AK37) | D40: =IF($A40="",0,'02_Buyers'!$BB37) | E40: =IF($A40="",0,'02_Buyers'!$BC37) | F40: 0 | G40: =IF($A40="",0,'02_Buyers'!$BD37) | H40: =IF($A40="",0,'02_Buyers'!$BE37) | I40: =IF($A40="",0,'02_Buyers'!$AB37) | J40: =IF($A40="","",F40-I40) | K40: =IF(OR($A40="",I40<=0),"",J40/I40) | L40: =IF($A40="","",IF(M40="대상 아님","대상 아님(L/C·선수금)",IF(AND(I40>0,K40<=-0.3),"감액 30%↑ — 사람 승인 필요",IF(J40>0,"증액 — 전결권자 승인","유지·소폭 감액")))) | M40: =IF($A40="","",'02_Buyers'!$BA37) | N40: =IF(OR($A40="",M40="대상 아님"),"",IF(F40<=50000,"채권관리팀장",IF(F40<=200000,"영업본부장","대표이사"))) | O40: =IF($A40="","",'02_Buyers'!$AG37) | Q40: =IF(OR($A40="",P40=""),"",F40-P40) | R40: =IF(OR($A40="",D40<=0),"",COUNTIFS($G$5:$G$154,G40,$D$5:$D$154,">0")) | T40: B | U40: =COUNTIF(grade_lp,"B") | V40: =SUMIFS(cur_limit,grade_lp,"B") | W40: =SUMIFS(L,grade_lp,"B")
A41: =IF('02_Buyers'!$A38="","",'02_Buyers'!$A38) | B41: =IF($A41="","",'02_Buyers'!$S38) | C41: =IF($A41="","",'02_Buyers'!$AK38) | D41: =IF($A41="",0,'02_Buyers'!$BB38) | E41: =IF($A41="",0,'02_Buyers'!$BC38) | F41: 0 | G41: =IF($A41="",0,'02_Buyers'!$BD38) | H41: =IF($A41="",0,'02_Buyers'!$BE38) | I41: =IF($A41="",0,'02_Buyers'!$AB38) | J41: =IF($A41="","",F41-I41) | K41: =IF(OR($A41="",I41<=0),"",J41/I41) | L41: =IF($A41="","",IF(M41="대상 아님","대상 아님(L/C·선수금)",IF(AND(I41>0,K41<=-0.3),"감액 30%↑ — 사람 승인 필요",IF(J41>0,"증액 — 전결권자 승인","유지·소폭 감액")))) | M41: =IF($A41="","",'02_Buyers'!$BA38) | N41: =IF(OR($A41="",M41="대상 아님"),"",IF(F41<=50000,"채권관리팀장",IF(F41<=200000,"영업본부장","대표이사"))) | O41: =IF($A41="","",'02_Buyers'!$AG38) | Q41: =IF(OR($A41="",P41=""),"",F41-P41) | R41: =IF(OR($A41="",D41<=0),"",COUNTIFS($G$5:$G$154,G41,$D$5:$D$154,">0")) | T41: C | U41: =COUNTIF(grade_lp,"C") | V41: =SUMIFS(cur_limit,grade_lp,"C") | W41: =SUMIFS(L,grade_lp,"C")
A42: =IF('02_Buyers'!$A39="","",'02_Buyers'!$A39) | B42: =IF($A42="","",'02_Buyers'!$S39) | C42: =IF($A42="","",'02_Buyers'!$AK39) | D42: =IF($A42="",0,'02_Buyers'!$BB39) | E42: =IF($A42="",0,'02_Buyers'!$BC39) | F42: 0 | G42: =IF($A42="",0,'02_Buyers'!$BD39) | H42: =IF($A42="",0,'02_Buyers'!$BE39) | I42: =IF($A42="",0,'02_Buyers'!$AB39) | J42: =IF($A42="","",F42-I42) | K42: =IF(OR($A42="",I42<=0),"",J42/I42) | L42: =IF($A42="","",IF(M42="대상 아님","대상 아님(L/C·선수금)",IF(AND(I42>0,K42<=-0.3),"감액 30%↑ — 사람 승인 필요",IF(J42>0,"증액 — 전결권자 승인","유지·소폭 감액")))) | M42: =IF($A42="","",'02_Buyers'!$BA39) | N42: =IF(OR($A42="",M42="대상 아님"),"",IF(F42<=50000,"채권관리팀장",IF(F42<=200000,"영업본부장","대표이사"))) | O42: =IF($A42="","",'02_Buyers'!$AG39) | Q42: =IF(OR($A42="",P42=""),"",F42-P42) | R42: =IF(OR($A42="",D42<=0),"",COUNTIFS($G$5:$G$154,G42,$D$5:$D$154,">0"))
A43: =IF('02_Buyers'!$A40="","",'02_Buyers'!$A40) | B43: =IF($A43="","",'02_Buyers'!$S40) | C43: =IF($A43="","",'02_Buyers'!$AK40) | D43: =IF($A43="",0,'02_Buyers'!$BB40) | E43: =IF($A43="",0,'02_Buyers'!$BC40) | F43: 0 | G43: =IF($A43="",0,'02_Buyers'!$BD40) | H43: =IF($A43="",0,'02_Buyers'!$BE40) | I43: =IF($A43="",0,'02_Buyers'!$AB40) | J43: =IF($A43="","",F43-I43) | K43: =IF(OR($A43="",I43<=0),"",J43/I43) | L43: =IF($A43="","",IF(M43="대상 아님","대상 아님(L/C·선수금)",IF(AND(I43>0,K43<=-0.3),"감액 30%↑ — 사람 승인 필요",IF(J43>0,"증액 — 전결권자 승인","유지·소폭 감액")))) | M43: =IF($A43="","",'02_Buyers'!$BA40) | N43: =IF(OR($A43="",M43="대상 아님"),"",IF(F43<=50000,"채권관리팀장",IF(F43<=200000,"영업본부장","대표이사"))) | O43: =IF($A43="","",'02_Buyers'!$AG40) | Q43: =IF(OR($A43="",P43=""),"",F43-P43) | R43: =IF(OR($A43="",D43<=0),"",COUNTIFS($G$5:$G$154,G43,$D$5:$D$154,">0"))
A44: =IF('02_Buyers'!$A41="","",'02_Buyers'!$A41) | B44: =IF($A44="","",'02_Buyers'!$S41) | C44: =IF($A44="","",'02_Buyers'!$AK41) | D44: =IF($A44="",0,'02_Buyers'!$BB41) | E44: =IF($A44="",0,'02_Buyers'!$BC41) | F44: 0 | G44: =IF($A44="",0,'02_Buyers'!$BD41) | H44: =IF($A44="",0,'02_Buyers'!$BE41) | I44: =IF($A44="",0,'02_Buyers'!$AB41) | J44: =IF($A44="","",F44-I44) | K44: =IF(OR($A44="",I44<=0),"",J44/I44) | L44: =IF($A44="","",IF(M44="대상 아님","대상 아님(L/C·선수금)",IF(AND(I44>0,K44<=-0.3),"감액 30%↑ — 사람 승인 필요",IF(J44>0,"증액 — 전결권자 승인","유지·소폭 감액")))) | M44: =IF($A44="","",'02_Buyers'!$BA41) | N44: =IF(OR($A44="",M44="대상 아님"),"",IF(F44<=50000,"채권관리팀장",IF(F44<=200000,"영업본부장","대표이사"))) | O44: =IF($A44="","",'02_Buyers'!$AG41) | Q44: =IF(OR($A44="",P44=""),"",F44-P44) | R44: =IF(OR($A44="",D44<=0),"",COUNTIFS($G$5:$G$154,G44,$D$5:$D$154,">0")) | T44: 해 찾기 입력표(대화상자가 비어 있으면 그대로 입력)
A45: =IF('02_Buyers'!$A42="","",'02_Buyers'!$A42) | B45: =IF($A45="","",'02_Buyers'!$S42) | C45: =IF($A45="","",'02_Buyers'!$AK42) | D45: =IF($A45="",0,'02_Buyers'!$BB42) | E45: =IF($A45="",0,'02_Buyers'!$BC42) | F45: 0 | G45: =IF($A45="",0,'02_Buyers'!$BD42) | H45: =IF($A45="",0,'02_Buyers'!$BE42) | I45: =IF($A45="",0,'02_Buyers'!$AB42) | J45: =IF($A45="","",F45-I45) | K45: =IF(OR($A45="",I45<=0),"",J45/I45) | L45: =IF($A45="","",IF(M45="대상 아님","대상 아님(L/C·선수금)",IF(AND(I45>0,K45<=-0.3),"감액 30%↑ — 사람 승인 필요",IF(J45>0,"증액 — 전결권자 승인","유지·소폭 감액")))) | M45: =IF($A45="","",'02_Buyers'!$BA42) | N45: =IF(OR($A45="",M45="대상 아님"),"",IF(F45<=50000,"채권관리팀장",IF(F45<=200000,"영업본부장","대표이사"))) | O45: =IF($A45="","",'02_Buyers'!$AG42) | Q45: =IF(OR($A45="",P45=""),"",F45-P45) | R45: =IF(OR($A45="",D45<=0),"",COUNTIFS($G$5:$G$154,G45,$D$5:$D$154,">0")) | T45: 목표 설정: $C$2 (Obj) → 최대값
A46: =IF('02_Buyers'!$A43="","",'02_Buyers'!$A43) | B46: =IF($A46="","",'02_Buyers'!$S43) | C46: =IF($A46="","",'02_Buyers'!$AK43) | D46: =IF($A46="",0,'02_Buyers'!$BB43) | E46: =IF($A46="",0,'02_Buyers'!$BC43) | F46: 0 | G46: =IF($A46="",0,'02_Buyers'!$BD43) | H46: =IF($A46="",0,'02_Buyers'!$BE43) | I46: =IF($A46="",0,'02_Buyers'!$AB43) | J46: =IF($A46="","",F46-I46) | K46: =IF(OR($A46="",I46<=0),"",J46/I46) | L46: =IF($A46="","",IF(M46="대상 아님","대상 아님(L/C·선수금)",IF(AND(I46>0,K46<=-0.3),"감액 30%↑ — 사람 승인 필요",IF(J46>0,"증액 — 전결권자 승인","유지·소폭 감액")))) | M46: =IF($A46="","",'02_Buyers'!$BA43) | N46: =IF(OR($A46="",M46="대상 아님"),"",IF(F46<=50000,"채권관리팀장",IF(F46<=200000,"영업본부장","대표이사"))) | O46: =IF($A46="","",'02_Buyers'!$AG43) | Q46: =IF(OR($A46="",P46=""),"",F46-P46) | R46: =IF(OR($A46="",D46<=0),"",COUNTIFS($G$5:$G$154,G46,$D$5:$D$154,">0")) | T46: 변수 셀 변경: $F$5:$F$154 (L)
A47: =IF('02_Buyers'!$A44="","",'02_Buyers'!$A44) | B47: =IF($A47="","",'02_Buyers'!$S44) | C47: =IF($A47="","",'02_Buyers'!$AK44) | D47: =IF($A47="",0,'02_Buyers'!$BB44) | E47: =IF($A47="",0,'02_Buyers'!$BC44) | F47: 0 | G47: =IF($A47="",0,'02_Buyers'!$BD44) | H47: =IF($A47="",0,'02_Buyers'!$BE44) | I47: =IF($A47="",0,'02_Buyers'!$AB44) | J47: =IF($A47="","",F47-I47) | K47: =IF(OR($A47="",I47<=0),"",J47/I47) | L47: =IF($A47="","",IF(M47="대상 아님","대상 아님(L/C·선수금)",IF(AND(I47>0,K47<=-0.3),"감액 30%↑ — 사람 승인 필요",IF(J47>0,"증액 — 전결권자 승인","유지·소폭 감액")))) | M47: =IF($A47="","",'02_Buyers'!$BA44) | N47: =IF(OR($A47="",M47="대상 아님"),"",IF(F47<=50000,"채권관리팀장",IF(F47<=200000,"영업본부장","대표이사"))) | O47: =IF($A47="","",'02_Buyers'!$AG44) | Q47: =IF(OR($A47="",P47=""),"",F47-P47) | R47: =IF(OR($A47="",D47<=0),"",COUNTIFS($G$5:$G$154,G47,$D$5:$D$154,">0")) | T47: 제약 1: $F$5:$F$154 <= $D$5:$D$154 (L ≤ UB)
A48: =IF('02_Buyers'!$A45="","",'02_Buyers'!$A45) | B48: =IF($A48="","",'02_Buyers'!$S45) | C48: =IF($A48="","",'02_Buyers'!$AK45) | D48: =IF($A48="",0,'02_Buyers'!$BB45) | E48: =IF($A48="",0,'02_Buyers'!$BC45) | F48: 0 | G48: =IF($A48="",0,'02_Buyers'!$BD45) | H48: =IF($A48="",0,'02_Buyers'!$BE45) | I48: =IF($A48="",0,'02_Buyers'!$AB45) | J48: =IF($A48="","",F48-I48) | K48: =IF(OR($A48="",I48<=0),"",J48/I48) | L48: =IF($A48="","",IF(M48="대상 아님","대상 아님(L/C·선수금)",IF(AND(I48>0,K48<=-0.3),"감액 30%↑ — 사람 승인 필요",IF(J48>0,"증액 — 전결권자 승인","유지·소폭 감액")))) | M48: =IF($A48="","",'02_Buyers'!$BA45) | N48: =IF(OR($A48="",M48="대상 아님"),"",IF(F48<=50000,"채권관리팀장",IF(F48<=200000,"영업본부장","대표이사"))) | O48: =IF($A48="","",'02_Buyers'!$AG45) | Q48: =IF(OR($A48="",P48=""),"",F48-P48) | R48: =IF(OR($A48="",D48<=0),"",COUNTIFS($G$5:$G$154,G48,$D$5:$D$154,">0")) | T48: 제약 2: $F$5:$F$154 >= $E$5:$E$154 (L ≥ LB)
A49: =IF('02_Buyers'!$A46="","",'02_Buyers'!$A46) | B49: =IF($A49="","",'02_Buyers'!$S46) | C49: =IF($A49="","",'02_Buyers'!$AK46) | D49: =IF($A49="",0,'02_Buyers'!$BB46) | E49: =IF($A49="",0,'02_Buyers'!$BC46) | F49: 0 | G49: =IF($A49="",0,'02_Buyers'!$BD46) | H49: =IF($A49="",0,'02_Buyers'!$BE46) | I49: =IF($A49="",0,'02_Buyers'!$AB46) | J49: =IF($A49="","",F49-I49) | K49: =IF(OR($A49="",I49<=0),"",J49/I49) | L49: =IF($A49="","",IF(M49="대상 아님","대상 아님(L/C·선수금)",IF(AND(I49>0,K49<=-0.3),"감액 30%↑ — 사람 승인 필요",IF(J49>0,"증액 — 전결권자 승인","유지·소폭 감액")))) | M49: =IF($A49="","",'02_Buyers'!$BA46) | N49: =IF(OR($A49="",M49="대상 아님"),"",IF(F49<=50000,"채권관리팀장",IF(F49<=200000,"영업본부장","대표이사"))) | O49: =IF($A49="","",'02_Buyers'!$AG46) | Q49: =IF(OR($A49="",P49=""),"",F49-P49) | R49: =IF(OR($A49="",D49<=0),"",COUNTIFS($G$5:$G$154,G49,$D$5:$D$154,">0")) | T49: 제약 3: $U$5 <= $W$5 (TotalL ≤ TotalCap)
A50: =IF('02_Buyers'!$A47="","",'02_Buyers'!$A47) | B50: =IF($A50="","",'02_Buyers'!$S47) | C50: =IF($A50="","",'02_Buyers'!$AK47) | D50: =IF($A50="",0,'02_Buyers'!$BB47) | E50: =IF($A50="",0,'02_Buyers'!$BC47) | F50: 0 | G50: =IF($A50="",0,'02_Buyers'!$BD47) | H50: =IF($A50="",0,'02_Buyers'!$BE47) | I50: =IF($A50="",0,'02_Buyers'!$AB47) | J50: =IF($A50="","",F50-I50) | K50: =IF(OR($A50="",I50<=0),"",J50/I50) | L50: =IF($A50="","",IF(M50="대상 아님","대상 아님(L/C·선수금)",IF(AND(I50>0,K50<=-0.3),"감액 30%↑ — 사람 승인 필요",IF(J50>0,"증액 — 전결권자 승인","유지·소폭 감액")))) | M50: =IF($A50="","",'02_Buyers'!$BA47) | N50: =IF(OR($A50="",M50="대상 아님"),"",IF(F50<=50000,"채권관리팀장",IF(F50<=200000,"영업본부장","대표이사"))) | O50: =IF($A50="","",'02_Buyers'!$AG47) | Q50: =IF(OR($A50="",P50=""),"",F50-P50) | R50: =IF(OR($A50="",D50<=0),"",COUNTIFS($G$5:$G$154,G50,$D$5:$D$154,">0")) | T50: 제약 4: $U$6 <= $W$6 (ELuse ≤ ELbudget)
A51: =IF('02_Buyers'!$A48="","",'02_Buyers'!$A48) | B51: =IF($A51="","",'02_Buyers'!$S48) | C51: =IF($A51="","",'02_Buyers'!$AK48) | D51: =IF($A51="",0,'02_Buyers'!$BB48) | E51: =IF($A51="",0,'02_Buyers'!$BC48) | F51: 0 | G51: =IF($A51="",0,'02_Buyers'!$BD48) | H51: =IF($A51="",0,'02_Buyers'!$BE48) | I51: =IF($A51="",0,'02_Buyers'!$AB48) | J51: =IF($A51="","",F51-I51) | K51: =IF(OR($A51="",I51<=0),"",J51/I51) | L51: =IF($A51="","",IF(M51="대상 아님","대상 아님(L/C·선수금)",IF(AND(I51>0,K51<=-0.3),"감액 30%↑ — 사람 승인 필요",IF(J51>0,"증액 — 전결권자 승인","유지·소폭 감액")))) | M51: =IF($A51="","",'02_Buyers'!$BA48) | N51: =IF(OR($A51="",M51="대상 아님"),"",IF(F51<=50000,"채권관리팀장",IF(F51<=200000,"영업본부장","대표이사"))) | O51: =IF($A51="","",'02_Buyers'!$AG48) | Q51: =IF(OR($A51="",P51=""),"",F51-P51) | R51: =IF(OR($A51="",D51<=0),"",COUNTIFS($G$5:$G$154,G51,$D$5:$D$154,">0")) | T51: 제약 5: $Z$12:$Z$31 <= $Y$12:$Y$31 (CtryUsed ≤ CtryCap, 20칸 한 줄)
A52: =IF('02_Buyers'!$A49="","",'02_Buyers'!$A49) | B52: =IF($A52="","",'02_Buyers'!$S49) | C52: =IF($A52="","",'02_Buyers'!$AK49) | D52: =IF($A52="",0,'02_Buyers'!$BB49) | E52: =IF($A52="",0,'02_Buyers'!$BC49) | F52: 0 | G52: =IF($A52="",0,'02_Buyers'!$BD49) | H52: =IF($A52="",0,'02_Buyers'!$BE49) | I52: =IF($A52="",0,'02_Buyers'!$AB49) | J52: =IF($A52="","",F52-I52) | K52: =IF(OR($A52="",I52<=0),"",J52/I52) | L52: =IF($A52="","",IF(M52="대상 아님","대상 아님(L/C·선수금)",IF(AND(I52>0,K52<=-0.3),"감액 30%↑ — 사람 승인 필요",IF(J52>0,"증액 — 전결권자 승인","유지·소폭 감액")))) | M52: =IF($A52="","",'02_Buyers'!$BA49) | N52: =IF(OR($A52="",M52="대상 아님"),"",IF(F52<=50000,"채권관리팀장",IF(F52<=200000,"영업본부장","대표이사"))) | O52: =IF($A52="","",'02_Buyers'!$AG49) | Q52: =IF(OR($A52="",P52=""),"",F52-P52) | R52: =IF(OR($A52="",D52<=0),"",COUNTIFS($G$5:$G$154,G52,$D$5:$D$154,">0")) | T52: 제약 6: $U$7 <= $W$7 (B_Used ≤ B_Cap)
A53: =IF('02_Buyers'!$A50="","",'02_Buyers'!$A50) | B53: =IF($A53="","",'02_Buyers'!$S50) | C53: =IF($A53="","",'02_Buyers'!$AK50) | D53: =IF($A53="",0,'02_Buyers'!$BB50) | E53: =IF($A53="",0,'02_Buyers'!$BC50) | F53: 0 | G53: =IF($A53="",0,'02_Buyers'!$BD50) | H53: =IF($A53="",0,'02_Buyers'!$BE50) | I53: =IF($A53="",0,'02_Buyers'!$AB50) | J53: =IF($A53="","",F53-I53) | K53: =IF(OR($A53="",I53<=0),"",J53/I53) | L53: =IF($A53="","",IF(M53="대상 아님","대상 아님(L/C·선수금)",IF(AND(I53>0,K53<=-0.3),"감액 30%↑ — 사람 승인 필요",IF(J53>0,"증액 — 전결권자 승인","유지·소폭 감액")))) | M53: =IF($A53="","",'02_Buyers'!$BA50) | N53: =IF(OR($A53="",M53="대상 아님"),"",IF(F53<=50000,"채권관리팀장",IF(F53<=200000,"영업본부장","대표이사"))) | O53: =IF($A53="","",'02_Buyers'!$AG50) | Q53: =IF(OR($A53="",P53=""),"",F53-P53) | R53: =IF(OR($A53="",D53<=0),"",COUNTIFS($G$5:$G$154,G53,$D$5:$D$154,">0")) | T53: '제한되지 않는 변수를 음이 아닌 수로 설정' ✔ · 해법: 단순 LP → 해 찾기
A54: =IF('02_Buyers'!$A51="","",'02_Buyers'!$A51) | B54: =IF($A54="","",'02_Buyers'!$S51) | C54: =IF($A54="","",'02_Buyers'!$AK51) | D54: =IF($A54="",0,'02_Buyers'!$BB51) | E54: =IF($A54="",0,'02_Buyers'!$BC51) | F54: 0 | G54: =IF($A54="",0,'02_Buyers'!$BD51) | H54: =IF($A54="",0,'02_Buyers'!$BE51) | I54: =IF($A54="",0,'02_Buyers'!$AB51) | J54: =IF($A54="","",F54-I54) | K54: =IF(OR($A54="",I54<=0),"",J54/I54) | L54: =IF($A54="","",IF(M54="대상 아님","대상 아님(L/C·선수금)",IF(AND(I54>0,K54<=-0.3),"감액 30%↑ — 사람 승인 필요",IF(J54>0,"증액 — 전결권자 승인","유지·소폭 감액")))) | M54: =IF($A54="","",'02_Buyers'!$BA51) | N54: =IF(OR($A54="",M54="대상 아님"),"",IF(F54<=50000,"채권관리팀장",IF(F54<=200000,"영업본부장","대표이사"))) | O54: =IF($A54="","",'02_Buyers'!$AG51) | Q54: =IF(OR($A54="",P54=""),"",F54-P54) | R54: =IF(OR($A54="",D54<=0),"",COUNTIFS($G$5:$G$154,G54,$D$5:$D$154,">0")) | T54: 결과 창: '해 찾기 해 보존' + 보고서 '해답'·'민감도' → 민감도 보고서의 잠재가격을 Z5:Z7·AC12:AC31에 옮겨 적기
A55: =IF('02_Buyers'!$A52="","",'02_Buyers'!$A52) | B55: =IF($A55="","",'02_Buyers'!$S52) | C55: =IF($A55="","",'02_Buyers'!$AK52) | D55: =IF($A55="",0,'02_Buyers'!$BB52) | E55: =IF($A55="",0,'02_Buyers'!$BC52) | F55: 0 | G55: =IF($A55="",0,'02_Buyers'!$BD52) | H55: =IF($A55="",0,'02_Buyers'!$BE52) | I55: =IF($A55="",0,'02_Buyers'!$AB52) | J55: =IF($A55="","",F55-I55) | K55: =IF(OR($A55="",I55<=0),"",J55/I55) | L55: =IF($A55="","",IF(M55="대상 아님","대상 아님(L/C·선수금)",IF(AND(I55>0,K55<=-0.3),"감액 30%↑ — 사람 승인 필요",IF(J55>0,"증액 — 전결권자 승인","유지·소폭 감액")))) | M55: =IF($A55="","",'02_Buyers'!$BA52) | N55: =IF(OR($A55="",M55="대상 아님"),"",IF(F55<=50000,"채권관리팀장",IF(F55<=200000,"영업본부장","대표이사"))) | O55: =IF($A55="","",'02_Buyers'!$AG52) | Q55: =IF(OR($A55="",P55=""),"",F55-P55) | R55: =IF(OR($A55="",D55<=0),"",COUNTIFS($G$5:$G$154,G55,$D$5:$D$154,">0")) | T55: 대안 최적해: 같은 coef(R열 동점 그룹)끼리는 해 찾기와 PuLP가 다른 바이어를 채울 수 있다 — 목적함수·걸린 제약으로 비교
A56: =IF('02_Buyers'!$A53="","",'02_Buyers'!$A53) | B56: =IF($A56="","",'02_Buyers'!$S53) | C56: =IF($A56="","",'02_Buyers'!$AK53) | D56: =IF($A56="",0,'02_Buyers'!$BB53) | E56: =IF($A56="",0,'02_Buyers'!$BC53) | F56: 0 | G56: =IF($A56="",0,'02_Buyers'!$BD53) | H56: =IF($A56="",0,'02_Buyers'!$BE53) | I56: =IF($A56="",0,'02_Buyers'!$AB53) | J56: =IF($A56="","",F56-I56) | K56: =IF(OR($A56="",I56<=0),"",J56/I56) | L56: =IF($A56="","",IF(M56="대상 아님","대상 아님(L/C·선수금)",IF(AND(I56>0,K56<=-0.3),"감액 30%↑ — 사람 승인 필요",IF(J56>0,"증액 — 전결권자 승인","유지·소폭 감액")))) | M56: =IF($A56="","",'02_Buyers'!$BA53) | N56: =IF(OR($A56="",M56="대상 아님"),"",IF(F56<=50000,"채권관리팀장",IF(F56<=200000,"영업본부장","대표이사"))) | O56: =IF($A56="","",'02_Buyers'!$AG53) | Q56: =IF(OR($A56="",P56=""),"",F56-P56) | R56: =IF(OR($A56="",D56<=0),"",COUNTIFS($G$5:$G$154,G56,$D$5:$D$154,">0"))
A57: =IF('02_Buyers'!$A54="","",'02_Buyers'!$A54) | B57: =IF($A57="","",'02_Buyers'!$S54) | C57: =IF($A57="","",'02_Buyers'!$AK54) | D57: =IF($A57="",0,'02_Buyers'!$BB54) | E57: =IF($A57="",0,'02_Buyers'!$BC54) | F57: 0 | G57: =IF($A57="",0,'02_Buyers'!$BD54) | H57: =IF($A57="",0,'02_Buyers'!$BE54) | I57: =IF($A57="",0,'02_Buyers'!$AB54) | J57: =IF($A57="","",F57-I57) | K57: =IF(OR($A57="",I57<=0),"",J57/I57) | L57: =IF($A57="","",IF(M57="대상 아님","대상 아님(L/C·선수금)",IF(AND(I57>0,K57<=-0.3),"감액 30%↑ — 사람 승인 필요",IF(J57>0,"증액 — 전결권자 승인","유지·소폭 감액")))) | M57: =IF($A57="","",'02_Buyers'!$BA54) | N57: =IF(OR($A57="",M57="대상 아님"),"",IF(F57<=50000,"채권관리팀장",IF(F57<=200000,"영업본부장","대표이사"))) | O57: =IF($A57="","",'02_Buyers'!$AG54) | Q57: =IF(OR($A57="",P57=""),"",F57-P57) | R57: =IF(OR($A57="",D57<=0),"",COUNTIFS($G$5:$G$154,G57,$D$5:$D$154,">0"))
A58: =IF('02_Buyers'!$A55="","",'02_Buyers'!$A55) | B58: =IF($A58="","",'02_Buyers'!$S55) | C58: =IF($A58="","",'02_Buyers'!$AK55) | D58: =IF($A58="",0,'02_Buyers'!$BB55) | E58: =IF($A58="",0,'02_Buyers'!$BC55) | F58: 0 | G58: =IF($A58="",0,'02_Buyers'!$BD55) | H58: =IF($A58="",0,'02_Buyers'!$BE55) | I58: =IF($A58="",0,'02_Buyers'!$AB55) | J58: =IF($A58="","",F58-I58) | K58: =IF(OR($A58="",I58<=0),"",J58/I58) | L58: =IF($A58="","",IF(M58="대상 아님","대상 아님(L/C·선수금)",IF(AND(I58>0,K58<=-0.3),"감액 30%↑ — 사람 승인 필요",IF(J58>0,"증액 — 전결권자 승인","유지·소폭 감액")))) | M58: =IF($A58="","",'02_Buyers'!$BA55) | N58: =IF(OR($A58="",M58="대상 아님"),"",IF(F58<=50000,"채권관리팀장",IF(F58<=200000,"영업본부장","대표이사"))) | O58: =IF($A58="","",'02_Buyers'!$AG55) | Q58: =IF(OR($A58="",P58=""),"",F58-P58) | R58: =IF(OR($A58="",D58<=0),"",COUNTIFS($G$5:$G$154,G58,$D$5:$D$154,">0"))
A59: =IF('02_Buyers'!$A56="","",'02_Buyers'!$A56) | B59: =IF($A59="","",'02_Buyers'!$S56) | C59: =IF($A59="","",'02_Buyers'!$AK56) | D59: =IF($A59="",0,'02_Buyers'!$BB56) | E59: =IF($A59="",0,'02_Buyers'!$BC56) | F59: 0 | G59: =IF($A59="",0,'02_Buyers'!$BD56) | H59: =IF($A59="",0,'02_Buyers'!$BE56) | I59: =IF($A59="",0,'02_Buyers'!$AB56) | J59: =IF($A59="","",F59-I59) | K59: =IF(OR($A59="",I59<=0),"",J59/I59) | L59: =IF($A59="","",IF(M59="대상 아님","대상 아님(L/C·선수금)",IF(AND(I59>0,K59<=-0.3),"감액 30%↑ — 사람 승인 필요",IF(J59>0,"증액 — 전결권자 승인","유지·소폭 감액")))) | M59: =IF($A59="","",'02_Buyers'!$BA56) | N59: =IF(OR($A59="",M59="대상 아님"),"",IF(F59<=50000,"채권관리팀장",IF(F59<=200000,"영업본부장","대표이사"))) | O59: =IF($A59="","",'02_Buyers'!$AG56) | Q59: =IF(OR($A59="",P59=""),"",F59-P59) | R59: =IF(OR($A59="",D59<=0),"",COUNTIFS($G$5:$G$154,G59,$D$5:$D$154,">0"))
A60: =IF('02_Buyers'!$A57="","",'02_Buyers'!$A57) | B60: =IF($A60="","",'02_Buyers'!$S57) | C60: =IF($A60="","",'02_Buyers'!$AK57) | D60: =IF($A60="",0,'02_Buyers'!$BB57) | E60: =IF($A60="",0,'02_Buyers'!$BC57) | F60: 0 | G60: =IF($A60="",0,'02_Buyers'!$BD57) | H60: =IF($A60="",0,'02_Buyers'!$BE57) | I60: =IF($A60="",0,'02_Buyers'!$AB57) | J60: =IF($A60="","",F60-I60) | K60: =IF(OR($A60="",I60<=0),"",J60/I60) | L60: =IF($A60="","",IF(M60="대상 아님","대상 아님(L/C·선수금)",IF(AND(I60>0,K60<=-0.3),"감액 30%↑ — 사람 승인 필요",IF(J60>0,"증액 — 전결권자 승인","유지·소폭 감액")))) | M60: =IF($A60="","",'02_Buyers'!$BA57) | N60: =IF(OR($A60="",M60="대상 아님"),"",IF(F60<=50000,"채권관리팀장",IF(F60<=200000,"영업본부장","대표이사"))) | O60: =IF($A60="","",'02_Buyers'!$AG57) | Q60: =IF(OR($A60="",P60=""),"",F60-P60) | R60: =IF(OR($A60="",D60<=0),"",COUNTIFS($G$5:$G$154,G60,$D$5:$D$154,">0"))
A61: =IF('02_Buyers'!$A58="","",'02_Buyers'!$A58) | B61: =IF($A61="","",'02_Buyers'!$S58) | C61: =IF($A61="","",'02_Buyers'!$AK58) | D61: =IF($A61="",0,'02_Buyers'!$BB58) | E61: =IF($A61="",0,'02_Buyers'!$BC58) | F61: 0 | G61: =IF($A61="",0,'02_Buyers'!$BD58) | H61: =IF($A61="",0,'02_Buyers'!$BE58) | I61: =IF($A61="",0,'02_Buyers'!$AB58) | J61: =IF($A61="","",F61-I61) | K61: =IF(OR($A61="",I61<=0),"",J61/I61) | L61: =IF($A61="","",IF(M61="대상 아님","대상 아님(L/C·선수금)",IF(AND(I61>0,K61<=-0.3),"감액 30%↑ — 사람 승인 필요",IF(J61>0,"증액 — 전결권자 승인","유지·소폭 감액")))) | M61: =IF($A61="","",'02_Buyers'!$BA58) | N61: =IF(OR($A61="",M61="대상 아님"),"",IF(F61<=50000,"채권관리팀장",IF(F61<=200000,"영업본부장","대표이사"))) | O61: =IF($A61="","",'02_Buyers'!$AG58) | Q61: =IF(OR($A61="",P61=""),"",F61-P61) | R61: =IF(OR($A61="",D61<=0),"",COUNTIFS($G$5:$G$154,G61,$D$5:$D$154,">0"))
A62: =IF('02_Buyers'!$A59="","",'02_Buyers'!$A59) | B62: =IF($A62="","",'02_Buyers'!$S59) | C62: =IF($A62="","",'02_Buyers'!$AK59) | D62: =IF($A62="",0,'02_Buyers'!$BB59) | E62: =IF($A62="",0,'02_Buyers'!$BC59) | F62: 0 | G62: =IF($A62="",0,'02_Buyers'!$BD59) | H62: =IF($A62="",0,'02_Buyers'!$BE59) | I62: =IF($A62="",0,'02_Buyers'!$AB59) | J62: =IF($A62="","",F62-I62) | K62: =IF(OR($A62="",I62<=0),"",J62/I62) | L62: =IF($A62="","",IF(M62="대상 아님","대상 아님(L/C·선수금)",IF(AND(I62>0,K62<=-0.3),"감액 30%↑ — 사람 승인 필요",IF(J62>0,"증액 — 전결권자 승인","유지·소폭 감액")))) | M62: =IF($A62="","",'02_Buyers'!$BA59) | N62: =IF(OR($A62="",M62="대상 아님"),"",IF(F62<=50000,"채권관리팀장",IF(F62<=200000,"영업본부장","대표이사"))) | O62: =IF($A62="","",'02_Buyers'!$AG59) | Q62: =IF(OR($A62="",P62=""),"",F62-P62) | R62: =IF(OR($A62="",D62<=0),"",COUNTIFS($G$5:$G$154,G62,$D$5:$D$154,">0"))
A63: =IF('02_Buyers'!$A60="","",'02_Buyers'!$A60) | B63: =IF($A63="","",'02_Buyers'!$S60) | C63: =IF($A63="","",'02_Buyers'!$AK60) | D63: =IF($A63="",0,'02_Buyers'!$BB60) | E63: =IF($A63="",0,'02_Buyers'!$BC60) | F63: 0 | G63: =IF($A63="",0,'02_Buyers'!$BD60) | H63: =IF($A63="",0,'02_Buyers'!$BE60) | I63: =IF($A63="",0,'02_Buyers'!$AB60) | J63: =IF($A63="","",F63-I63) | K63: =IF(OR($A63="",I63<=0),"",J63/I63) | L63: =IF($A63="","",IF(M63="대상 아님","대상 아님(L/C·선수금)",IF(AND(I63>0,K63<=-0.3),"감액 30%↑ — 사람 승인 필요",IF(J63>0,"증액 — 전결권자 승인","유지·소폭 감액")))) | M63: =IF($A63="","",'02_Buyers'!$BA60) | N63: =IF(OR($A63="",M63="대상 아님"),"",IF(F63<=50000,"채권관리팀장",IF(F63<=200000,"영업본부장","대표이사"))) | O63: =IF($A63="","",'02_Buyers'!$AG60) | Q63: =IF(OR($A63="",P63=""),"",F63-P63) | R63: =IF(OR($A63="",D63<=0),"",COUNTIFS($G$5:$G$154,G63,$D$5:$D$154,">0"))
A64: =IF('02_Buyers'!$A61="","",'02_Buyers'!$A61) | B64: =IF($A64="","",'02_Buyers'!$S61) | C64: =IF($A64="","",'02_Buyers'!$AK61) | D64: =IF($A64="",0,'02_Buyers'!$BB61) | E64: =IF($A64="",0,'02_Buyers'!$BC61) | F64: 0 | G64: =IF($A64="",0,'02_Buyers'!$BD61) | H64: =IF($A64="",0,'02_Buyers'!$BE61) | I64: =IF($A64="",0,'02_Buyers'!$AB61) | J64: =IF($A64="","",F64-I64) | K64: =IF(OR($A64="",I64<=0),"",J64/I64) | L64: =IF($A64="","",IF(M64="대상 아님","대상 아님(L/C·선수금)",IF(AND(I64>0,K64<=-0.3),"감액 30%↑ — 사람 승인 필요",IF(J64>0,"증액 — 전결권자 승인","유지·소폭 감액")))) | M64: =IF($A64="","",'02_Buyers'!$BA61) | N64: =IF(OR($A64="",M64="대상 아님"),"",IF(F64<=50000,"채권관리팀장",IF(F64<=200000,"영업본부장","대표이사"))) | O64: =IF($A64="","",'02_Buyers'!$AG61) | Q64: =IF(OR($A64="",P64=""),"",F64-P64) | R64: =IF(OR($A64="",D64<=0),"",COUNTIFS($G$5:$G$154,G64,$D$5:$D$154,">0"))
A65: =IF('02_Buyers'!$A62="","",'02_Buyers'!$A62) | B65: =IF($A65="","",'02_Buyers'!$S62) | C65: =IF($A65="","",'02_Buyers'!$AK62) | D65: =IF($A65="",0,'02_Buyers'!$BB62) | E65: =IF($A65="",0,'02_Buyers'!$BC62) | F65: 0 | G65: =IF($A65="",0,'02_Buyers'!$BD62) | H65: =IF($A65="",0,'02_Buyers'!$BE62) | I65: =IF($A65="",0,'02_Buyers'!$AB62) | J65: =IF($A65="","",F65-I65) | K65: =IF(OR($A65="",I65<=0),"",J65/I65) | L65: =IF($A65="","",IF(M65="대상 아님","대상 아님(L/C·선수금)",IF(AND(I65>0,K65<=-0.3),"감액 30%↑ — 사람 승인 필요",IF(J65>0,"증액 — 전결권자 승인","유지·소폭 감액")))) | M65: =IF($A65="","",'02_Buyers'!$BA62) | N65: =IF(OR($A65="",M65="대상 아님"),"",IF(F65<=50000,"채권관리팀장",IF(F65<=200000,"영업본부장","대표이사"))) | O65: =IF($A65="","",'02_Buyers'!$AG62) | Q65: =IF(OR($A65="",P65=""),"",F65-P65) | R65: =IF(OR($A65="",D65<=0),"",COUNTIFS($G$5:$G$154,G65,$D$5:$D$154,">0"))
A66: =IF('02_Buyers'!$A63="","",'02_Buyers'!$A63) | B66: =IF($A66="","",'02_Buyers'!$S63) | C66: =IF($A66="","",'02_Buyers'!$AK63) | D66: =IF($A66="",0,'02_Buyers'!$BB63) | E66: =IF($A66="",0,'02_Buyers'!$BC63) | F66: 0 | G66: =IF($A66="",0,'02_Buyers'!$BD63) | H66: =IF($A66="",0,'02_Buyers'!$BE63) | I66: =IF($A66="",0,'02_Buyers'!$AB63) | J66: =IF($A66="","",F66-I66) | K66: =IF(OR($A66="",I66<=0),"",J66/I66) | L66: =IF($A66="","",IF(M66="대상 아님","대상 아님(L/C·선수금)",IF(AND(I66>0,K66<=-0.3),"감액 30%↑ — 사람 승인 필요",IF(J66>0,"증액 — 전결권자 승인","유지·소폭 감액")))) | M66: =IF($A66="","",'02_Buyers'!$BA63) | N66: =IF(OR($A66="",M66="대상 아님"),"",IF(F66<=50000,"채권관리팀장",IF(F66<=200000,"영업본부장","대표이사"))) | O66: =IF($A66="","",'02_Buyers'!$AG63) | Q66: =IF(OR($A66="",P66=""),"",F66-P66) | R66: =IF(OR($A66="",D66<=0),"",COUNTIFS($G$5:$G$154,G66,$D$5:$D$154,">0"))
A67: =IF('02_Buyers'!$A64="","",'02_Buyers'!$A64) | B67: =IF($A67="","",'02_Buyers'!$S64) | C67: =IF($A67="","",'02_Buyers'!$AK64) | D67: =IF($A67="",0,'02_Buyers'!$BB64) | E67: =IF($A67="",0,'02_Buyers'!$BC64) | F67: 0 | G67: =IF($A67="",0,'02_Buyers'!$BD64) | H67: =IF($A67="",0,'02_Buyers'!$BE64) | I67: =IF($A67="",0,'02_Buyers'!$AB64) | J67: =IF($A67="","",F67-I67) | K67: =IF(OR($A67="",I67<=0),"",J67/I67) | L67: =IF($A67="","",IF(M67="대상 아님","대상 아님(L/C·선수금)",IF(AND(I67>0,K67<=-0.3),"감액 30%↑ — 사람 승인 필요",IF(J67>0,"증액 — 전결권자 승인","유지·소폭 감액")))) | M67: =IF($A67="","",'02_Buyers'!$BA64) | N67: =IF(OR($A67="",M67="대상 아님"),"",IF(F67<=50000,"채권관리팀장",IF(F67<=200000,"영업본부장","대표이사"))) | O67: =IF($A67="","",'02_Buyers'!$AG64) | Q67: =IF(OR($A67="",P67=""),"",F67-P67) | R67: =IF(OR($A67="",D67<=0),"",COUNTIFS($G$5:$G$154,G67,$D$5:$D$154,">0"))
... A154: =IF('02_Buyers'!$A151="","",'02_Buyers'!$A151) | B154: =IF($A154="","",'02_Buyers'!$S151) | C154: =IF($A154="","",'02_Buyers'!$AK151) | D154: =IF($A154="",0,'02_Buyers'!$BB151) | E154: =IF($A154="",0,'02_Buyers'!$BC151) | F154: 0 | G154: =IF($A154="",0,'02_Buyers'!$BD151) | H154: =IF($A154="",0,'02_Buyers'!$BE151) | I154: =IF($A154="",0,'02_Buyers'!$AB151) | J154: =IF($A154="","",F154-I154) | K154: =IF(OR($A154="",I154<=0),"",J154/I154) | L154: =IF($A154="","",IF(M154="대상 아님","대상 아님(L/C·선수금)",IF(AND(I154>0,K154<=-0.3),"감액 30%↑ — 사람 승인 필요",IF(J154>0,"증액 — 전결권자 승인","유지·소폭 감액")))) | M154: =IF($A154="","",'02_Buyers'!$BA151) | N154: =IF(OR($A154="",M154="대상 아님"),"",IF(F154<=50000,"채권관리팀장",IF(F154<=200000,"영업본부장","대표이사"))) | O154: =IF($A154="","",'02_Buyers'!$AG151) | Q154: =IF(OR($A154="",P154=""),"",F154-P154) | R154: =IF(OR($A154="",D154<=0),"",COUNTIFS($G$5:$G$154,G154,$D$5:$D$154,">0"))

Sheet 11_Scenario
A1: 11_Scenario — 거시 충격 4단계(S1~S4) + 기준 S0 + 사용자 U1 · 실제 충격 재현 · 몬테카를로
A2: EL_s = Σ 잔액 × MIN(1, PD_eff × PD 배수) × LGD_s × (1 − 보상비율) · 원화 환산 = Σ 잔액 × 원/달러 · 금융비용 = Σ 잔액 × (TSOFR3M + bp + 가산) × 결제기간 ÷ 360
A3: PD 배수·LGD 상향·송금 지연은 [교육용 가정](R09 충격 크기는 BIS·FRED 실측). 시나리오는 예측이 아니라 가정이다 | AG3: 데이터 표가 깨졌으면: AG6:AH1006 선택 → 데이터 → 가상 분석 → 데이터 표 → '열 입력 셀' = $AJ$1
A5: scenario_id | B5: name_ko | C5: row_type | D5: local_fx_chg | E5: usd_krw_base | F5: usd_krw_level | G5: krw_chg | H5: rate_shock_bp | I5: oil_chg | J5: pd_multiplier | K5: lgd_adj | L5: lgd_scenario | M5: transfer_restriction | N5: transfer_delay_days | O5: fx_scope_crc_min | P5: basis | Q5: source | AG5: 회차 | AH5: 1회 손실(데이터 표)
A6: S0 | B6: 기준 | C6: scenario | D6: 0 | E6: 1360 | F6: 1360 | G6: 0 | H6: 0 | I6: 0 | J6: 1 | K6: 0 | L6: 0.6 | M6: N | N6: 0 | P6: G03 P6 원/달러 매매기준율(2026-09-23) · Term SOFR 3M 4.047% | Q6: R09 §2.8(BIS·FRED·Allianz) · 03 Part2 §4.7 · PD 배수·LGD 상향·송금 지연·적용 국가 = 교육용 가정 | AG6: (수식 행) | AH6: =TotalLoss
A7: S1 | B7: 경미 | C7: scenario | D7: -0.1 | E7: 1360 | F7: 1292 | G7: -0.05 | H7: 100 | I7: 0.2 | J7: 1.2 | K7: 0 | L7: 0.6 | M7: N | N7: 0 | O7: 3 | P7: IDR 2025-26(−11%) · 2026 글로벌 부도 +6%(Allianz) · 원/달러 ±5% 중 수출자에게 불리한 원화 강세 방향 [교육용 가정] | Q7: R09 §2.8(BIS·FRED·Allianz) · 03 Part2 §4.7 · PD 배수·LGD 상향·송금 지연·적용 국가 = 교육용 가정 | AG7: 1
A8: S2 | B8: 중간 | C8: scenario | D8: -0.25 | E8: 1360 | F8: 1550 | G8: 0.1397 | H8: 250 | I8: 0.5 | J8: 1.5 | K8: 0 | L8: 0.6 | M8: N | N8: 0 | O8: 3 | P8: KRW 2021-22(−25%) · 한은 2021-22 +225bp · 원/달러 1,550(2026-06 수준) | Q8: R09 §2.8(BIS·FRED·Allianz) · 03 Part2 §4.7 · PD 배수·LGD 상향·송금 지연·적용 국가 = 교육용 가정 | AG8: 2 | AH8: 0
A9: S3 | B9: 심각 | C9: scenario | D9: -0.45 | E9: 1360 | F9: 1570 | G9: 0.1544 | H9: 450 | I9: 0.94 | J9: 2.5 | K9: 0 | L9: 0.6 | M9: N | N9: 0 | O9: 5 | P9: TRY 2018(−46%)·LKR 2022(−45%)·PKR 2022-23(−42%) · 연준 2022-23 +450bp · 브렌트 2026-04-07 $138.21(+94%) · 원/달러 1,570(2009-03) | Q9: R09 §2.8(BIS·FRED·Allianz) · 03 Part2 §4.7 · PD 배수·LGD 상향·송금 지연·적용 국가 = 교육용 가정 | AG9: 3 | AH9: 0
A10: S4 | B10: 극단 | C10: scenario | D10: -0.7 | E10: 1360 | F10: 1960 | G10: 0.4412 | H10: 450 | I10: 1 | J10: 4 | K10: 0.2 | L10: 0.8 | M10: Y | N10: 60 | O10: 6 | P10: EGP 2022-24(−67%)·NGN 2023-24(−72%)·ARS 2023(하루 −54%) · 원/달러 1,960(1997-12) · 금리는 USD +450bp [교육용 가정](신흥국 정책금리 +40%p는 참고) · 송금 지연 60일(KOTRA 모잠비크 '최대 2개월') · LGD 80%('LGD 상향' [교육용 가정]) | Q10: R09 §2.8(BIS·FRED·Allianz) · 03 Part2 §4.7 · PD 배수·LGD 상향·송금 지연·적용 국가 = 교육용 가정 | AG10: 4 | AH10: 0
A11: R2026 | B11: 2026 실제 원/달러 경로(참고) | C11: reference | E11: 1529.94 | F11: 1345.63 | G11: -0.120469 | H11: 25 | I11: 0.61 | J11: 1 | K11: 0 | L11: 0.6 | M11: N | N11: 0 | P11: FRED H.10 원/달러(과정 환율 정본, D11) 2026-06-09 1,529.94 → 2026-09-10 1,345.63(−12.0%, 원화 강세) — USD 채권 원화 환산 손실 재현. 참고: 같은 날 한국은행 ECOS 매매기준율은 1,546.5 → 1,337.9(−13.5%) — 출처마다 값이 다르다. 같은 해 연준 +25bp(09-16)·한은 +50bp(07-16·08-27)·브렌트 $71.32 → $114.89(09-22, 최고 $138.21) | Q11: R09 §2.8(BIS·FRED·Allianz) · 03 Part2 §4.7 · PD 배수·LGD 상향·송금 지연·적용 국가 = 교육용 가정 | AG11: 5 | AH11: 0
A12: U1 | B12: 사용자(카드) — 값을 바꿔 쓴다 | C12: scenario | D12: 0 | E12: 1360 | F12: 1360 | G12: 0 | H12: 0 | I12: 0 | J12: 1 | K12: 0 | L12: 0.6 | M12: N | N12: 0 | P12: Day6 위기 카드 등 사용자 입력(기본 = S0) | Q12: 사용자 | AG12: 6 | AH12: 0
AG13: 7 | AH13: 0
A14: 시나리오 결과(현재 미결 잔액 기준, 연간) | AG14: 8 | AH14: 0
A15: 항목 | B15: S0 | C15: S1 | D15: S2 | E15: S3 | F15: S4 | G15: U1 | AG15: 9 | AH15: 0
A16: PD 배수 | B16: =$J$6 | C16: =$J$7 | D16: =$J$8 | E16: =$J$9 | F16: =$J$10 | G16: =$J$12 | AG16: 10 | AH16: 0
A17: LGD(무보험) | B17: =MIN(1,LGD+$K$6) | C17: =MIN(1,LGD+$K$7) | D17: =MIN(1,LGD+$K$8) | E17: =MIN(1,LGD+$K$9) | F17: =MIN(1,LGD+$K$10) | G17: =MIN(1,LGD+$K$12) | AG17: 11 | AH17: 0
A18: 원/달러 | B18: =$F$6 | C18: =$F$7 | D18: =$F$8 | E18: =$F$9 | F18: =$F$10 | G18: =$F$12 | AG18: 12 | AH18: 0
A19: 금리 충격(bp) | B19: =$H$6 | C19: =$H$7 | D19: =$H$8 | E19: =$H$9 | F19: =$H$10 | G19: =$H$12 | AG19: 13 | AH19: 0
A20: 예상손실 EL(USD) | B20: =SUM(K65:K214) | C20: =SUM(L65:L214) | D20: =SUM(M65:M214) | E20: =SUM(N65:N214) | F20: =SUM(O65:O214) | G20: =SUM(P65:P214) | AG20: 14 | AH20: 0
A21: S0 대비 | B21: =IFERROR(B20/$B$20-1,0) | C21: =IFERROR(C20/$B$20-1,0) | D21: =IFERROR(D20/$B$20-1,0) | E21: =IFERROR(E20/$B$20-1,0) | F21: =IFERROR(F20/$B$20-1,0) | G21: =IFERROR(G20/$B$20-1,0) | AG21: 15 | AH21: 0
A22: 잔액 원화 환산(원) | B22: =SUM($B$65:$B$214)*$F$6 | C22: =SUM($B$65:$B$214)*$F$7 | D22: =SUM($B$65:$B$214)*$F$8 | E22: =SUM($B$65:$B$214)*$F$9 | F22: =SUM($B$65:$B$214)*$F$10 | G22: =SUM($B$65:$B$214)*$F$12 | AG22: 16 | AH22: 0
A23: 금융비용(USD) | B23: =SUM(Q65:Q214) | C23: =SUM(R65:R214) | D23: =SUM(S65:S214) | E23: =SUM(T65:T214) | F23: =SUM(U65:U214) | G23: =SUM(V65:V214) | AG23: 17 | AH23: 0
A24: 송금 지연 비용(USD) | B24: =SUM(W65:W214) | C24: =SUM(X65:X214) | D24: =SUM(Y65:Y214) | E24: =SUM(Z65:Z214) | F24: =SUM(AA65:AA214) | G24: =SUM(AB65:AB214) | AG24: 18 | AH24: 0
A25: EL 원화(원) | B25: =B20*$F$6 | C25: =C20*$F$7 | D25: =D20*$F$8 | E25: =E20*$F$9 | F25: =F20*$F$10 | G25: =G20*$F$12 | AG25: 19 | AH25: 0
A26: 바이어국 통화 변화(참고) | B26: =$D$6 | C26: =$D$7 | D26: =$D$8 | E26: =$D$9 | F26: =$D$10 | G26: =$D$12 | AG26: 20 | AH26: 0
A27: 유가 변화(참고) | B27: =$I$6 | C27: =$I$7 | D27: =$I$8 | E27: =$I$9 | F27: =$I$10 | G27: =$I$12 | AG27: 21 | AH27: 0
AG28: 22 | AH28: 0
A29: 실제 충격 재현(R2026): 원/달러 FRED H.10 2026-06-09 1,529.94 → 09-10 1,345.63(−12.0%) · 참고 ECOS 매매기준율 1,546.5 → 1,337.9(−13.5%) | AG29: 23 | AH29: 0
A30: 출발 원/달러 | B30: =$E$11 | AG30: 24 | AH30: 0
A31: 도착 원/달러 | B31: =$F$11 | AG31: 25 | AH31: 0
A32: 변화율 | B32: =$G$11 | AG32: 26 | AH32: 0
A33: USD 표시 채권(USD) | B33: =SUMIFS($B$65:$B$214,$J$65:$J$214,"USD") | AG33: 27 | AH33: 0
A34: USD 채권 원화 가치 변화(원) | B34: =B33*(B31-B30) | AG34: 28 | AH34: 0
A35: 전체 잔액(USD 환산) 기준(원) | B35: =SUM($B$65:$B$214)*(B31-B30) | AG35: 29 | AH35: 0
AG36: 30 | AH36: 0
A37: 몬테카를로(현재 잔액, 1년) — 시나리오를 고르고 F9 | AG37: 31 | AH37: 0
A38: 선택 시나리오 | C38: S0 | D38: ← 드롭다운(S0~S4·U1) | AG38: 32 | AH38: 0
A39: PD 배수 | C39: =INDEX($J$6:$J$12,MATCH($C$38,$A$6:$A$12,0)) | AG39: 33 | AH39: 0
A40: LGD 가산 | C40: =INDEX($K$6:$K$12,MATCH($C$38,$A$6:$A$12,0)) | AG40: 34 | AH40: 0
A41: 공통요인 Z(1회) | C41: =_xlfn.NORM.S.INV(RAND()) | AG41: 35 | AH41: 0
A42: 1회 손실 TotalLoss(USD) | C42: =SUM($AE$65:$AE$214) | AG42: 36 | AH42: 0
A43: 해석적 EL(선택 시나리오) | C43: =SUMPRODUCT($AC$65:$AC$214,$AD$65:$AD$214) | AG43: 37 | AH43: 0
A44: 평균(1,000회) | C44: =AVERAGE($AH$7:$AH$1006) | D44: ← 데이터 표 AG6:AH1006(F9로 갱신) | AG44: 38 | AH44: 0
A45: 표준편차 | C45: =_xlfn.STDEV.S($AH$7:$AH$1006) | AG45: 39 | AH45: 0
A46: P95 | C46: =_xlfn.PERCENTILE.INC($AH$7:$AH$1006,0.95) | AG46: 40 | AH46: 0
A47: P99 | C47: =_xlfn.PERCENTILE.INC($AH$7:$AH$1006,0.99) | AG47: 41 | AH47: 0
A48: 최대 | C48: =MAX($AH$7:$AH$1006) | AG48: 42 | AH48: 0
A49: 손실 > 0 비율 | C49: =IFERROR(COUNTIF($AH$7:$AH$1006,">0")/COUNT($AH$7:$AH$1006),0) | AG49: 43 | AH49: 0
A50: 평균 ÷ 해석적 EL − 1 | C50: =IFERROR(C44/C43-1,0) | AG50: 44 | AH50: 0
AG51: 45 | AH51: 0
A52: 구간 하한 | B52: 구간 상한 | C52: 횟수 | E52: 구간 폭 | F52: =MAX(1000,ROUNDUP(MAX($AH$7:$AH$1006)/10,-3)) | AG52: 46 | AH52: 0
A53: 0 | B53: 0 | C53: =COUNTIF($AH$7:$AH$1006,0) | AG53: 47 | AH53: 0
A54: =(ROW()-54)*$F$52 | B54: =A54+$F$52 | C54: =COUNTIFS($AH$7:$AH$1006,">0",$AH$7:$AH$1006,"<="&B54) | AG54: 48 | AH54: 0
A55: =(ROW()-54)*$F$52 | B55: =A55+$F$52 | C55: =COUNTIFS($AH$7:$AH$1006,">"&A55,$AH$7:$AH$1006,"<="&B55) | AG55: 49 | AH55: 0
A56: =(ROW()-54)*$F$52 | B56: =A56+$F$52 | C56: =COUNTIFS($AH$7:$AH$1006,">"&A56,$AH$7:$AH$1006,"<="&B56) | AG56: 50 | AH56: 0
A57: =(ROW()-54)*$F$52 | B57: =A57+$F$52 | C57: =COUNTIFS($AH$7:$AH$1006,">"&A57,$AH$7:$AH$1006,"<="&B57) | AG57: 51 | AH57: 0
A58: =(ROW()-54)*$F$52 | B58: =A58+$F$52 | C58: =COUNTIFS($AH$7:$AH$1006,">"&A58,$AH$7:$AH$1006,"<="&B58) | AG58: 52 | AH58: 0
A59: =(ROW()-54)*$F$52 | B59: =A59+$F$52 | C59: =COUNTIFS($AH$7:$AH$1006,">"&A59,$AH$7:$AH$1006,"<="&B59) | AG59: 53 | AH59: 0
A60: =(ROW()-54)*$F$52 | B60: =A60+$F$52 | C60: =COUNTIFS($AH$7:$AH$1006,">"&A60,$AH$7:$AH$1006,"<="&B60) | AG60: 54 | AH60: 0
A61: =(ROW()-54)*$F$52 | B61: =A61+$F$52 | C61: =COUNTIFS($AH$7:$AH$1006,">"&A61,$AH$7:$AH$1006,"<="&B61) | AG61: 55 | AH61: 0
A62: =(ROW()-54)*$F$52 | B62: =A62+$F$52 | C62: =COUNTIFS($AH$7:$AH$1006,">"&A62,$AH$7:$AH$1006,"<="&B62) | AG62: 56 | AH62: 0
A63: =(ROW()-54)*$F$52 | B63: =A63+$F$52 | C63: =COUNTIF($AH$7:$AH$1006,">"&A63) | AG63: 57 | AH63: 0
A64: buyer_id | B64: 잔액 USD | C64: PD_eff | D64: LGD | E64: 보상비율 | F64: 가산 | G64: 결제기간 | H64: CRC(미분류 0) | I64: L/C | J64: 통화 | K64: EL S0 | L64: EL S1 | M64: EL S2 | N64: EL S3 | O64: EL S4 | P64: EL U1 | Q64: 금융비용 S0 | R64: 금융비용 S1 | S64: 금융비용 S2 | T64: 금융비용 S3 | U64: 금융비용 S4 | V64: 금융비용 U1 | W64: 송금지연 S0 | X64: 송금지연 S1 | Y64: 송금지연 S2 | Z64: 송금지연 S3 | AA64: 송금지연 S4 | AB64: 송금지연 U1 | AC64: MC PD | AD64: MC 손실 | AE64: MC 1회 | AG64: 58 | AH64: 0
A65: =IF('02_Buyers'!$A2="","",'02_Buyers'!$A2) | B65: =IF($A65="",0,'02_Buyers'!$Z2) | C65: =IF($A65="",0,'02_Buyers'!$AM2) | D65: =IF($A65="",0,'02_Buyers'!$AN2) | E65: =IF($A65="",0,'02_Buyers'!$AO2) | F65: =IF($A65="",0,'02_Buyers'!$AP2) | G65: =IF($A65="",0,'02_Buyers'!$V2) | H65: =IF(OR($A65="",'02_Buyers'!$AC2=""),0,'02_Buyers'!$AC2) | I65: =IF($A65="",0,IF(OR('02_Buyers'!$U2="LC_SIGHT",'02_Buyers'!$U2="LC_USANCE"),1,0)) | J65: =IF($A65="","",'02_Buyers'!$T2) | K65: =IF($A65="",0,$B65*MIN(1,$C65*$J$6)*IF($I65=1,LGD_LC,MIN(1,LGD+$K$6))*(1-$E65)) | L65: =IF($A65="",0,$B65*MIN(1,$C65*$J$7)*IF($I65=1,LGD_LC,MIN(1,LGD+$K$7))*(1-$E65)) | M65: =IF($A65="",0,$B65*MIN(1,$C65*$J$8)*IF($I65=1,LGD_LC,MIN(1,LGD+$K$8))*(1-$E65)) | N65: =IF($A65="",0,$B65*MIN(1,$C65*$J$9)*IF($I65=1,LGD_LC,MIN(1,LGD+$K$9))*(1-$E65)) | O65: =IF($A65="",0,$B65*MIN(1,$C65*$J$10)*IF($I65=1,LGD_LC,MIN(1,LGD+$K$10))*(1-$E65)) | P65: =IF($A65="",0,$B65*MIN(1,$C65*$J$12)*IF($I65=1,LGD_LC,MIN(1,LGD+$K$12))*(1-$E65)) | Q65: =IF($A65="",0,$B65*(TSOFR3M+$H$6/10000+$F65)*$G65/DayBasis) | R65: =IF($A65="",0,$B65*(TSOFR3M+$H$7/10000+$F65)*$G65/DayBasis) | S65: =IF($A65="",0,$B65*(TSOFR3M+$H$8/10000+$F65)*$G65/DayBasis) | T65: =IF($A65="",0,$B65*(TSOFR3M+$H$9/10000+$F65)*$G65/DayBasis) | U65: =IF($A65="",0,$B65*(TSOFR3M+$H$10/10000+$F65)*$G65/DayBasis) | V65: =IF($A65="",0,$B65*(TSOFR3M+$H$12/10000+$F65)*$G65/DayBasis) | W65: =IF(OR($A65="",$M$6<>"Y",$O$6=""),0,IF($H65>=$O$6,$B65*(TSOFR3M+$H$6/10000+$F65)*$N$6/DayBasis,0)) | X65: =IF(OR($A65="",$M$7<>"Y",$O$7=""),0,IF($H65>=$O$7,$B65*(TSOFR3M+$H$7/10000+$F65)*$N$7/DayBasis,0)) | Y65: =IF(OR($A65="",$M$8<>"Y",$O$8=""),0,IF($H65>=$O$8,$B65*(TSOFR3M+$H$8/10000+$F65)*$N$8/DayBasis,0)) | Z65: =IF(OR($A65="",$M$9<>"Y",$O$9=""),0,IF($H65>=$O$9,$B65*(TSOFR3M+$H$9/10000+$F65)*$N$9/DayBasis,0)) | AA65: =IF(OR($A65="",$M$10<>"Y",$O$10=""),0,IF($H65>=$O$10,$B65*(TSOFR3M+$H$10/10000+$F65)*$N$10/DayBasis,0)) | AB65: =IF(OR($A65="",$M$12<>"Y",$O$12=""),0,IF($H65>=$O$12,$B65*(TSOFR3M+$H$12/10000+$F65)*$N$12/DayBasis,0)) | AC65: =IF($A65="",0,MIN(1,$C65*$C$39)) | AD65: =IF($A65="",0,$B65*IF($I65=1,LGD_LC,MIN(1,LGD+$C$40))*(1-$E65)) | AE65: =IF(OR($A65="",$B65<=0,$AC65<=0),0,IF($AC65>=1,$AD65,IF(_xlfn.NORM.S.INV(RAND())*SQRT(1-Rho)+$C$41*SQRT(Rho)<_xlfn.NORM.S.INV($AC65),$AD65,0))) | AG65: 59 | AH65: 0
A66: =IF('02_Buyers'!$A3="","",'02_Buyers'!$A3) | B66: =IF($A66="",0,'02_Buyers'!$Z3) | C66: =IF($A66="",0,'02_Buyers'!$AM3) | D66: =IF($A66="",0,'02_Buyers'!$AN3) | E66: =IF($A66="",0,'02_Buyers'!$AO3) | F66: =IF($A66="",0,'02_Buyers'!$AP3) | G66: =IF($A66="",0,'02_Buyers'!$V3) | H66: =IF(OR($A66="",'02_Buyers'!$AC3=""),0,'02_Buyers'!$AC3) | I66: =IF($A66="",0,IF(OR('02_Buyers'!$U3="LC_SIGHT",'02_Buyers'!$U3="LC_USANCE"),1,0)) | J66: =IF($A66="","",'02_Buyers'!$T3) | K66: =IF($A66="",0,$B66*MIN(1,$C66*$J$6)*IF($I66=1,LGD_LC,MIN(1,LGD+$K$6))*(1-$E66)) | L66: =IF($A66="",0,$B66*MIN(1,$C66*$J$7)*IF($I66=1,LGD_LC,MIN(1,LGD+$K$7))*(1-$E66)) | M66: =IF($A66="",0,$B66*MIN(1,$C66*$J$8)*IF($I66=1,LGD_LC,MIN(1,LGD+$K$8))*(1-$E66)) | N66: =IF($A66="",0,$B66*MIN(1,$C66*$J$9)*IF($I66=1,LGD_LC,MIN(1,LGD+$K$9))*(1-$E66)) | O66: =IF($A66="",0,$B66*MIN(1,$C66*$J$10)*IF($I66=1,LGD_LC,MIN(1,LGD+$K$10))*(1-$E66)) | P66: =IF($A66="",0,$B66*MIN(1,$C66*$J$12)*IF($I66=1,LGD_LC,MIN(1,LGD+$K$12))*(1-$E66)) | Q66: =IF($A66="",0,$B66*(TSOFR3M+$H$6/10000+$F66)*$G66/DayBasis) | R66: =IF($A66="",0,$B66*(TSOFR3M+$H$7/10000+$F66)*$G66/DayBasis) | S66: =IF($A66="",0,$B66*(TSOFR3M+$H$8/10000+$F66)*$G66/DayBasis) | T66: =IF($A66="",0,$B66*(TSOFR3M+$H$9/10000+$F66)*$G66/DayBasis) | U66: =IF($A66="",0,$B66*(TSOFR3M+$H$10/10000+$F66)*$G66/DayBasis) | V66: =IF($A66="",0,$B66*(TSOFR3M+$H$12/10000+$F66)*$G66/DayBasis) | W66: =IF(OR($A66="",$M$6<>"Y",$O$6=""),0,IF($H66>=$O$6,$B66*(TSOFR3M+$H$6/10000+$F66)*$N$6/DayBasis,0)) | X66: =IF(OR($A66="",$M$7<>"Y",$O$7=""),0,IF($H66>=$O$7,$B66*(TSOFR3M+$H$7/10000+$F66)*$N$7/DayBasis,0)) | Y66: =IF(OR($A66="",$M$8<>"Y",$O$8=""),0,IF($H66>=$O$8,$B66*(TSOFR3M+$H$8/10000+$F66)*$N$8/DayBasis,0)) | Z66: =IF(OR($A66="",$M$9<>"Y",$O$9=""),0,IF($H66>=$O$9,$B66*(TSOFR3M+$H$9/10000+$F66)*$N$9/DayBasis,0)) | AA66: =IF(OR($A66="",$M$10<>"Y",$O$10=""),0,IF($H66>=$O$10,$B66*(TSOFR3M+$H$10/10000+$F66)*$N$10/DayBasis,0)) | AB66: =IF(OR($A66="",$M$12<>"Y",$O$12=""),0,IF($H66>=$O$12,$B66*(TSOFR3M+$H$12/10000+$F66)*$N$12/DayBasis,0)) | AC66: =IF($A66="",0,MIN(1,$C66*$C$39)) | AD66: =IF($A66="",0,$B66*IF($I66=1,LGD_LC,MIN(1,LGD+$C$40))*(1-$E66)) | AE66: =IF(OR($A66="",$B66<=0,$AC66<=0),0,IF($AC66>=1,$AD66,IF(_xlfn.NORM.S.INV(RAND())*SQRT(1-Rho)+$C$41*SQRT(Rho)<_xlfn.NORM.S.INV($AC66),$AD66,0))) | AG66: 60 | AH66: 0
A67: =IF('02_Buyers'!$A4="","",'02_Buyers'!$A4) | B67: =IF($A67="",0,'02_Buyers'!$Z4) | C67: =IF($A67="",0,'02_Buyers'!$AM4) | D67: =IF($A67="",0,'02_Buyers'!$AN4) | E67: =IF($A67="",0,'02_Buyers'!$AO4) | F67: =IF($A67="",0,'02_Buyers'!$AP4) | G67: =IF($A67="",0,'02_Buyers'!$V4) | H67: =IF(OR($A67="",'02_Buyers'!$AC4=""),0,'02_Buyers'!$AC4) | I67: =IF($A67="",0,IF(OR('02_Buyers'!$U4="LC_SIGHT",'02_Buyers'!$U4="LC_USANCE"),1,0)) | J67: =IF($A67="","",'02_Buyers'!$T4) | K67: =IF($A67="",0,$B67*MIN(1,$C67*$J$6)*IF($I67=1,LGD_LC,MIN(1,LGD+$K$6))*(1-$E67)) | L67: =IF($A67="",0,$B67*MIN(1,$C67*$J$7)*IF($I67=1,LGD_LC,MIN(1,LGD+$K$7))*(1-$E67)) | M67: =IF($A67="",0,$B67*MIN(1,$C67*$J$8)*IF($I67=1,LGD_LC,MIN(1,LGD+$K$8))*(1-$E67)) | N67: =IF($A67="",0,$B67*MIN(1,$C67*$J$9)*IF($I67=1,LGD_LC,MIN(1,LGD+$K$9))*(1-$E67)) | O67: =IF($A67="",0,$B67*MIN(1,$C67*$J$10)*IF($I67=1,LGD_LC,MIN(1,LGD+$K$10))*(1-$E67)) | P67: =IF($A67="",0,$B67*MIN(1,$C67*$J$12)*IF($I67=1,LGD_LC,MIN(1,LGD+$K$12))*(1-$E67)) | Q67: =IF($A67="",0,$B67*(TSOFR3M+$H$6/10000+$F67)*$G67/DayBasis) | R67: =IF($A67="",0,$B67*(TSOFR3M+$H$7/10000+$F67)*$G67/DayBasis) | S67: =IF($A67="",0,$B67*(TSOFR3M+$H$8/10000+$F67)*$G67/DayBasis) | T67: =IF($A67="",0,$B67*(TSOFR3M+$H$9/10000+$F67)*$G67/DayBasis) | U67: =IF($A67="",0,$B67*(TSOFR3M+$H$10/10000+$F67)*$G67/DayBasis) | V67: =IF($A67="",0,$B67*(TSOFR3M+$H$12/10000+$F67)*$G67/DayBasis) | W67: =IF(OR($A67="",$M$6<>"Y",$O$6=""),0,IF($H67>=$O$6,$B67*(TSOFR3M+$H$6/10000+$F67)*$N$6/DayBasis,0)) | X67: =IF(OR($A67="",$M$7<>"Y",$O$7=""),0,IF($H67>=$O$7,$B67*(TSOFR3M+$H$7/10000+$F67)*$N$7/DayBasis,0)) | Y67: =IF(OR($A67="",$M$8<>"Y",$O$8=""),0,IF($H67>=$O$8,$B67*(TSOFR3M+$H$8/10000+$F67)*$N$8/DayBasis,0)) | Z67: =IF(OR($A67="",$M$9<>"Y",$O$9=""),0,IF($H67>=$O$9,$B67*(TSOFR3M+$H$9/10000+$F67)*$N$9/DayBasis,0)) | AA67: =IF(OR($A67="",$M$10<>"Y",$O$10=""),0,IF($H67>=$O$10,$B67*(TSOFR3M+$H$10/10000+$F67)*$N$10/DayBasis,0)) | AB67: =IF(OR($A67="",$M$12<>"Y",$O$12=""),0,IF($H67>=$O$12,$B67*(TSOFR3M+$H$12/10000+$F67)*$N$12/DayBasis,0)) | AC67: =IF($A67="",0,MIN(1,$C67*$C$39)) | AD67: =IF($A67="",0,$B67*IF($I67=1,LGD_LC,MIN(1,LGD+$C$40))*(1-$E67)) | AE67: =IF(OR($A67="",$B67<=0,$AC67<=0),0,IF($AC67>=1,$AD67,IF(_xlfn.NORM.S.INV(RAND())*SQRT(1-Rho)+$C$41*SQRT(Rho)<_xlfn.NORM.S.INV($AC67),$AD67,0))) | AG67: 61 | AH67: 0
A68: =IF('02_Buyers'!$A5="","",'02_Buyers'!$A5) | B68: =IF($A68="",0,'02_Buyers'!$Z5) | C68: =IF($A68="",0,'02_Buyers'!$AM5) | D68: =IF($A68="",0,'02_Buyers'!$AN5) | E68: =IF($A68="",0,'02_Buyers'!$AO5) | F68: =IF($A68="",0,'02_Buyers'!$AP5) | G68: =IF($A68="",0,'02_Buyers'!$V5) | H68: =IF(OR($A68="",'02_Buyers'!$AC5=""),0,'02_Buyers'!$AC5) | I68: =IF($A68="",0,IF(OR('02_Buyers'!$U5="LC_SIGHT",'02_Buyers'!$U5="LC_USANCE"),1,0)) | J68: =IF($A68="","",'02_Buyers'!$T5) | K68: =IF($A68="",0,$B68*MIN(1,$C68*$J$6)*IF($I68=1,LGD_LC,MIN(1,LGD+$K$6))*(1-$E68)) | L68: =IF($A68="",0,$B68*MIN(1,$C68*$J$7)*IF($I68=1,LGD_LC,MIN(1,LGD+$K$7))*(1-$E68)) | M68: =IF($A68="",0,$B68*MIN(1,$C68*$J$8)*IF($I68=1,LGD_LC,MIN(1,LGD+$K$8))*(1-$E68)) | N68: =IF($A68="",0,$B68*MIN(1,$C68*$J$9)*IF($I68=1,LGD_LC,MIN(1,LGD+$K$9))*(1-$E68)) | O68: =IF($A68="",0,$B68*MIN(1,$C68*$J$10)*IF($I68=1,LGD_LC,MIN(1,LGD+$K$10))*(1-$E68)) | P68: =IF($A68="",0,$B68*MIN(1,$C68*$J$12)*IF($I68=1,LGD_LC,MIN(1,LGD+$K$12))*(1-$E68)) | Q68: =IF($A68="",0,$B68*(TSOFR3M+$H$6/10000+$F68)*$G68/DayBasis) | R68: =IF($A68="",0,$B68*(TSOFR3M+$H$7/10000+$F68)*$G68/DayBasis) | S68: =IF($A68="",0,$B68*(TSOFR3M+$H$8/10000+$F68)*$G68/DayBasis) | T68: =IF($A68="",0,$B68*(TSOFR3M+$H$9/10000+$F68)*$G68/DayBasis) | U68: =IF($A68="",0,$B68*(TSOFR3M+$H$10/10000+$F68)*$G68/DayBasis) | V68: =IF($A68="",0,$B68*(TSOFR3M+$H$12/10000+$F68)*$G68/DayBasis) | W68: =IF(OR($A68="",$M$6<>"Y",$O$6=""),0,IF($H68>=$O$6,$B68*(TSOFR3M+$H$6/10000+$F68)*$N$6/DayBasis,0)) | X68: =IF(OR($A68="",$M$7<>"Y",$O$7=""),0,IF($H68>=$O$7,$B68*(TSOFR3M+$H$7/10000+$F68)*$N$7/DayBasis,0)) | Y68: =IF(OR($A68="",$M$8<>"Y",$O$8=""),0,IF($H68>=$O$8,$B68*(TSOFR3M+$H$8/10000+$F68)*$N$8/DayBasis,0)) | Z68: =IF(OR($A68="",$M$9<>"Y",$O$9=""),0,IF($H68>=$O$9,$B68*(TSOFR3M+$H$9/10000+$F68)*$N$9/DayBasis,0)) | AA68: =IF(OR($A68="",$M$10<>"Y",$O$10=""),0,IF($H68>=$O$10,$B68*(TSOFR3M+$H$10/10000+$F68)*$N$10/DayBasis,0)) | AB68: =IF(OR($A68="",$M$12<>"Y",$O$12=""),0,IF($H68>=$O$12,$B68*(TSOFR3M+$H$12/10000+$F68)*$N$12/DayBasis,0)) | AC68: =IF($A68="",0,MIN(1,$C68*$C$39)) | AD68: =IF($A68="",0,$B68*IF($I68=1,LGD_LC,MIN(1,LGD+$C$40))*(1-$E68)) | AE68: =IF(OR($A68="",$B68<=0,$AC68<=0),0,IF($AC68>=1,$AD68,IF(_xlfn.NORM.S.INV(RAND())*SQRT(1-Rho)+$C$41*SQRT(Rho)<_xlfn.NORM.S.INV($AC68),$AD68,0))) | AG68: 62 | AH68: 0
A69: =IF('02_Buyers'!$A6="","",'02_Buyers'!$A6) | B69: =IF($A69="",0,'02_Buyers'!$Z6) | C69: =IF($A69="",0,'02_Buyers'!$AM6) | D69: =IF($A69="",0,'02_Buyers'!$AN6) | E69: =IF($A69="",0,'02_Buyers'!$AO6) | F69: =IF($A69="",0,'02_Buyers'!$AP6) | G69: =IF($A69="",0,'02_Buyers'!$V6) | H69: =IF(OR($A69="",'02_Buyers'!$AC6=""),0,'02_Buyers'!$AC6) | I69: =IF($A69="",0,IF(OR('02_Buyers'!$U6="LC_SIGHT",'02_Buyers'!$U6="LC_USANCE"),1,0)) | J69: =IF($A69="","",'02_Buyers'!$T6) | K69: =IF($A69="",0,$B69*MIN(1,$C69*$J$6)*IF($I69=1,LGD_LC,MIN(1,LGD+$K$6))*(1-$E69)) | L69: =IF($A69="",0,$B69*MIN(1,$C69*$J$7)*IF($I69=1,LGD_LC,MIN(1,LGD+$K$7))*(1-$E69)) | M69: =IF($A69="",0,$B69*MIN(1,$C69*$J$8)*IF($I69=1,LGD_LC,MIN(1,LGD+$K$8))*(1-$E69)) | N69: =IF($A69="",0,$B69*MIN(1,$C69*$J$9)*IF($I69=1,LGD_LC,MIN(1,LGD+$K$9))*(1-$E69)) | O69: =IF($A69="",0,$B69*MIN(1,$C69*$J$10)*IF($I69=1,LGD_LC,MIN(1,LGD+$K$10))*(1-$E69)) | P69: =IF($A69="",0,$B69*MIN(1,$C69*$J$12)*IF($I69=1,LGD_LC,MIN(1,LGD+$K$12))*(1-$E69)) | Q69: =IF($A69="",0,$B69*(TSOFR3M+$H$6/10000+$F69)*$G69/DayBasis) | R69: =IF($A69="",0,$B69*(TSOFR3M+$H$7/10000+$F69)*$G69/DayBasis) | S69: =IF($A69="",0,$B69*(TSOFR3M+$H$8/10000+$F69)*$G69/DayBasis) | T69: =IF($A69="",0,$B69*(TSOFR3M+$H$9/10000+$F69)*$G69/DayBasis) | U69: =IF($A69="",0,$B69*(TSOFR3M+$H$10/10000+$F69)*$G69/DayBasis) | V69: =IF($A69="",0,$B69*(TSOFR3M+$H$12/10000+$F69)*$G69/DayBasis) | W69: =IF(OR($A69="",$M$6<>"Y",$O$6=""),0,IF($H69>=$O$6,$B69*(TSOFR3M+$H$6/10000+$F69)*$N$6/DayBasis,0)) | X69: =IF(OR($A69="",$M$7<>"Y",$O$7=""),0,IF($H69>=$O$7,$B69*(TSOFR3M+$H$7/10000+$F69)*$N$7/DayBasis,0)) | Y69: =IF(OR($A69="",$M$8<>"Y",$O$8=""),0,IF($H69>=$O$8,$B69*(TSOFR3M+$H$8/10000+$F69)*$N$8/DayBasis,0)) | Z69: =IF(OR($A69="",$M$9<>"Y",$O$9=""),0,IF($H69>=$O$9,$B69*(TSOFR3M+$H$9/10000+$F69)*$N$9/DayBasis,0)) | AA69: =IF(OR($A69="",$M$10<>"Y",$O$10=""),0,IF($H69>=$O$10,$B69*(TSOFR3M+$H$10/10000+$F69)*$N$10/DayBasis,0)) | AB69: =IF(OR($A69="",$M$12<>"Y",$O$12=""),0,IF($H69>=$O$12,$B69*(TSOFR3M+$H$12/10000+$F69)*$N$12/DayBasis,0)) | AC69: =IF($A69="",0,MIN(1,$C69*$C$39)) | AD69: =IF($A69="",0,$B69*IF($I69=1,LGD_LC,MIN(1,LGD+$C$40))*(1-$E69)) | AE69: =IF(OR($A69="",$B69<=0,$AC69<=0),0,IF($AC69>=1,$AD69,IF(_xlfn.NORM.S.INV(RAND())*SQRT(1-Rho)+$C$41*SQRT(Rho)<_xlfn.NORM.S.INV($AC69),$AD69,0))) | AG69: 63 | AH69: 0
A70: =IF('02_Buyers'!$A7="","",'02_Buyers'!$A7) | B70: =IF($A70="",0,'02_Buyers'!$Z7) | C70: =IF($A70="",0,'02_Buyers'!$AM7) | D70: =IF($A70="",0,'02_Buyers'!$AN7) | E70: =IF($A70="",0,'02_Buyers'!$AO7) | F70: =IF($A70="",0,'02_Buyers'!$AP7) | G70: =IF($A70="",0,'02_Buyers'!$V7) | H70: =IF(OR($A70="",'02_Buyers'!$AC7=""),0,'02_Buyers'!$AC7) | I70: =IF($A70="",0,IF(OR('02_Buyers'!$U7="LC_SIGHT",'02_Buyers'!$U7="LC_USANCE"),1,0)) | J70: =IF($A70="","",'02_Buyers'!$T7) | K70: =IF($A70="",0,$B70*MIN(1,$C70*$J$6)*IF($I70=1,LGD_LC,MIN(1,LGD+$K$6))*(1-$E70)) | L70: =IF($A70="",0,$B70*MIN(1,$C70*$J$7)*IF($I70=1,LGD_LC,MIN(1,LGD+$K$7))*(1-$E70)) | M70: =IF($A70="",0,$B70*MIN(1,$C70*$J$8)*IF($I70=1,LGD_LC,MIN(1,LGD+$K$8))*(1-$E70)) | N70: =IF($A70="",0,$B70*MIN(1,$C70*$J$9)*IF($I70=1,LGD_LC,MIN(1,LGD+$K$9))*(1-$E70)) | O70: =IF($A70="",0,$B70*MIN(1,$C70*$J$10)*IF($I70=1,LGD_LC,MIN(1,LGD+$K$10))*(1-$E70)) | P70: =IF($A70="",0,$B70*MIN(1,$C70*$J$12)*IF($I70=1,LGD_LC,MIN(1,LGD+$K$12))*(1-$E70)) | Q70: =IF($A70="",0,$B70*(TSOFR3M+$H$6/10000+$F70)*$G70/DayBasis) | R70: =IF($A70="",0,$B70*(TSOFR3M+$H$7/10000+$F70)*$G70/DayBasis) | S70: =IF($A70="",0,$B70*(TSOFR3M+$H$8/10000+$F70)*$G70/DayBasis) | T70: =IF($A70="",0,$B70*(TSOFR3M+$H$9/10000+$F70)*$G70/DayBasis) | U70: =IF($A70="",0,$B70*(TSOFR3M+$H$10/10000+$F70)*$G70/DayBasis) | V70: =IF($A70="",0,$B70*(TSOFR3M+$H$12/10000+$F70)*$G70/DayBasis) | W70: =IF(OR($A70="",$M$6<>"Y",$O$6=""),0,IF($H70>=$O$6,$B70*(TSOFR3M+$H$6/10000+$F70)*$N$6/DayBasis,0)) | X70: =IF(OR($A70="",$M$7<>"Y",$O$7=""),0,IF($H70>=$O$7,$B70*(TSOFR3M+$H$7/10000+$F70)*$N$7/DayBasis,0)) | Y70: =IF(OR($A70="",$M$8<>"Y",$O$8=""),0,IF($H70>=$O$8,$B70*(TSOFR3M+$H$8/10000+$F70)*$N$8/DayBasis,0)) | Z70: =IF(OR($A70="",$M$9<>"Y",$O$9=""),0,IF($H70>=$O$9,$B70*(TSOFR3M+$H$9/10000+$F70)*$N$9/DayBasis,0)) | AA70: =IF(OR($A70="",$M$10<>"Y",$O$10=""),0,IF($H70>=$O$10,$B70*(TSOFR3M+$H$10/10000+$F70)*$N$10/DayBasis,0)) | AB70: =IF(OR($A70="",$M$12<>"Y",$O$12=""),0,IF($H70>=$O$12,$B70*(TSOFR3M+$H$12/10000+$F70)*$N$12/DayBasis,0)) | AC70: =IF($A70="",0,MIN(1,$C70*$C$39)) | AD70: =IF($A70="",0,$B70*IF($I70=1,LGD_LC,MIN(1,LGD+$C$40))*(1-$E70)) | AE70: =IF(OR($A70="",$B70<=0,$AC70<=0),0,IF($AC70>=1,$AD70,IF(_xlfn.NORM.S.INV(RAND())*SQRT(1-Rho)+$C$41*SQRT(Rho)<_xlfn.NORM.S.INV($AC70),$AD70,0))) | AG70: 64 | AH70: 0
A71: =IF('02_Buyers'!$A8="","",'02_Buyers'!$A8) | B71: =IF($A71="",0,'02_Buyers'!$Z8) | C71: =IF($A71="",0,'02_Buyers'!$AM8) | D71: =IF($A71="",0,'02_Buyers'!$AN8) | E71: =IF($A71="",0,'02_Buyers'!$AO8) | F71: =IF($A71="",0,'02_Buyers'!$AP8) | G71: =IF($A71="",0,'02_Buyers'!$V8) | H71: =IF(OR($A71="",'02_Buyers'!$AC8=""),0,'02_Buyers'!$AC8) | I71: =IF($A71="",0,IF(OR('02_Buyers'!$U8="LC_SIGHT",'02_Buyers'!$U8="LC_USANCE"),1,0)) | J71: =IF($A71="","",'02_Buyers'!$T8) | K71: =IF($A71="",0,$B71*MIN(1,$C71*$J$6)*IF($I71=1,LGD_LC,MIN(1,LGD+$K$6))*(1-$E71)) | L71: =IF($A71="",0,$B71*MIN(1,$C71*$J$7)*IF($I71=1,LGD_LC,MIN(1,LGD+$K$7))*(1-$E71)) | M71: =IF($A71="",0,$B71*MIN(1,$C71*$J$8)*IF($I71=1,LGD_LC,MIN(1,LGD+$K$8))*(1-$E71)) | N71: =IF($A71="",0,$B71*MIN(1,$C71*$J$9)*IF($I71=1,LGD_LC,MIN(1,LGD+$K$9))*(1-$E71)) | O71: =IF($A71="",0,$B71*MIN(1,$C71*$J$10)*IF($I71=1,LGD_LC,MIN(1,LGD+$K$10))*(1-$E71)) | P71: =IF($A71="",0,$B71*MIN(1,$C71*$J$12)*IF($I71=1,LGD_LC,MIN(1,LGD+$K$12))*(1-$E71)) | Q71: =IF($A71="",0,$B71*(TSOFR3M+$H$6/10000+$F71)*$G71/DayBasis) | R71: =IF($A71="",0,$B71*(TSOFR3M+$H$7/10000+$F71)*$G71/DayBasis) | S71: =IF($A71="",0,$B71*(TSOFR3M+$H$8/10000+$F71)*$G71/DayBasis) | T71: =IF($A71="",0,$B71*(TSOFR3M+$H$9/10000+$F71)*$G71/DayBasis) | U71: =IF($A71="",0,$B71*(TSOFR3M+$H$10/10000+$F71)*$G71/DayBasis) | V71: =IF($A71="",0,$B71*(TSOFR3M+$H$12/10000+$F71)*$G71/DayBasis) | W71: =IF(OR($A71="",$M$6<>"Y",$O$6=""),0,IF($H71>=$O$6,$B71*(TSOFR3M+$H$6/10000+$F71)*$N$6/DayBasis,0)) | X71: =IF(OR($A71="",$M$7<>"Y",$O$7=""),0,IF($H71>=$O$7,$B71*(TSOFR3M+$H$7/10000+$F71)*$N$7/DayBasis,0)) | Y71: =IF(OR($A71="",$M$8<>"Y",$O$8=""),0,IF($H71>=$O$8,$B71*(TSOFR3M+$H$8/10000+$F71)*$N$8/DayBasis,0)) | Z71: =IF(OR($A71="",$M$9<>"Y",$O$9=""),0,IF($H71>=$O$9,$B71*(TSOFR3M+$H$9/10000+$F71)*$N$9/DayBasis,0)) | AA71: =IF(OR($A71="",$M$10<>"Y",$O$10=""),0,IF($H71>=$O$10,$B71*(TSOFR3M+$H$10/10000+$F71)*$N$10/DayBasis,0)) | AB71: =IF(OR($A71="",$M$12<>"Y",$O$12=""),0,IF($H71>=$O$12,$B71*(TSOFR3M+$H$12/10000+$F71)*$N$12/DayBasis,0)) | AC71: =IF($A71="",0,MIN(1,$C71*$C$39)) | AD71: =IF($A71="",0,$B71*IF($I71=1,LGD_LC,MIN(1,LGD+$C$40))*(1-$E71)) | AE71: =IF(OR($A71="",$B71<=0,$AC71<=0),0,IF($AC71>=1,$AD71,IF(_xlfn.NORM.S.INV(RAND())*SQRT(1-Rho)+$C$41*SQRT(Rho)<_xlfn.NORM.S.INV($AC71),$AD71,0))) | AG71: 65 | AH71: 0
A72: =IF('02_Buyers'!$A9="","",'02_Buyers'!$A9) | B72: =IF($A72="",0,'02_Buyers'!$Z9) | C72: =IF($A72="",0,'02_Buyers'!$AM9) | D72: =IF($A72="",0,'02_Buyers'!$AN9) | E72: =IF($A72="",0,'02_Buyers'!$AO9) | F72: =IF($A72="",0,'02_Buyers'!$AP9) | G72: =IF($A72="",0,'02_Buyers'!$V9) | H72: =IF(OR($A72="",'02_Buyers'!$AC9=""),0,'02_Buyers'!$AC9) | I72: =IF($A72="",0,IF(OR('02_Buyers'!$U9="LC_SIGHT",'02_Buyers'!$U9="LC_USANCE"),1,0)) | J72: =IF($A72="","",'02_Buyers'!$T9) | K72: =IF($A72="",0,$B72*MIN(1,$C72*$J$6)*IF($I72=1,LGD_LC,MIN(1,LGD+$K$6))*(1-$E72)) | L72: =IF($A72="",0,$B72*MIN(1,$C72*$J$7)*IF($I72=1,LGD_LC,MIN(1,LGD+$K$7))*(1-$E72)) | M72: =IF($A72="",0,$B72*MIN(1,$C72*$J$8)*IF($I72=1,LGD_LC,MIN(1,LGD+$K$8))*(1-$E72)) | N72: =IF($A72="",0,$B72*MIN(1,$C72*$J$9)*IF($I72=1,LGD_LC,MIN(1,LGD+$K$9))*(1-$E72)) | O72: =IF($A72="",0,$B72*MIN(1,$C72*$J$10)*IF($I72=1,LGD_LC,MIN(1,LGD+$K$10))*(1-$E72)) | P72: =IF($A72="",0,$B72*MIN(1,$C72*$J$12)*IF($I72=1,LGD_LC,MIN(1,LGD+$K$12))*(1-$E72)) | Q72: =IF($A72="",0,$B72*(TSOFR3M+$H$6/10000+$F72)*$G72/DayBasis) | R72: =IF($A72="",0,$B72*(TSOFR3M+$H$7/10000+$F72)*$G72/DayBasis) | S72: =IF($A72="",0,$B72*(TSOFR3M+$H$8/10000+$F72)*$G72/DayBasis) | T72: =IF($A72="",0,$B72*(TSOFR3M+$H$9/10000+$F72)*$G72/DayBasis) | U72: =IF($A72="",0,$B72*(TSOFR3M+$H$10/10000+$F72)*$G72/DayBasis) | V72: =IF($A72="",0,$B72*(TSOFR3M+$H$12/10000+$F72)*$G72/DayBasis) | W72: =IF(OR($A72="",$M$6<>"Y",$O$6=""),0,IF($H72>=$O$6,$B72*(TSOFR3M+$H$6/10000+$F72)*$N$6/DayBasis,0)) | X72: =IF(OR($A72="",$M$7<>"Y",$O$7=""),0,IF($H72>=$O$7,$B72*(TSOFR3M+$H$7/10000+$F72)*$N$7/DayBasis,0)) | Y72: =IF(OR($A72="",$M$8<>"Y",$O$8=""),0,IF($H72>=$O$8,$B72*(TSOFR3M+$H$8/10000+$F72)*$N$8/DayBasis,0)) | Z72: =IF(OR($A72="",$M$9<>"Y",$O$9=""),0,IF($H72>=$O$9,$B72*(TSOFR3M+$H$9/10000+$F72)*$N$9/DayBasis,0)) | AA72: =IF(OR($A72="",$M$10<>"Y",$O$10=""),0,IF($H72>=$O$10,$B72*(TSOFR3M+$H$10/10000+$F72)*$N$10/DayBasis,0)) | AB72: =IF(OR($A72="",$M$12<>"Y",$O$12=""),0,IF($H72>=$O$12,$B72*(TSOFR3M+$H$12/10000+$F72)*$N$12/DayBasis,0)) | AC72: =IF($A72="",0,MIN(1,$C72*$C$39)) | AD72: =IF($A72="",0,$B72*IF($I72=1,LGD_LC,MIN(1,LGD+$C$40))*(1-$E72)) | AE72: =IF(OR($A72="",$B72<=0,$AC72<=0),0,IF($AC72>=1,$AD72,IF(_xlfn.NORM.S.INV(RAND())*SQRT(1-Rho)+$C$41*SQRT(Rho)<_xlfn.NORM.S.INV($AC72),$AD72,0))) | AG72: 66 | AH72: 0
A73: =IF('02_Buyers'!$A10="","",'02_Buyers'!$A10) | B73: =IF($A73="",0,'02_Buyers'!$Z10) | C73: =IF($A73="",0,'02_Buyers'!$AM10) | D73: =IF($A73="",0,'02_Buyers'!$AN10) | E73: =IF($A73="",0,'02_Buyers'!$AO10) | F73: =IF($A73="",0,'02_Buyers'!$AP10) | G73: =IF($A73="",0,'02_Buyers'!$V10) | H73: =IF(OR($A73="",'02_Buyers'!$AC10=""),0,'02_Buyers'!$AC10) | I73: =IF($A73="",0,IF(OR('02_Buyers'!$U10="LC_SIGHT",'02_Buyers'!$U10="LC_USANCE"),1,0)) | J73: =IF($A73="","",'02_Buyers'!$T10) | K73: =IF($A73="",0,$B73*MIN(1,$C73*$J$6)*IF($I73=1,LGD_LC,MIN(1,LGD+$K$6))*(1-$E73)) | L73: =IF($A73="",0,$B73*MIN(1,$C73*$J$7)*IF($I73=1,LGD_LC,MIN(1,LGD+$K$7))*(1-$E73)) | M73: =IF($A73="",0,$B73*MIN(1,$C73*$J$8)*IF($I73=1,LGD_LC,MIN(1,LGD+$K$8))*(1-$E73)) | N73: =IF($A73="",0,$B73*MIN(1,$C73*$J$9)*IF($I73=1,LGD_LC,MIN(1,LGD+$K$9))*(1-$E73)) | O73: =IF($A73="",0,$B73*MIN(1,$C73*$J$10)*IF($I73=1,LGD_LC,MIN(1,LGD+$K$10))*(1-$E73)) | P73: =IF($A73="",0,$B73*MIN(1,$C73*$J$12)*IF($I73=1,LGD_LC,MIN(1,LGD+$K$12))*(1-$E73)) | Q73: =IF($A73="",0,$B73*(TSOFR3M+$H$6/10000+$F73)*$G73/DayBasis) | R73: =IF($A73="",0,$B73*(TSOFR3M+$H$7/10000+$F73)*$G73/DayBasis) | S73: =IF($A73="",0,$B73*(TSOFR3M+$H$8/10000+$F73)*$G73/DayBasis) | T73: =IF($A73="",0,$B73*(TSOFR3M+$H$9/10000+$F73)*$G73/DayBasis) | U73: =IF($A73="",0,$B73*(TSOFR3M+$H$10/10000+$F73)*$G73/DayBasis) | V73: =IF($A73="",0,$B73*(TSOFR3M+$H$12/10000+$F73)*$G73/DayBasis) | W73: =IF(OR($A73="",$M$6<>"Y",$O$6=""),0,IF($H73>=$O$6,$B73*(TSOFR3M+$H$6/10000+$F73)*$N$6/DayBasis,0)) | X73: =IF(OR($A73="",$M$7<>"Y",$O$7=""),0,IF($H73>=$O$7,$B73*(TSOFR3M+$H$7/10000+$F73)*$N$7/DayBasis,0)) | Y73: =IF(OR($A73="",$M$8<>"Y",$O$8=""),0,IF($H73>=$O$8,$B73*(TSOFR3M+$H$8/10000+$F73)*$N$8/DayBasis,0)) | Z73: =IF(OR($A73="",$M$9<>"Y",$O$9=""),0,IF($H73>=$O$9,$B73*(TSOFR3M+$H$9/10000+$F73)*$N$9/DayBasis,0)) | AA73: =IF(OR($A73="",$M$10<>"Y",$O$10=""),0,IF($H73>=$O$10,$B73*(TSOFR3M+$H$10/10000+$F73)*$N$10/DayBasis,0)) | AB73: =IF(OR($A73="",$M$12<>"Y",$O$12=""),0,IF($H73>=$O$12,$B73*(TSOFR3M+$H$12/10000+$F73)*$N$12/DayBasis,0)) | AC73: =IF($A73="",0,MIN(1,$C73*$C$39)) | AD73: =IF($A73="",0,$B73*IF($I73=1,LGD_LC,MIN(1,LGD+$C$40))*(1-$E73)) | AE73: =IF(OR($A73="",$B73<=0,$AC73<=0),0,IF($AC73>=1,$AD73,IF(_xlfn.NORM.S.INV(RAND())*SQRT(1-Rho)+$C$41*SQRT(Rho)<_xlfn.NORM.S.INV($AC73),$AD73,0))) | AG73: 67 | AH73: 0
A74: =IF('02_Buyers'!$A11="","",'02_Buyers'!$A11) | B74: =IF($A74="",0,'02_Buyers'!$Z11) | C74: =IF($A74="",0,'02_Buyers'!$AM11) | D74: =IF($A74="",0,'02_Buyers'!$AN11) | E74: =IF($A74="",0,'02_Buyers'!$AO11) | F74: =IF($A74="",0,'02_Buyers'!$AP11) | G74: =IF($A74="",0,'02_Buyers'!$V11) | H74: =IF(OR($A74="",'02_Buyers'!$AC11=""),0,'02_Buyers'!$AC11) | I74: =IF($A74="",0,IF(OR('02_Buyers'!$U11="LC_SIGHT",'02_Buyers'!$U11="LC_USANCE"),1,0)) | J74: =IF($A74="","",'02_Buyers'!$T11) | K74: =IF($A74="",0,$B74*MIN(1,$C74*$J$6)*IF($I74=1,LGD_LC,MIN(1,LGD+$K$6))*(1-$E74)) | L74: =IF($A74="",0,$B74*MIN(1,$C74*$J$7)*IF($I74=1,LGD_LC,MIN(1,LGD+$K$7))*(1-$E74)) | M74: =IF($A74="",0,$B74*MIN(1,$C74*$J$8)*IF($I74=1,LGD_LC,MIN(1,LGD+$K$8))*(1-$E74)) | N74: =IF($A74="",0,$B74*MIN(1,$C74*$J$9)*IF($I74=1,LGD_LC,MIN(1,LGD+$K$9))*(1-$E74)) | O74: =IF($A74="",0,$B74*MIN(1,$C74*$J$10)*IF($I74=1,LGD_LC,MIN(1,LGD+$K$10))*(1-$E74)) | P74: =IF($A74="",0,$B74*MIN(1,$C74*$J$12)*IF($I74=1,LGD_LC,MIN(1,LGD+$K$12))*(1-$E74)) | Q74: =IF($A74="",0,$B74*(TSOFR3M+$H$6/10000+$F74)*$G74/DayBasis) | R74: =IF($A74="",0,$B74*(TSOFR3M+$H$7/10000+$F74)*$G74/DayBasis) | S74: =IF($A74="",0,$B74*(TSOFR3M+$H$8/10000+$F74)*$G74/DayBasis) | T74: =IF($A74="",0,$B74*(TSOFR3M+$H$9/10000+$F74)*$G74/DayBasis) | U74: =IF($A74="",0,$B74*(TSOFR3M+$H$10/10000+$F74)*$G74/DayBasis) | V74: =IF($A74="",0,$B74*(TSOFR3M+$H$12/10000+$F74)*$G74/DayBasis) | W74: =IF(OR($A74="",$M$6<>"Y",$O$6=""),0,IF($H74>=$O$6,$B74*(TSOFR3M+$H$6/10000+$F74)*$N$6/DayBasis,0)) | X74: =IF(OR($A74="",$M$7<>"Y",$O$7=""),0,IF($H74>=$O$7,$B74*(TSOFR3M+$H$7/10000+$F74)*$N$7/DayBasis,0)) | Y74: =IF(OR($A74="",$M$8<>"Y",$O$8=""),0,IF($H74>=$O$8,$B74*(TSOFR3M+$H$8/10000+$F74)*$N$8/DayBasis,0)) | Z74: =IF(OR($A74="",$M$9<>"Y",$O$9=""),0,IF($H74>=$O$9,$B74*(TSOFR3M+$H$9/10000+$F74)*$N$9/DayBasis,0)) | AA74: =IF(OR($A74="",$M$10<>"Y",$O$10=""),0,IF($H74>=$O$10,$B74*(TSOFR3M+$H$10/10000+$F74)*$N$10/DayBasis,0)) | AB74: =IF(OR($A74="",$M$12<>"Y",$O$12=""),0,IF($H74>=$O$12,$B74*(TSOFR3M+$H$12/10000+$F74)*$N$12/DayBasis,0)) | AC74: =IF($A74="",0,MIN(1,$C74*$C$39)) | AD74: =IF($A74="",0,$B74*IF($I74=1,LGD_LC,MIN(1,LGD+$C$40))*(1-$E74)) | AE74: =IF(OR($A74="",$B74<=0,$AC74<=0),0,IF($AC74>=1,$AD74,IF(_xlfn.NORM.S.INV(RAND())*SQRT(1-Rho)+$C$41*SQRT(Rho)<_xlfn.NORM.S.INV($AC74),$AD74,0))) | AG74: 68 | AH74: 0
A75: =IF('02_Buyers'!$A12="","",'02_Buyers'!$A12) | B75: =IF($A75="",0,'02_Buyers'!$Z12) | C75: =IF($A75="",0,'02_Buyers'!$AM12) | D75: =IF($A75="",0,'02_Buyers'!$AN12) | E75: =IF($A75="",0,'02_Buyers'!$AO12) | F75: =IF($A75="",0,'02_Buyers'!$AP12) | G75: =IF($A75="",0,'02_Buyers'!$V12) | H75: =IF(OR($A75="",'02_Buyers'!$AC12=""),0,'02_Buyers'!$AC12) | I75: =IF($A75="",0,IF(OR('02_Buyers'!$U12="LC_SIGHT",'02_Buyers'!$U12="LC_USANCE"),1,0)) | J75: =IF($A75="","",'02_Buyers'!$T12) | K75: =IF($A75="",0,$B75*MIN(1,$C75*$J$6)*IF($I75=1,LGD_LC,MIN(1,LGD+$K$6))*(1-$E75)) | L75: =IF($A75="",0,$B75*MIN(1,$C75*$J$7)*IF($I75=1,LGD_LC,MIN(1,LGD+$K$7))*(1-$E75)) | M75: =IF($A75="",0,$B75*MIN(1,$C75*$J$8)*IF($I75=1,LGD_LC,MIN(1,LGD+$K$8))*(1-$E75)) | N75: =IF($A75="",0,$B75*MIN(1,$C75*$J$9)*IF($I75=1,LGD_LC,MIN(1,LGD+$K$9))*(1-$E75)) | O75: =IF($A75="",0,$B75*MIN(1,$C75*$J$10)*IF($I75=1,LGD_LC,MIN(1,LGD+$K$10))*(1-$E75)) | P75: =IF($A75="",0,$B75*MIN(1,$C75*$J$12)*IF($I75=1,LGD_LC,MIN(1,LGD+$K$12))*(1-$E75)) | Q75: =IF($A75="",0,$B75*(TSOFR3M+$H$6/10000+$F75)*$G75/DayBasis) | R75: =IF($A75="",0,$B75*(TSOFR3M+$H$7/10000+$F75)*$G75/DayBasis) | S75: =IF($A75="",0,$B75*(TSOFR3M+$H$8/10000+$F75)*$G75/DayBasis) | T75: =IF($A75="",0,$B75*(TSOFR3M+$H$9/10000+$F75)*$G75/DayBasis) | U75: =IF($A75="",0,$B75*(TSOFR3M+$H$10/10000+$F75)*$G75/DayBasis) | V75: =IF($A75="",0,$B75*(TSOFR3M+$H$12/10000+$F75)*$G75/DayBasis) | W75: =IF(OR($A75="",$M$6<>"Y",$O$6=""),0,IF($H75>=$O$6,$B75*(TSOFR3M+$H$6/10000+$F75)*$N$6/DayBasis,0)) | X75: =IF(OR($A75="",$M$7<>"Y",$O$7=""),0,IF($H75>=$O$7,$B75*(TSOFR3M+$H$7/10000+$F75)*$N$7/DayBasis,0)) | Y75: =IF(OR($A75="",$M$8<>"Y",$O$8=""),0,IF($H75>=$O$8,$B75*(TSOFR3M+$H$8/10000+$F75)*$N$8/DayBasis,0)) | Z75: =IF(OR($A75="",$M$9<>"Y",$O$9=""),0,IF($H75>=$O$9,$B75*(TSOFR3M+$H$9/10000+$F75)*$N$9/DayBasis,0)) | AA75: =IF(OR($A75="",$M$10<>"Y",$O$10=""),0,IF($H75>=$O$10,$B75*(TSOFR3M+$H$10/10000+$F75)*$N$10/DayBasis,0)) | AB75: =IF(OR($A75="",$M$12<>"Y",$O$12=""),0,IF($H75>=$O$12,$B75*(TSOFR3M+$H$12/10000+$F75)*$N$12/DayBasis,0)) | AC75: =IF($A75="",0,MIN(1,$C75*$C$39)) | AD75: =IF($A75="",0,$B75*IF($I75=1,LGD_LC,MIN(1,LGD+$C$40))*(1-$E75)) | AE75: =IF(OR($A75="",$B75<=0,$AC75<=0),0,IF($AC75>=1,$AD75,IF(_xlfn.NORM.S.INV(RAND())*SQRT(1-Rho)+$C$41*SQRT(Rho)<_xlfn.NORM.S.INV($AC75),$AD75,0))) | AG75: 69 | AH75: 0
A76: =IF('02_Buyers'!$A13="","",'02_Buyers'!$A13) | B76: =IF($A76="",0,'02_Buyers'!$Z13) | C76: =IF($A76="",0,'02_Buyers'!$AM13) | D76: =IF($A76="",0,'02_Buyers'!$AN13) | E76: =IF($A76="",0,'02_Buyers'!$AO13) | F76: =IF($A76="",0,'02_Buyers'!$AP13) | G76: =IF($A76="",0,'02_Buyers'!$V13) | H76: =IF(OR($A76="",'02_Buyers'!$AC13=""),0,'02_Buyers'!$AC13) | I76: =IF($A76="",0,IF(OR('02_Buyers'!$U13="LC_SIGHT",'02_Buyers'!$U13="LC_USANCE"),1,0)) | J76: =IF($A76="","",'02_Buyers'!$T13) | K76: =IF($A76="",0,$B76*MIN(1,$C76*$J$6)*IF($I76=1,LGD_LC,MIN(1,LGD+$K$6))*(1-$E76)) | L76: =IF($A76="",0,$B76*MIN(1,$C76*$J$7)*IF($I76=1,LGD_LC,MIN(1,LGD+$K$7))*(1-$E76)) | M76: =IF($A76="",0,$B76*MIN(1,$C76*$J$8)*IF($I76=1,LGD_LC,MIN(1,LGD+$K$8))*(1-$E76)) | N76: =IF($A76="",0,$B76*MIN(1,$C76*$J$9)*IF($I76=1,LGD_LC,MIN(1,LGD+$K$9))*(1-$E76)) | O76: =IF($A76="",0,$B76*MIN(1,$C76*$J$10)*IF($I76=1,LGD_LC,MIN(1,LGD+$K$10))*(1-$E76)) | P76: =IF($A76="",0,$B76*MIN(1,$C76*$J$12)*IF($I76=1,LGD_LC,MIN(1,LGD+$K$12))*(1-$E76)) | Q76: =IF($A76="",0,$B76*(TSOFR3M+$H$6/10000+$F76)*$G76/DayBasis) | R76: =IF($A76="",0,$B76*(TSOFR3M+$H$7/10000+$F76)*$G76/DayBasis) | S76: =IF($A76="",0,$B76*(TSOFR3M+$H$8/10000+$F76)*$G76/DayBasis) | T76: =IF($A76="",0,$B76*(TSOFR3M+$H$9/10000+$F76)*$G76/DayBasis) | U76: =IF($A76="",0,$B76*(TSOFR3M+$H$10/10000+$F76)*$G76/DayBasis) | V76: =IF($A76="",0,$B76*(TSOFR3M+$H$12/10000+$F76)*$G76/DayBasis) | W76: =IF(OR($A76="",$M$6<>"Y",$O$6=""),0,IF($H76>=$O$6,$B76*(TSOFR3M+$H$6/10000+$F76)*$N$6/DayBasis,0)) | X76: =IF(OR($A76="",$M$7<>"Y",$O$7=""),0,IF($H76>=$O$7,$B76*(TSOFR3M+$H$7/10000+$F76)*$N$7/DayBasis,0)) | Y76: =IF(OR($A76="",$M$8<>"Y",$O$8=""),0,IF($H76>=$O$8,$B76*(TSOFR3M+$H$8/10000+$F76)*$N$8/DayBasis,0)) | Z76: =IF(OR($A76="",$M$9<>"Y",$O$9=""),0,IF($H76>=$O$9,$B76*(TSOFR3M+$H$9/10000+$F76)*$N$9/DayBasis,0)) | AA76: =IF(OR($A76="",$M$10<>"Y",$O$10=""),0,IF($H76>=$O$10,$B76*(TSOFR3M+$H$10/10000+$F76)*$N$10/DayBasis,0)) | AB76: =IF(OR($A76="",$M$12<>"Y",$O$12=""),0,IF($H76>=$O$12,$B76*(TSOFR3M+$H$12/10000+$F76)*$N$12/DayBasis,0)) | AC76: =IF($A76="",0,MIN(1,$C76*$C$39)) | AD76: =IF($A76="",0,$B76*IF($I76=1,LGD_LC,MIN(1,LGD+$C$40))*(1-$E76)) | AE76: =IF(OR($A76="",$B76<=0,$AC76<=0),0,IF($AC76>=1,$AD76,IF(_xlfn.NORM.S.INV(RAND())*SQRT(1-Rho)+$C$41*SQRT(Rho)<_xlfn.NORM.S.INV($AC76),$AD76,0))) | AG76: 70 | AH76: 0
... A214: =IF('02_Buyers'!$A151="","",'02_Buyers'!$A151) | B214: =IF($A214="",0,'02_Buyers'!$Z151) | C214: =IF($A214="",0,'02_Buyers'!$AM151) | D214: =IF($A214="",0,'02_Buyers'!$AN151) | E214: =IF($A214="",0,'02_Buyers'!$AO151) | F214: =IF($A214="",0,'02_Buyers'!$AP151) | G214: =IF($A214="",0,'02_Buyers'!$V151) | H214: =IF(OR($A214="",'02_Buyers'!$AC151=""),0,'02_Buyers'!$AC151) | I214: =IF($A214="",0,IF(OR('02_Buyers'!$U151="LC_SIGHT",'02_Buyers'!$U151="LC_USANCE"),1,0)) | J214: =IF($A214="","",'02_Buyers'!$T151) | K214: =IF($A214="",0,$B214*MIN(1,$C214*$J$6)*IF($I214=1,LGD_LC,MIN(1,LGD+$K$6))*(1-$E214)) | L214: =IF($A214="",0,$B214*MIN(1,$C214*$J$7)*IF($I214=1,LGD_LC,MIN(1,LGD+$K$7))*(1-$E214)) | M214: =IF($A214="",0,$B214*MIN(1,$C214*$J$8)*IF($I214=1,LGD_LC,MIN(1,LGD+$K$8))*(1-$E214)) | N214: =IF($A214="",0,$B214*MIN(1,$C214*$J$9)*IF($I214=1,LGD_LC,MIN(1,LGD+$K$9))*(1-$E214)) | O214: =IF($A214="",0,$B214*MIN(1,$C214*$J$10)*IF($I214=1,LGD_LC,MIN(1,LGD+$K$10))*(1-$E214)) | P214: =IF($A214="",0,$B214*MIN(1,$C214*$J$12)*IF($I214=1,LGD_LC,MIN(1,LGD+$K$12))*(1-$E214)) | Q214: =IF($A214="",0,$B214*(TSOFR3M+$H$6/10000+$F214)*$G214/DayBasis) | R214: =IF($A214="",0,$B214*(TSOFR3M+$H$7/10000+$F214)*$G214/DayBasis) | S214: =IF($A214="",0,$B214*(TSOFR3M+$H$8/10000+$F214)*$G214/DayBasis) | T214: =IF($A214="",0,$B214*(TSOFR3M+$H$9/10000+$F214)*$G214/DayBasis) | U214: =IF($A214="",0,$B214*(TSOFR3M+$H$10/10000+$F214)*$G214/DayBasis) | V214: =IF($A214="",0,$B214*(TSOFR3M+$H$12/10000+$F214)*$G214/DayBasis) | W214: =IF(OR($A214="",$M$6<>"Y",$O$6=""),0,IF($H214>=$O$6,$B214*(TSOFR3M+$H$6/10000+$F214)*$N$6/DayBasis,0)) | X214: =IF(OR($A214="",$M$7<>"Y",$O$7=""),0,IF($H214>=$O$7,$B214*(TSOFR3M+$H$7/10000+$F214)*$N$7/DayBasis,0)) | Y214: =IF(OR($A214="",$M$8<>"Y",$O$8=""),0,IF($H214>=$O$8,$B214*(TSOFR3M+$H$8/10000+$F214)*$N$8/DayBasis,0)) | Z214: =IF(OR($A214="",$M$9<>"Y",$O$9=""),0,IF($H214>=$O$9,$B214*(TSOFR3M+$H$9/10000+$F214)*$N$9/DayBasis,0)) | AA214: =IF(OR($A214="",$M$10<>"Y",$O$10=""),0,IF($H214>=$O$10,$B214*(TSOFR3M+$H$10/10000+$F214)*$N$10/DayBasis,0)) | AB214: =IF(OR($A214="",$M$12<>"Y",$O$12=""),0,IF($H214>=$O$12,$B214*(TSOFR3M+$H$12/10000+$F214)*$N$12/DayBasis,0)) | AC214: =IF($A214="",0,MIN(1,$C214*$C$39)) | AD214: =IF($A214="",0,$B214*IF($I214=1,LGD_LC,MIN(1,LGD+$C$40))*(1-$E214)) | AE214: =IF(OR($A214="",$B214<=0,$AC214<=0),0,IF($AC214>=1,$AD214,IF(_xlfn.NORM.S.INV(RAND())*SQRT(1-Rho)+$C$41*SQRT(Rho)<_xlfn.NORM.S.INV($AC214),$AD214,0))) | AG214: 208 | AH214: 0
AG215: 209 | AH215: 0
AG216: 210 | AH216: 0
AG217: 211 | AH217: 0
AG218: 212 | AH218: 0
AG219: 213 | AH219: 0
AG220: 214 | AH220: 0
AG221: 215 | AH221: 0
AG222: 216 | AH222: 0
AG223: 217 | AH223: 0
AG224: 218 | AH224: 0
AG225: 219 | AH225: 0
AG226: 220 | AH226: 0
... AG1006: 1000 | AH1006: 0

Sheet 12_ECL
A1: 12_ECL — 충당금 매트릭스 3종(🔵) · 연령 = 13_EarlyWarning open_inv(미결)
A2: 구간 정의가 서로 다르다 — IFRS 9 예시(4구간)·인바디(4구간) 요율은 한빛 6구간에 '가장 가까운 구간'으로 붙였다(매핑 = 교육용 가정)
A3: 충당금(매트릭스)은 총액 기준(보험 미반영) · PD×LGD×EAD(02_Buyers EL)는 보험·신용사건 반영 — 같은 숫자가 나오지 않는 것이 정상
A5: 구간 | B5: 한빛(제32조) | C5: IFRS 9 예시 | D5: 인바디 해외 | E5: IFRS 매핑 | F5: 인바디 매핑 | G5: 잔액(USD) | H5: 충당금 한빛 | I5: 충당금 IFRS | J5: 충당금 인바디
A6: 미연체 | B6: 0.01 | C6: 0.01 | D6: 0.0248 | E6: 미연체 | F6: 현재 | G6: =SUMIFS(inv_usd,inv_bucket,A6,inv_paid,"N") | H6: =$G6*B6 | I6: =$G6*C6 | J6: =$G6*D6
A7: 1-30 | B7: 0.025 | C7: 0.02 | D7: 0.0248 | E7: 30일 미만 | F7: 현재(3개월 미만 연체 포함으로 해석) | G7: =SUMIFS(inv_usd,inv_bucket,A7,inv_paid,"N") | H7: =$G7*B7 | I7: =$G7*C7 | J7: =$G7*D7
A8: 31-90 | B8: 0.08 | C8: 0.03 | D8: 0.0248 | E8: 30~90일 | F8: 현재(같음) | G8: =SUMIFS(inv_usd,inv_bucket,A8,inv_paid,"N") | H8: =$G8*B8 | I8: =$G8*C8 | J8: =$G8*D8
A9: 91-180 | B9: 0.22 | C9: 0.2 | D9: 0.074 | E9: 90~180일 | F9: 3~6개월 | G9: =SUMIFS(inv_usd,inv_bucket,A9,inv_paid,"N") | H9: =$G9*B9 | I9: =$G9*C9 | J9: =$G9*D9
A10: 181-365 | B10: 0.5 | C10: 0.2 | D10: 0.2182 | E10: (없음 → 90~180일) | F10: 6~12개월 | G10: =SUMIFS(inv_usd,inv_bucket,A10,inv_paid,"N") | H10: =$G10*B10 | I10: =$G10*C10 | J10: =$G10*D10
A11: 365+ | B11: 1 | C11: 0.2 | D11: 0.1898 | E11: (없음 → 90~180일) | F11: 1년 초과 | G11: =SUMIFS(inv_usd,inv_bucket,A11,inv_paid,"N") | H11: =$G11*B11 | I11: =$G11*C11 | J11: =$G11*D11
A12: 합계 | G12: =SUM(G6:G11) | H12: =SUM(H6:H11) | I12: =SUM(I6:I11) | J12: =SUM(J6:J11)
A14: 비교
A15: PD×LGD×EAD(02_Buyers EL, 보험·신용사건 반영) | B15: =SUM('02_Buyers'!$BG$2:$BG$151)
A16: 한빛 매트릭스 − PD×LGD×EAD | B16: =H12-B15
A17: 02_Buyers 잔액 합계 | B17: =SUM('02_Buyers'!$Z$2:$Z$151)
A18: open_inv 잔액 합계(300행 상한 — 차이는 제외된 미연체 건) | B18: =G12

Sheet 13_EarlyWarning
A1: 13_EarlyWarning — 조기경보·독촉 사다리(정본) · open_inv(기준일 미결 인보이스 ≤300행)
A2: D-3 사전 안내 → D+7 친절한 리마인더 → D+15 단호한 통지 → D+30 최종 통지·선적 보류(약관 제7조①2) · 결제기일 + 1개월 이내 K-SURE 사고발생통지(제21조②, 사람 결정) · 파산신청 인지 즉시 선적 중단(제7조①6)
A3: AsOf | B3: =AsOf | AB3: 바이어 단위 요약(02_Buyers 행 순서) — ship_hold → 02_Buyers UB
A4: invoice_id | B4: buyer_id | C4: country_code | D4: payment_method | E4: currency | F4: ksure_insured | G4: ship_date | H4: due_date | I4: amount_ccy | J4: amount_usd | K4: paid | L4: insurance_type | M4: terms_change_date | N4: bank_change_request | O4: dpd | P4: stage | Q4: notice_deadline | R4: notice_days_left | S4: ksure_alert | T4: export_notice_by | U4: terms_notify_by | V4: fraud_alert | W4: nonlc_dpd | X4: hold30 | Y4: aging_bucket | Z4: imminent_rank | AB4: buyer_id | AC4: bankruptcy_flag | AD4: open_cnt | AE4: open_usd | AF4: oldest_dpd_nonlc | AG4: over30_cnt | AH4: ship_hold | AI4: escalate | AJ4: ksure_imminent_cnt | AK4: L_new | AL4: util_new | AM4: util_alert | AN4: crc_now | AO4: crc_prev | AP4: crc_alert | AQ4: hold_rank | AS4: 단계 | AT4: 건수 | AU4: 금액(USD)
A5: INV-2608-0001 | B5: B001 | C5: NLD | D5: OA | E5: EUR | F5: N | G5: 46235 | H5: 46325 | I5: 3610 | J5: 4115.4 | K5: N | N5: N | O5: =IF($A5="","",AsOf-$H5) | P5: =IF($A5="","",IF($K5="Y","-",IF($O5>=30,"D+30 최종통지·선적보류",IF($O5>=15,"D+15 단호한 통지",IF($O5>=7,"D+7 친절한 리마인더",IF(AND($O5>=-3,$O5<=-1),"D-3 사전 안내","모니터링")))))) | Q5: =IF($A5="","",EDATE($H5,1)) | R5: =IF($A5="","",$Q5-AsOf) | S5: =IF($A5="","",IF(OR($K5="Y",$F5<>"Y",$O5<=0),"",IF($R5<0,"통지 기한 경과 — 즉시 확인",IF($R5<=NoticeWarnDays,"통지 기한 임박 — 사람 결정","")))) | T5: =IF(OR($A5="",$F5<>"Y"),"",IF(IF($L5="",InsuranceType,$L5)="포괄",DATE(YEAR($G5),MONTH($G5)+1,20),WORKDAY($G5,10))) | U5: =IF(OR($A5="",$M5=""),"",WORKDAY($M5,10)) | V5: =IF($A5="","",IF($N5="Y","사기 의심: 콜백 검증 전 대금 안내 중단","")) | W5: =IF($A5="","",IF(AND($K5="N",$D5<>"LC_SIGHT",$D5<>"LC_USANCE",$D5<>"TT_ADV"),$O5,"")) | X5: =IF($A5="",0,IF(AND($K5="N",$D5<>"LC_SIGHT",$D5<>"LC_USANCE",$D5<>"TT_ADV",$O5>=30),1,0)) | Y5: =IF($A5="","",IF($O5<=0,"미연체",IF($O5<=30,"1-30",IF($O5<=90,"31-90",IF($O5<=180,"91-180",IF($O5<=365,"181-365","365+")))))) | Z5: =IF($S5="통지 기한 임박 — 사람 결정",COUNTIF($S$5:$S5,"통지 기한 임박 — 사람 결정"),"") | AB5: =IF('02_Buyers'!$A2="","",'02_Buyers'!$A2) | AC5: =IF($AB5="","",'02_Buyers'!$AH2) | AD5: =IF($AB5="","",COUNTIFS(inv_buyer,$AB5,inv_paid,"N")) | AE5: =IF($AB5="","",SUMIFS(inv_usd,inv_buyer,$AB5,inv_paid,"N")) | AF5: =IF($AB5="","",_xlfn.MAXIFS(inv_nonlc_dpd,inv_buyer,$AB5)) | AG5: =IF($AB5="","",COUNTIFS(inv_buyer,$AB5,inv_hold30,1)) | AH5: =IF($AB5="","",IF(OR($AC5=1,$AG5>0),"선적 보류","")) | AI5: =IF($AH5<>"선적 보류","","내부 에스컬레이션: 여신 한도 동결 제안(사람 승인)") | AJ5: =IF($AB5="","",COUNTIFS(inv_buyer,$AB5,inv_alert,"통지 기한 임박*")) | AK5: =IF($AB5="","",'10_LimitLP'!$F5) | AL5: =IF(OR($AB5="",$AK5<=0),"",$AE5/$AK5) | AM5: =IF($AL5="","",IF($AL5>=0.8,"사용률 80%↑ — 출고 전 사전승인(제18조)","")) | AN5: =IF($AB5="","",IFERROR(IF(INDEX($AU$21:$AU$40,MATCH('02_Buyers'!$S2,$AS$21:$AS$40,0))="","",INDEX($AU$21:$AU$40,MATCH('02_Buyers'!$S2,$AS$21:$AS$40,0))),"")) | AO5: =IF($AB5="","",IFERROR(IF(INDEX($AV$21:$AV$40,MATCH('02_Buyers'!$S2,$AS$21:$AS$40,0))="","",INDEX($AV$21:$AV$40,MATCH('02_Buyers'!$S2,$AS$21:$AS$40,0))),"")) | AP5: =IF(OR($AB5="",$AN5="",$AO5=""),"",IF($AN5>$AO5,"국가등급 하향 — 한도 재산정","")) | AQ5: =IF($AH5="선적 보류",COUNTIF($AH$5:$AH5,"선적 보류"),"") | AS5: D-3 사전 안내 | AT5: =COUNTIF(inv_stage,AS5) | AU5: =SUMIFS(inv_usd,inv_stage,AS5)
A6: INV-2608-0014 | B6: B001 | C6: NLD | D6: OA | E6: EUR | F6: N | G6: 46237 | H6: 46327 | I6: 5620 | J6: 6406.79 | K6: N | N6: N | O6: =IF($A6="","",AsOf-$H6) | P6: =IF($A6="","",IF($K6="Y","-",IF($O6>=30,"D+30 최종통지·선적보류",IF($O6>=15,"D+15 단호한 통지",IF($O6>=7,"D+7 친절한 리마인더",IF(AND($O6>=-3,$O6<=-1),"D-3 사전 안내","모니터링")))))) | Q6: =IF($A6="","",EDATE($H6,1)) | R6: =IF($A6="","",$Q6-AsOf) | S6: =IF($A6="","",IF(OR($K6="Y",$F6<>"Y",$O6<=0),"",IF($R6<0,"통지 기한 경과 — 즉시 확인",IF($R6<=NoticeWarnDays,"통지 기한 임박 — 사람 결정","")))) | T6: =IF(OR($A6="",$F6<>"Y"),"",IF(IF($L6="",InsuranceType,$L6)="포괄",DATE(YEAR($G6),MONTH($G6)+1,20),WORKDAY($G6,10))) | U6: =IF(OR($A6="",$M6=""),"",WORKDAY($M6,10)) | V6: =IF($A6="","",IF($N6="Y","사기 의심: 콜백 검증 전 대금 안내 중단","")) | W6: =IF($A6="","",IF(AND($K6="N",$D6<>"LC_SIGHT",$D6<>"LC_USANCE",$D6<>"TT_ADV"),$O6,"")) | X6: =IF($A6="",0,IF(AND($K6="N",$D6<>"LC_SIGHT",$D6<>"LC_USANCE",$D6<>"TT_ADV",$O6>=30),1,0)) | Y6: =IF($A6="","",IF($O6<=0,"미연체",IF($O6<=30,"1-30",IF($O6<=90,"31-90",IF($O6<=180,"91-180",IF($O6<=365,"181-365","365+")))))) | Z6: =IF($S6="통지 기한 임박 — 사람 결정",COUNTIF($S$5:$S6,"통지 기한 임박 — 사람 결정"),"") | AB6: =IF('02_Buyers'!$A3="","",'02_Buyers'!$A3) | AC6: =IF($AB6="","",'02_Buyers'!$AH3) | AD6: =IF($AB6="","",COUNTIFS(inv_buyer,$AB6,inv_paid,"N")) | AE6: =IF($AB6="","",SUMIFS(inv_usd,inv_buyer,$AB6,inv_paid,"N")) | AF6: =IF($AB6="","",_xlfn.MAXIFS(inv_nonlc_dpd,inv_buyer,$AB6)) | AG6: =IF($AB6="","",COUNTIFS(inv_buyer,$AB6,inv_hold30,1)) | AH6: =IF($AB6="","",IF(OR($AC6=1,$AG6>0),"선적 보류","")) | AI6: =IF($AH6<>"선적 보류","","내부 에스컬레이션: 여신 한도 동결 제안(사람 승인)") | AJ6: =IF($AB6="","",COUNTIFS(inv_buyer,$AB6,inv_alert,"통지 기한 임박*")) | AK6: =IF($AB6="","",'10_LimitLP'!$F6) | AL6: =IF(OR($AB6="",$AK6<=0),"",$AE6/$AK6) | AM6: =IF($AL6="","",IF($AL6>=0.8,"사용률 80%↑ — 출고 전 사전승인(제18조)","")) | AN6: =IF($AB6="","",IFERROR(IF(INDEX($AU$21:$AU$40,MATCH('02_Buyers'!$S3,$AS$21:$AS$40,0))="","",INDEX($AU$21:$AU$40,MATCH('02_Buyers'!$S3,$AS$21:$AS$40,0))),"")) | AO6: =IF($AB6="","",IFERROR(IF(INDEX($AV$21:$AV$40,MATCH('02_Buyers'!$S3,$AS$21:$AS$40,0))="","",INDEX($AV$21:$AV$40,MATCH('02_Buyers'!$S3,$AS$21:$AS$40,0))),"")) | AP6: =IF(OR($AB6="",$AN6="",$AO6=""),"",IF($AN6>$AO6,"국가등급 하향 — 한도 재산정","")) | AQ6: =IF($AH6="선적 보류",COUNTIF($AH$5:$AH6,"선적 보류"),"") | AS6: D+7 친절한 리마인더 | AT6: =COUNTIF(inv_stage,AS6) | AU6: =SUMIFS(inv_usd,inv_stage,AS6)
A7: INV-2608-0032 | B7: B001 | C7: NLD | D7: OA | E7: EUR | F7: N | G7: 46242 | H7: 46332 | I7: 8870 | J7: 10111.79 | K7: N | N7: N | O7: =IF($A7="","",AsOf-$H7) | P7: =IF($A7="","",IF($K7="Y","-",IF($O7>=30,"D+30 최종통지·선적보류",IF($O7>=15,"D+15 단호한 통지",IF($O7>=7,"D+7 친절한 리마인더",IF(AND($O7>=-3,$O7<=-1),"D-3 사전 안내","모니터링")))))) | Q7: =IF($A7="","",EDATE($H7,1)) | R7: =IF($A7="","",$Q7-AsOf) | S7: =IF($A7="","",IF(OR($K7="Y",$F7<>"Y",$O7<=0),"",IF($R7<0,"통지 기한 경과 — 즉시 확인",IF($R7<=NoticeWarnDays,"통지 기한 임박 — 사람 결정","")))) | T7: =IF(OR($A7="",$F7<>"Y"),"",IF(IF($L7="",InsuranceType,$L7)="포괄",DATE(YEAR($G7),MONTH($G7)+1,20),WORKDAY($G7,10))) | U7: =IF(OR($A7="",$M7=""),"",WORKDAY($M7,10)) | V7: =IF($A7="","",IF($N7="Y","사기 의심: 콜백 검증 전 대금 안내 중단","")) | W7: =IF($A7="","",IF(AND($K7="N",$D7<>"LC_SIGHT",$D7<>"LC_USANCE",$D7<>"TT_ADV"),$O7,"")) | X7: =IF($A7="",0,IF(AND($K7="N",$D7<>"LC_SIGHT",$D7<>"LC_USANCE",$D7<>"TT_ADV",$O7>=30),1,0)) | Y7: =IF($A7="","",IF($O7<=0,"미연체",IF($O7<=30,"1-30",IF($O7<=90,"31-90",IF($O7<=180,"91-180",IF($O7<=365,"181-365","365+")))))) | Z7: =IF($S7="통지 기한 임박 — 사람 결정",COUNTIF($S$5:$S7,"통지 기한 임박 — 사람 결정"),"") | AB7: =IF('02_Buyers'!$A4="","",'02_Buyers'!$A4) | AC7: =IF($AB7="","",'02_Buyers'!$AH4) | AD7: =IF($AB7="","",COUNTIFS(inv_buyer,$AB7,inv_paid,"N")) | AE7: =IF($AB7="","",SUMIFS(inv_usd,inv_buyer,$AB7,inv_paid,"N")) | AF7: =IF($AB7="","",_xlfn.MAXIFS(inv_nonlc_dpd,inv_buyer,$AB7)) | AG7: =IF($AB7="","",COUNTIFS(inv_buyer,$AB7,inv_hold30,1)) | AH7: =IF($AB7="","",IF(OR($AC7=1,$AG7>0),"선적 보류","")) | AI7: =IF($AH7<>"선적 보류","","내부 에스컬레이션: 여신 한도 동결 제안(사람 승인)") | AJ7: =IF($AB7="","",COUNTIFS(inv_buyer,$AB7,inv_alert,"통지 기한 임박*")) | AK7: =IF($AB7="","",'10_LimitLP'!$F7) | AL7: =IF(OR($AB7="",$AK7<=0),"",$AE7/$AK7) | AM7: =IF($AL7="","",IF($AL7>=0.8,"사용률 80%↑ — 출고 전 사전승인(제18조)","")) | AN7: =IF($AB7="","",IFERROR(IF(INDEX($AU$21:$AU$40,MATCH('02_Buyers'!$S4,$AS$21:$AS$40,0))="","",INDEX($AU$21:$AU$40,MATCH('02_Buyers'!$S4,$AS$21:$AS$40,0))),"")) | AO7: =IF($AB7="","",IFERROR(IF(INDEX($AV$21:$AV$40,MATCH('02_Buyers'!$S4,$AS$21:$AS$40,0))="","",INDEX($AV$21:$AV$40,MATCH('02_Buyers'!$S4,$AS$21:$AS$40,0))),"")) | AP7: =IF(OR($AB7="",$AN7="",$AO7=""),"",IF($AN7>$AO7,"국가등급 하향 — 한도 재산정","")) | AQ7: =IF($AH7="선적 보류",COUNTIF($AH$5:$AH7,"선적 보류"),"") | AS7: D+15 단호한 통지 | AT7: =COUNTIF(inv_stage,AS7) | AU7: =SUMIFS(inv_usd,inv_stage,AS7)
A8: INV-2609-0135 | B8: B001 | C8: NLD | D8: OA | E8: EUR | F8: N | G8: 46291 | H8: 46381 | I8: 5630 | J8: 6418.19 | K8: N | N8: N | O8: =IF($A8="","",AsOf-$H8) | P8: =IF($A8="","",IF($K8="Y","-",IF($O8>=30,"D+30 최종통지·선적보류",IF($O8>=15,"D+15 단호한 통지",IF($O8>=7,"D+7 친절한 리마인더",IF(AND($O8>=-3,$O8<=-1),"D-3 사전 안내","모니터링")))))) | Q8: =IF($A8="","",EDATE($H8,1)) | R8: =IF($A8="","",$Q8-AsOf) | S8: =IF($A8="","",IF(OR($K8="Y",$F8<>"Y",$O8<=0),"",IF($R8<0,"통지 기한 경과 — 즉시 확인",IF($R8<=NoticeWarnDays,"통지 기한 임박 — 사람 결정","")))) | T8: =IF(OR($A8="",$F8<>"Y"),"",IF(IF($L8="",InsuranceType,$L8)="포괄",DATE(YEAR($G8),MONTH($G8)+1,20),WORKDAY($G8,10))) | U8: =IF(OR($A8="",$M8=""),"",WORKDAY($M8,10)) | V8: =IF($A8="","",IF($N8="Y","사기 의심: 콜백 검증 전 대금 안내 중단","")) | W8: =IF($A8="","",IF(AND($K8="N",$D8<>"LC_SIGHT",$D8<>"LC_USANCE",$D8<>"TT_ADV"),$O8,"")) | X8: =IF($A8="",0,IF(AND($K8="N",$D8<>"LC_SIGHT",$D8<>"LC_USANCE",$D8<>"TT_ADV",$O8>=30),1,0)) | Y8: =IF($A8="","",IF($O8<=0,"미연체",IF($O8<=30,"1-30",IF($O8<=90,"31-90",IF($O8<=180,"91-180",IF($O8<=365,"181-365","365+")))))) | Z8: =IF($S8="통지 기한 임박 — 사람 결정",COUNTIF($S$5:$S8,"통지 기한 임박 — 사람 결정"),"") | AB8: =IF('02_Buyers'!$A5="","",'02_Buyers'!$A5) | AC8: =IF($AB8="","",'02_Buyers'!$AH5) | AD8: =IF($AB8="","",COUNTIFS(inv_buyer,$AB8,inv_paid,"N")) | AE8: =IF($AB8="","",SUMIFS(inv_usd,inv_buyer,$AB8,inv_paid,"N")) | AF8: =IF($AB8="","",_xlfn.MAXIFS(inv_nonlc_dpd,inv_buyer,$AB8)) | AG8: =IF($AB8="","",COUNTIFS(inv_buyer,$AB8,inv_hold30,1)) | AH8: =IF($AB8="","",IF(OR($AC8=1,$AG8>0),"선적 보류","")) | AI8: =IF($AH8<>"선적 보류","","내부 에스컬레이션: 여신 한도 동결 제안(사람 승인)") | AJ8: =IF($AB8="","",COUNTIFS(inv_buyer,$AB8,inv_alert,"통지 기한 임박*")) | AK8: =IF($AB8="","",'10_LimitLP'!$F8) | AL8: =IF(OR($AB8="",$AK8<=0),"",$AE8/$AK8) | AM8: =IF($AL8="","",IF($AL8>=0.8,"사용률 80%↑ — 출고 전 사전승인(제18조)","")) | AN8: =IF($AB8="","",IFERROR(IF(INDEX($AU$21:$AU$40,MATCH('02_Buyers'!$S5,$AS$21:$AS$40,0))="","",INDEX($AU$21:$AU$40,MATCH('02_Buyers'!$S5,$AS$21:$AS$40,0))),"")) | AO8: =IF($AB8="","",IFERROR(IF(INDEX($AV$21:$AV$40,MATCH('02_Buyers'!$S5,$AS$21:$AS$40,0))="","",INDEX($AV$21:$AV$40,MATCH('02_Buyers'!$S5,$AS$21:$AS$40,0))),"")) | AP8: =IF(OR($AB8="",$AN8="",$AO8=""),"",IF($AN8>$AO8,"국가등급 하향 — 한도 재산정","")) | AQ8: =IF($AH8="선적 보류",COUNTIF($AH$5:$AH8,"선적 보류"),"") | AS8: D+30 최종통지·선적보류 | AT8: =COUNTIF(inv_stage,AS8) | AU8: =SUMIFS(inv_usd,inv_stage,AS8)
A9: INV-2607-0171 | B9: B002 | C9: CHN | D9: OA | E9: USD | F9: N | G9: 46232 | H9: 46322 | I9: 9170 | J9: 9170 | K9: N | N9: N | O9: =IF($A9="","",AsOf-$H9) | P9: =IF($A9="","",IF($K9="Y","-",IF($O9>=30,"D+30 최종통지·선적보류",IF($O9>=15,"D+15 단호한 통지",IF($O9>=7,"D+7 친절한 리마인더",IF(AND($O9>=-3,$O9<=-1),"D-3 사전 안내","모니터링")))))) | Q9: =IF($A9="","",EDATE($H9,1)) | R9: =IF($A9="","",$Q9-AsOf) | S9: =IF($A9="","",IF(OR($K9="Y",$F9<>"Y",$O9<=0),"",IF($R9<0,"통지 기한 경과 — 즉시 확인",IF($R9<=NoticeWarnDays,"통지 기한 임박 — 사람 결정","")))) | T9: =IF(OR($A9="",$F9<>"Y"),"",IF(IF($L9="",InsuranceType,$L9)="포괄",DATE(YEAR($G9),MONTH($G9)+1,20),WORKDAY($G9,10))) | U9: =IF(OR($A9="",$M9=""),"",WORKDAY($M9,10)) | V9: =IF($A9="","",IF($N9="Y","사기 의심: 콜백 검증 전 대금 안내 중단","")) | W9: =IF($A9="","",IF(AND($K9="N",$D9<>"LC_SIGHT",$D9<>"LC_USANCE",$D9<>"TT_ADV"),$O9,"")) | X9: =IF($A9="",0,IF(AND($K9="N",$D9<>"LC_SIGHT",$D9<>"LC_USANCE",$D9<>"TT_ADV",$O9>=30),1,0)) | Y9: =IF($A9="","",IF($O9<=0,"미연체",IF($O9<=30,"1-30",IF($O9<=90,"31-90",IF($O9<=180,"91-180",IF($O9<=365,"181-365","365+")))))) | Z9: =IF($S9="통지 기한 임박 — 사람 결정",COUNTIF($S$5:$S9,"통지 기한 임박 — 사람 결정"),"") | AB9: =IF('02_Buyers'!$A6="","",'02_Buyers'!$A6) | AC9: =IF($AB9="","",'02_Buyers'!$AH6) | AD9: =IF($AB9="","",COUNTIFS(inv_buyer,$AB9,inv_paid,"N")) | AE9: =IF($AB9="","",SUMIFS(inv_usd,inv_buyer,$AB9,inv_paid,"N")) | AF9: =IF($AB9="","",_xlfn.MAXIFS(inv_nonlc_dpd,inv_buyer,$AB9)) | AG9: =IF($AB9="","",COUNTIFS(inv_buyer,$AB9,inv_hold30,1)) | AH9: =IF($AB9="","",IF(OR($AC9=1,$AG9>0),"선적 보류","")) | AI9: =IF($AH9<>"선적 보류","","내부 에스컬레이션: 여신 한도 동결 제안(사람 승인)") | AJ9: =IF($AB9="","",COUNTIFS(inv_buyer,$AB9,inv_alert,"통지 기한 임박*")) | AK9: =IF($AB9="","",'10_LimitLP'!$F9) | AL9: =IF(OR($AB9="",$AK9<=0),"",$AE9/$AK9) | AM9: =IF($AL9="","",IF($AL9>=0.8,"사용률 80%↑ — 출고 전 사전승인(제18조)","")) | AN9: =IF($AB9="","",IFERROR(IF(INDEX($AU$21:$AU$40,MATCH('02_Buyers'!$S6,$AS$21:$AS$40,0))="","",INDEX($AU$21:$AU$40,MATCH('02_Buyers'!$S6,$AS$21:$AS$40,0))),"")) | AO9: =IF($AB9="","",IFERROR(IF(INDEX($AV$21:$AV$40,MATCH('02_Buyers'!$S6,$AS$21:$AS$40,0))="","",INDEX($AV$21:$AV$40,MATCH('02_Buyers'!$S6,$AS$21:$AS$40,0))),"")) | AP9: =IF(OR($AB9="",$AN9="",$AO9=""),"",IF($AN9>$AO9,"국가등급 하향 — 한도 재산정","")) | AQ9: =IF($AH9="선적 보류",COUNTIF($AH$5:$AH9,"선적 보류"),"") | AS9: 모니터링 | AT9: =COUNTIF(inv_stage,AS9) | AU9: =SUMIFS(inv_usd,inv_stage,AS9)
A10: INV-2609-0033 | B10: B002 | C10: CHN | D10: OA | E10: USD | F10: N | G10: 46271 | H10: 46361 | I10: 900 | J10: 900 | K10: N | N10: N | O10: =IF($A10="","",AsOf-$H10) | P10: =IF($A10="","",IF($K10="Y","-",IF($O10>=30,"D+30 최종통지·선적보류",IF($O10>=15,"D+15 단호한 통지",IF($O10>=7,"D+7 친절한 리마인더",IF(AND($O10>=-3,$O10<=-1),"D-3 사전 안내","모니터링")))))) | Q10: =IF($A10="","",EDATE($H10,1)) | R10: =IF($A10="","",$Q10-AsOf) | S10: =IF($A10="","",IF(OR($K10="Y",$F10<>"Y",$O10<=0),"",IF($R10<0,"통지 기한 경과 — 즉시 확인",IF($R10<=NoticeWarnDays,"통지 기한 임박 — 사람 결정","")))) | T10: =IF(OR($A10="",$F10<>"Y"),"",IF(IF($L10="",InsuranceType,$L10)="포괄",DATE(YEAR($G10),MONTH($G10)+1,20),WORKDAY($G10,10))) | U10: =IF(OR($A10="",$M10=""),"",WORKDAY($M10,10)) | V10: =IF($A10="","",IF($N10="Y","사기 의심: 콜백 검증 전 대금 안내 중단","")) | W10: =IF($A10="","",IF(AND($K10="N",$D10<>"LC_SIGHT",$D10<>"LC_USANCE",$D10<>"TT_ADV"),$O10,"")) | X10: =IF($A10="",0,IF(AND($K10="N",$D10<>"LC_SIGHT",$D10<>"LC_USANCE",$D10<>"TT_ADV",$O10>=30),1,0)) | Y10: =IF($A10="","",IF($O10<=0,"미연체",IF($O10<=30,"1-30",IF($O10<=90,"31-90",IF($O10<=180,"91-180",IF($O10<=365,"181-365","365+")))))) | Z10: =IF($S10="통지 기한 임박 — 사람 결정",COUNTIF($S$5:$S10,"통지 기한 임박 — 사람 결정"),"") | AB10: =IF('02_Buyers'!$A7="","",'02_Buyers'!$A7) | AC10: =IF($AB10="","",'02_Buyers'!$AH7) | AD10: =IF($AB10="","",COUNTIFS(inv_buyer,$AB10,inv_paid,"N")) | AE10: =IF($AB10="","",SUMIFS(inv_usd,inv_buyer,$AB10,inv_paid,"N")) | AF10: =IF($AB10="","",_xlfn.MAXIFS(inv_nonlc_dpd,inv_buyer,$AB10)) | AG10: =IF($AB10="","",COUNTIFS(inv_buyer,$AB10,inv_hold30,1)) | AH10: =IF($AB10="","",IF(OR($AC10=1,$AG10>0),"선적 보류","")) | AI10: =IF($AH10<>"선적 보류","","내부 에스컬레이션: 여신 한도 동결 제안(사람 승인)") | AJ10: =IF($AB10="","",COUNTIFS(inv_buyer,$AB10,inv_alert,"통지 기한 임박*")) | AK10: =IF($AB10="","",'10_LimitLP'!$F10) | AL10: =IF(OR($AB10="",$AK10<=0),"",$AE10/$AK10) | AM10: =IF($AL10="","",IF($AL10>=0.8,"사용률 80%↑ — 출고 전 사전승인(제18조)","")) | AN10: =IF($AB10="","",IFERROR(IF(INDEX($AU$21:$AU$40,MATCH('02_Buyers'!$S7,$AS$21:$AS$40,0))="","",INDEX($AU$21:$AU$40,MATCH('02_Buyers'!$S7,$AS$21:$AS$40,0))),"")) | AO10: =IF($AB10="","",IFERROR(IF(INDEX($AV$21:$AV$40,MATCH('02_Buyers'!$S7,$AS$21:$AS$40,0))="","",INDEX($AV$21:$AV$40,MATCH('02_Buyers'!$S7,$AS$21:$AS$40,0))),"")) | AP10: =IF(OR($AB10="",$AN10="",$AO10=""),"",IF($AN10>$AO10,"국가등급 하향 — 한도 재산정","")) | AQ10: =IF($AH10="선적 보류",COUNTIF($AH$5:$AH10,"선적 보류"),"") | AS10: 합계(미결) | AT10: =SUM(AT5:AT9) | AU10: =SUM(AU5:AU9)
A11: INV-2606-0085 | B11: B005 | C11: VNM | D11: OA | E11: USD | F11: Y | G11: 46192 | H11: 46282 | I11: 19920 | J11: 19920 | K11: N | L11: 개별 | N11: N | O11: =IF($A11="","",AsOf-$H11) | P11: =IF($A11="","",IF($K11="Y","-",IF($O11>=30,"D+30 최종통지·선적보류",IF($O11>=15,"D+15 단호한 통지",IF($O11>=7,"D+7 친절한 리마인더",IF(AND($O11>=-3,$O11<=-1),"D-3 사전 안내","모니터링")))))) | Q11: =IF($A11="","",EDATE($H11,1)) | R11: =IF($A11="","",$Q11-AsOf) | S11: =IF($A11="","",IF(OR($K11="Y",$F11<>"Y",$O11<=0),"",IF($R11<0,"통지 기한 경과 — 즉시 확인",IF($R11<=NoticeWarnDays,"통지 기한 임박 — 사람 결정","")))) | T11: =IF(OR($A11="",$F11<>"Y"),"",IF(IF($L11="",InsuranceType,$L11)="포괄",DATE(YEAR($G11),MONTH($G11)+1,20),WORKDAY($G11,10))) | U11: =IF(OR($A11="",$M11=""),"",WORKDAY($M11,10)) | V11: =IF($A11="","",IF($N11="Y","사기 의심: 콜백 검증 전 대금 안내 중단","")) | W11: =IF($A11="","",IF(AND($K11="N",$D11<>"LC_SIGHT",$D11<>"LC_USANCE",$D11<>"TT_ADV"),$O11,"")) | X11: =IF($A11="",0,IF(AND($K11="N",$D11<>"LC_SIGHT",$D11<>"LC_USANCE",$D11<>"TT_ADV",$O11>=30),1,0)) | Y11: =IF($A11="","",IF($O11<=0,"미연체",IF($O11<=30,"1-30",IF($O11<=90,"31-90",IF($O11<=180,"91-180",IF($O11<=365,"181-365","365+")))))) | Z11: =IF($S11="통지 기한 임박 — 사람 결정",COUNTIF($S$5:$S11,"통지 기한 임박 — 사람 결정"),"") | AB11: =IF('02_Buyers'!$A8="","",'02_Buyers'!$A8) | AC11: =IF($AB11="","",'02_Buyers'!$AH8) | AD11: =IF($AB11="","",COUNTIFS(inv_buyer,$AB11,inv_paid,"N")) | AE11: =IF($AB11="","",SUMIFS(inv_usd,inv_buyer,$AB11,inv_paid,"N")) | AF11: =IF($AB11="","",_xlfn.MAXIFS(inv_nonlc_dpd,inv_buyer,$AB11)) | AG11: =IF($AB11="","",COUNTIFS(inv_buyer,$AB11,inv_hold30,1)) | AH11: =IF($AB11="","",IF(OR($AC11=1,$AG11>0),"선적 보류","")) | AI11: =IF($AH11<>"선적 보류","","내부 에스컬레이션: 여신 한도 동결 제안(사람 승인)") | AJ11: =IF($AB11="","",COUNTIFS(inv_buyer,$AB11,inv_alert,"통지 기한 임박*")) | AK11: =IF($AB11="","",'10_LimitLP'!$F11) | AL11: =IF(OR($AB11="",$AK11<=0),"",$AE11/$AK11) | AM11: =IF($AL11="","",IF($AL11>=0.8,"사용률 80%↑ — 출고 전 사전승인(제18조)","")) | AN11: =IF($AB11="","",IFERROR(IF(INDEX($AU$21:$AU$40,MATCH('02_Buyers'!$S8,$AS$21:$AS$40,0))="","",INDEX($AU$21:$AU$40,MATCH('02_Buyers'!$S8,$AS$21:$AS$40,0))),"")) | AO11: =IF($AB11="","",IFERROR(IF(INDEX($AV$21:$AV$40,MATCH('02_Buyers'!$S8,$AS$21:$AS$40,0))="","",INDEX($AV$21:$AV$40,MATCH('02_Buyers'!$S8,$AS$21:$AS$40,0))),"")) | AP11: =IF(OR($AB11="",$AN11="",$AO11=""),"",IF($AN11>$AO11,"국가등급 하향 — 한도 재산정","")) | AQ11: =IF($AH11="선적 보류",COUNTIF($AH$5:$AH11,"선적 보류"),"")
A12: INV-2607-0014 | B12: B005 | C12: VNM | D12: OA | E12: USD | F12: Y | G12: 46207 | H12: 46297 | I12: 23100 | J12: 23100 | K12: N | L12: 개별 | N12: N | O12: =IF($A12="","",AsOf-$H12) | P12: =IF($A12="","",IF($K12="Y","-",IF($O12>=30,"D+30 최종통지·선적보류",IF($O12>=15,"D+15 단호한 통지",IF($O12>=7,"D+7 친절한 리마인더",IF(AND($O12>=-3,$O12<=-1),"D-3 사전 안내","모니터링")))))) | Q12: =IF($A12="","",EDATE($H12,1)) | R12: =IF($A12="","",$Q12-AsOf) | S12: =IF($A12="","",IF(OR($K12="Y",$F12<>"Y",$O12<=0),"",IF($R12<0,"통지 기한 경과 — 즉시 확인",IF($R12<=NoticeWarnDays,"통지 기한 임박 — 사람 결정","")))) | T12: =IF(OR($A12="",$F12<>"Y"),"",IF(IF($L12="",InsuranceType,$L12)="포괄",DATE(YEAR($G12),MONTH($G12)+1,20),WORKDAY($G12,10))) | U12: =IF(OR($A12="",$M12=""),"",WORKDAY($M12,10)) | V12: =IF($A12="","",IF($N12="Y","사기 의심: 콜백 검증 전 대금 안내 중단","")) | W12: =IF($A12="","",IF(AND($K12="N",$D12<>"LC_SIGHT",$D12<>"LC_USANCE",$D12<>"TT_ADV"),$O12,"")) | X12: =IF($A12="",0,IF(AND($K12="N",$D12<>"LC_SIGHT",$D12<>"LC_USANCE",$D12<>"TT_ADV",$O12>=30),1,0)) | Y12: =IF($A12="","",IF($O12<=0,"미연체",IF($O12<=30,"1-30",IF($O12<=90,"31-90",IF($O12<=180,"91-180",IF($O12<=365,"181-365","365+")))))) | Z12: =IF($S12="통지 기한 임박 — 사람 결정",COUNTIF($S$5:$S12,"통지 기한 임박 — 사람 결정"),"") | AB12: =IF('02_Buyers'!$A9="","",'02_Buyers'!$A9) | AC12: =IF($AB12="","",'02_Buyers'!$AH9) | AD12: =IF($AB12="","",COUNTIFS(inv_buyer,$AB12,inv_paid,"N")) | AE12: =IF($AB12="","",SUMIFS(inv_usd,inv_buyer,$AB12,inv_paid,"N")) | AF12: =IF($AB12="","",_xlfn.MAXIFS(inv_nonlc_dpd,inv_buyer,$AB12)) | AG12: =IF($AB12="","",COUNTIFS(inv_buyer,$AB12,inv_hold30,1)) | AH12: =IF($AB12="","",IF(OR($AC12=1,$AG12>0),"선적 보류","")) | AI12: =IF($AH12<>"선적 보류","","내부 에스컬레이션: 여신 한도 동결 제안(사람 승인)") | AJ12: =IF($AB12="","",COUNTIFS(inv_buyer,$AB12,inv_alert,"통지 기한 임박*")) | AK12: =IF($AB12="","",'10_LimitLP'!$F12) | AL12: =IF(OR($AB12="",$AK12<=0),"",$AE12/$AK12) | AM12: =IF($AL12="","",IF($AL12>=0.8,"사용률 80%↑ — 출고 전 사전승인(제18조)","")) | AN12: =IF($AB12="","",IFERROR(IF(INDEX($AU$21:$AU$40,MATCH('02_Buyers'!$S9,$AS$21:$AS$40,0))="","",INDEX($AU$21:$AU$40,MATCH('02_Buyers'!$S9,$AS$21:$AS$40,0))),"")) | AO12: =IF($AB12="","",IFERROR(IF(INDEX($AV$21:$AV$40,MATCH('02_Buyers'!$S9,$AS$21:$AS$40,0))="","",INDEX($AV$21:$AV$40,MATCH('02_Buyers'!$S9,$AS$21:$AS$40,0))),"")) | AP12: =IF(OR($AB12="",$AN12="",$AO12=""),"",IF($AN12>$AO12,"국가등급 하향 — 한도 재산정","")) | AQ12: =IF($AH12="선적 보류",COUNTIF($AH$5:$AH12,"선적 보류"),"") | AS12: K-SURE 통지 기한 임박(건) | AT12: =COUNTIF(inv_alert,"통지 기한 임박*")
A13: INV-2607-0043 | B13: B005 | C13: VNM | D13: OA | E13: USD | F13: Y | G13: 46212 | H13: 46302 | I13: 9130 | J13: 9130 | K13: N | L13: 개별 | N13: N | O13: =IF($A13="","",AsOf-$H13) | P13: =IF($A13="","",IF($K13="Y","-",IF($O13>=30,"D+30 최종통지·선적보류",IF($O13>=15,"D+15 단호한 통지",IF($O13>=7,"D+7 친절한 리마인더",IF(AND($O13>=-3,$O13<=-1),"D-3 사전 안내","모니터링")))))) | Q13: =IF($A13="","",EDATE($H13,1)) | R13: =IF($A13="","",$Q13-AsOf) | S13: =IF($A13="","",IF(OR($K13="Y",$F13<>"Y",$O13<=0),"",IF($R13<0,"통지 기한 경과 — 즉시 확인",IF($R13<=NoticeWarnDays,"통지 기한 임박 — 사람 결정","")))) | T13: =IF(OR($A13="",$F13<>"Y"),"",IF(IF($L13="",InsuranceType,$L13)="포괄",DATE(YEAR($G13),MONTH($G13)+1,20),WORKDAY($G13,10))) | U13: =IF(OR($A13="",$M13=""),"",WORKDAY($M13,10)) | V13: =IF($A13="","",IF($N13="Y","사기 의심: 콜백 검증 전 대금 안내 중단","")) | W13: =IF($A13="","",IF(AND($K13="N",$D13<>"LC_SIGHT",$D13<>"LC_USANCE",$D13<>"TT_ADV"),$O13,"")) | X13: =IF($A13="",0,IF(AND($K13="N",$D13<>"LC_SIGHT",$D13<>"LC_USANCE",$D13<>"TT_ADV",$O13>=30),1,0)) | Y13: =IF($A13="","",IF($O13<=0,"미연체",IF($O13<=30,"1-30",IF($O13<=90,"31-90",IF($O13<=180,"91-180",IF($O13<=365,"181-365","365+")))))) | Z13: =IF($S13="통지 기한 임박 — 사람 결정",COUNTIF($S$5:$S13,"통지 기한 임박 — 사람 결정"),"") | AB13: =IF('02_Buyers'!$A10="","",'02_Buyers'!$A10) | AC13: =IF($AB13="","",'02_Buyers'!$AH10) | AD13: =IF($AB13="","",COUNTIFS(inv_buyer,$AB13,inv_paid,"N")) | AE13: =IF($AB13="","",SUMIFS(inv_usd,inv_buyer,$AB13,inv_paid,"N")) | AF13: =IF($AB13="","",_xlfn.MAXIFS(inv_nonlc_dpd,inv_buyer,$AB13)) | AG13: =IF($AB13="","",COUNTIFS(inv_buyer,$AB13,inv_hold30,1)) | AH13: =IF($AB13="","",IF(OR($AC13=1,$AG13>0),"선적 보류","")) | AI13: =IF($AH13<>"선적 보류","","내부 에스컬레이션: 여신 한도 동결 제안(사람 승인)") | AJ13: =IF($AB13="","",COUNTIFS(inv_buyer,$AB13,inv_alert,"통지 기한 임박*")) | AK13: =IF($AB13="","",'10_LimitLP'!$F13) | AL13: =IF(OR($AB13="",$AK13<=0),"",$AE13/$AK13) | AM13: =IF($AL13="","",IF($AL13>=0.8,"사용률 80%↑ — 출고 전 사전승인(제18조)","")) | AN13: =IF($AB13="","",IFERROR(IF(INDEX($AU$21:$AU$40,MATCH('02_Buyers'!$S10,$AS$21:$AS$40,0))="","",INDEX($AU$21:$AU$40,MATCH('02_Buyers'!$S10,$AS$21:$AS$40,0))),"")) | AO13: =IF($AB13="","",IFERROR(IF(INDEX($AV$21:$AV$40,MATCH('02_Buyers'!$S10,$AS$21:$AS$40,0))="","",INDEX($AV$21:$AV$40,MATCH('02_Buyers'!$S10,$AS$21:$AS$40,0))),"")) | AP13: =IF(OR($AB13="",$AN13="",$AO13=""),"",IF($AN13>$AO13,"국가등급 하향 — 한도 재산정","")) | AQ13: =IF($AH13="선적 보류",COUNTIF($AH$5:$AH13,"선적 보류"),"") | AS13: K-SURE 통지 기한 경과(건) | AT13: =COUNTIF(inv_alert,"통지 기한 경과*")
A14: INV-2607-0085 | B14: B005 | C14: VNM | D14: OA | E14: USD | F14: Y | G14: 46219 | H14: 46309 | I14: 38050 | J14: 38050 | K14: N | L14: 개별 | N14: N | O14: =IF($A14="","",AsOf-$H14) | P14: =IF($A14="","",IF($K14="Y","-",IF($O14>=30,"D+30 최종통지·선적보류",IF($O14>=15,"D+15 단호한 통지",IF($O14>=7,"D+7 친절한 리마인더",IF(AND($O14>=-3,$O14<=-1),"D-3 사전 안내","모니터링")))))) | Q14: =IF($A14="","",EDATE($H14,1)) | R14: =IF($A14="","",$Q14-AsOf) | S14: =IF($A14="","",IF(OR($K14="Y",$F14<>"Y",$O14<=0),"",IF($R14<0,"통지 기한 경과 — 즉시 확인",IF($R14<=NoticeWarnDays,"통지 기한 임박 — 사람 결정","")))) | T14: =IF(OR($A14="",$F14<>"Y"),"",IF(IF($L14="",InsuranceType,$L14)="포괄",DATE(YEAR($G14),MONTH($G14)+1,20),WORKDAY($G14,10))) | U14: =IF(OR($A14="",$M14=""),"",WORKDAY($M14,10)) | V14: =IF($A14="","",IF($N14="Y","사기 의심: 콜백 검증 전 대금 안내 중단","")) | W14: =IF($A14="","",IF(AND($K14="N",$D14<>"LC_SIGHT",$D14<>"LC_USANCE",$D14<>"TT_ADV"),$O14,"")) | X14: =IF($A14="",0,IF(AND($K14="N",$D14<>"LC_SIGHT",$D14<>"LC_USANCE",$D14<>"TT_ADV",$O14>=30),1,0)) | Y14: =IF($A14="","",IF($O14<=0,"미연체",IF($O14<=30,"1-30",IF($O14<=90,"31-90",IF($O14<=180,"91-180",IF($O14<=365,"181-365","365+")))))) | Z14: =IF($S14="통지 기한 임박 — 사람 결정",COUNTIF($S$5:$S14,"통지 기한 임박 — 사람 결정"),"") | AB14: =IF('02_Buyers'!$A11="","",'02_Buyers'!$A11) | AC14: =IF($AB14="","",'02_Buyers'!$AH11) | AD14: =IF($AB14="","",COUNTIFS(inv_buyer,$AB14,inv_paid,"N")) | AE14: =IF($AB14="","",SUMIFS(inv_usd,inv_buyer,$AB14,inv_paid,"N")) | AF14: =IF($AB14="","",_xlfn.MAXIFS(inv_nonlc_dpd,inv_buyer,$AB14)) | AG14: =IF($AB14="","",COUNTIFS(inv_buyer,$AB14,inv_hold30,1)) | AH14: =IF($AB14="","",IF(OR($AC14=1,$AG14>0),"선적 보류","")) | AI14: =IF($AH14<>"선적 보류","","내부 에스컬레이션: 여신 한도 동결 제안(사람 승인)") | AJ14: =IF($AB14="","",COUNTIFS(inv_buyer,$AB14,inv_alert,"통지 기한 임박*")) | AK14: =IF($AB14="","",'10_LimitLP'!$F14) | AL14: =IF(OR($AB14="",$AK14<=0),"",$AE14/$AK14) | AM14: =IF($AL14="","",IF($AL14>=0.8,"사용률 80%↑ — 출고 전 사전승인(제18조)","")) | AN14: =IF($AB14="","",IFERROR(IF(INDEX($AU$21:$AU$40,MATCH('02_Buyers'!$S11,$AS$21:$AS$40,0))="","",INDEX($AU$21:$AU$40,MATCH('02_Buyers'!$S11,$AS$21:$AS$40,0))),"")) | AO14: =IF($AB14="","",IFERROR(IF(INDEX($AV$21:$AV$40,MATCH('02_Buyers'!$S11,$AS$21:$AS$40,0))="","",INDEX($AV$21:$AV$40,MATCH('02_Buyers'!$S11,$AS$21:$AS$40,0))),"")) | AP14: =IF(OR($AB14="",$AN14="",$AO14=""),"",IF($AN14>$AO14,"국가등급 하향 — 한도 재산정","")) | AQ14: =IF($AH14="선적 보류",COUNTIF($AH$5:$AH14,"선적 보류"),"") | AS14: 사기 경보(건) | AT14: =COUNTIF(inv_fraud,"사기*")
A15: INV-2607-0133 | B15: B005 | C15: VNM | D15: OA | E15: USD | F15: Y | G15: 46225 | H15: 46315 | I15: 13160 | J15: 13160 | K15: N | L15: 개별 | N15: N | O15: =IF($A15="","",AsOf-$H15) | P15: =IF($A15="","",IF($K15="Y","-",IF($O15>=30,"D+30 최종통지·선적보류",IF($O15>=15,"D+15 단호한 통지",IF($O15>=7,"D+7 친절한 리마인더",IF(AND($O15>=-3,$O15<=-1),"D-3 사전 안내","모니터링")))))) | Q15: =IF($A15="","",EDATE($H15,1)) | R15: =IF($A15="","",$Q15-AsOf) | S15: =IF($A15="","",IF(OR($K15="Y",$F15<>"Y",$O15<=0),"",IF($R15<0,"통지 기한 경과 — 즉시 확인",IF($R15<=NoticeWarnDays,"통지 기한 임박 — 사람 결정","")))) | T15: =IF(OR($A15="",$F15<>"Y"),"",IF(IF($L15="",InsuranceType,$L15)="포괄",DATE(YEAR($G15),MONTH($G15)+1,20),WORKDAY($G15,10))) | U15: =IF(OR($A15="",$M15=""),"",WORKDAY($M15,10)) | V15: =IF($A15="","",IF($N15="Y","사기 의심: 콜백 검증 전 대금 안내 중단","")) | W15: =IF($A15="","",IF(AND($K15="N",$D15<>"LC_SIGHT",$D15<>"LC_USANCE",$D15<>"TT_ADV"),$O15,"")) | X15: =IF($A15="",0,IF(AND($K15="N",$D15<>"LC_SIGHT",$D15<>"LC_USANCE",$D15<>"TT_ADV",$O15>=30),1,0)) | Y15: =IF($A15="","",IF($O15<=0,"미연체",IF($O15<=30,"1-30",IF($O15<=90,"31-90",IF($O15<=180,"91-180",IF($O15<=365,"181-365","365+")))))) | Z15: =IF($S15="통지 기한 임박 — 사람 결정",COUNTIF($S$5:$S15,"통지 기한 임박 — 사람 결정"),"") | AB15: =IF('02_Buyers'!$A12="","",'02_Buyers'!$A12) | AC15: =IF($AB15="","",'02_Buyers'!$AH12) | AD15: =IF($AB15="","",COUNTIFS(inv_buyer,$AB15,inv_paid,"N")) | AE15: =IF($AB15="","",SUMIFS(inv_usd,inv_buyer,$AB15,inv_paid,"N")) | AF15: =IF($AB15="","",_xlfn.MAXIFS(inv_nonlc_dpd,inv_buyer,$AB15)) | AG15: =IF($AB15="","",COUNTIFS(inv_buyer,$AB15,inv_hold30,1)) | AH15: =IF($AB15="","",IF(OR($AC15=1,$AG15>0),"선적 보류","")) | AI15: =IF($AH15<>"선적 보류","","내부 에스컬레이션: 여신 한도 동결 제안(사람 승인)") | AJ15: =IF($AB15="","",COUNTIFS(inv_buyer,$AB15,inv_alert,"통지 기한 임박*")) | AK15: =IF($AB15="","",'10_LimitLP'!$F15) | AL15: =IF(OR($AB15="",$AK15<=0),"",$AE15/$AK15) | AM15: =IF($AL15="","",IF($AL15>=0.8,"사용률 80%↑ — 출고 전 사전승인(제18조)","")) | AN15: =IF($AB15="","",IFERROR(IF(INDEX($AU$21:$AU$40,MATCH('02_Buyers'!$S12,$AS$21:$AS$40,0))="","",INDEX($AU$21:$AU$40,MATCH('02_Buyers'!$S12,$AS$21:$AS$40,0))),"")) | AO15: =IF($AB15="","",IFERROR(IF(INDEX($AV$21:$AV$40,MATCH('02_Buyers'!$S12,$AS$21:$AS$40,0))="","",INDEX($AV$21:$AV$40,MATCH('02_Buyers'!$S12,$AS$21:$AS$40,0))),"")) | AP15: =IF(OR($AB15="",$AN15="",$AO15=""),"",IF($AN15>$AO15,"국가등급 하향 — 한도 재산정","")) | AQ15: =IF($AH15="선적 보류",COUNTIF($AH$5:$AH15,"선적 보류"),"") | AS15: 선적 보류 바이어(곳) | AT15: =COUNTIF(ew_ship_hold,"선적 보류")
A16: INV-2608-0066 | B16: B005 | C16: VNM | D16: OA | E16: USD | F16: Y | G16: 46249 | H16: 46339 | I16: 7750 | J16: 7750 | K16: N | L16: 개별 | N16: N | O16: =IF($A16="","",AsOf-$H16) | P16: =IF($A16="","",IF($K16="Y","-",IF($O16>=30,"D+30 최종통지·선적보류",IF($O16>=15,"D+15 단호한 통지",IF($O16>=7,"D+7 친절한 리마인더",IF(AND($O16>=-3,$O16<=-1),"D-3 사전 안내","모니터링")))))) | Q16: =IF($A16="","",EDATE($H16,1)) | R16: =IF($A16="","",$Q16-AsOf) | S16: =IF($A16="","",IF(OR($K16="Y",$F16<>"Y",$O16<=0),"",IF($R16<0,"통지 기한 경과 — 즉시 확인",IF($R16<=NoticeWarnDays,"통지 기한 임박 — 사람 결정","")))) | T16: =IF(OR($A16="",$F16<>"Y"),"",IF(IF($L16="",InsuranceType,$L16)="포괄",DATE(YEAR($G16),MONTH($G16)+1,20),WORKDAY($G16,10))) | U16: =IF(OR($A16="",$M16=""),"",WORKDAY($M16,10)) | V16: =IF($A16="","",IF($N16="Y","사기 의심: 콜백 검증 전 대금 안내 중단","")) | W16: =IF($A16="","",IF(AND($K16="N",$D16<>"LC_SIGHT",$D16<>"LC_USANCE",$D16<>"TT_ADV"),$O16,"")) | X16: =IF($A16="",0,IF(AND($K16="N",$D16<>"LC_SIGHT",$D16<>"LC_USANCE",$D16<>"TT_ADV",$O16>=30),1,0)) | Y16: =IF($A16="","",IF($O16<=0,"미연체",IF($O16<=30,"1-30",IF($O16<=90,"31-90",IF($O16<=180,"91-180",IF($O16<=365,"181-365","365+")))))) | Z16: =IF($S16="통지 기한 임박 — 사람 결정",COUNTIF($S$5:$S16,"통지 기한 임박 — 사람 결정"),"") | AB16: =IF('02_Buyers'!$A13="","",'02_Buyers'!$A13) | AC16: =IF($AB16="","",'02_Buyers'!$AH13) | AD16: =IF($AB16="","",COUNTIFS(inv_buyer,$AB16,inv_paid,"N")) | AE16: =IF($AB16="","",SUMIFS(inv_usd,inv_buyer,$AB16,inv_paid,"N")) | AF16: =IF($AB16="","",_xlfn.MAXIFS(inv_nonlc_dpd,inv_buyer,$AB16)) | AG16: =IF($AB16="","",COUNTIFS(inv_buyer,$AB16,inv_hold30,1)) | AH16: =IF($AB16="","",IF(OR($AC16=1,$AG16>0),"선적 보류","")) | AI16: =IF($AH16<>"선적 보류","","내부 에스컬레이션: 여신 한도 동결 제안(사람 승인)") | AJ16: =IF($AB16="","",COUNTIFS(inv_buyer,$AB16,inv_alert,"통지 기한 임박*")) | AK16: =IF($AB16="","",'10_LimitLP'!$F16) | AL16: =IF(OR($AB16="",$AK16<=0),"",$AE16/$AK16) | AM16: =IF($AL16="","",IF($AL16>=0.8,"사용률 80%↑ — 출고 전 사전승인(제18조)","")) | AN16: =IF($AB16="","",IFERROR(IF(INDEX($AU$21:$AU$40,MATCH('02_Buyers'!$S13,$AS$21:$AS$40,0))="","",INDEX($AU$21:$AU$40,MATCH('02_Buyers'!$S13,$AS$21:$AS$40,0))),"")) | AO16: =IF($AB16="","",IFERROR(IF(INDEX($AV$21:$AV$40,MATCH('02_Buyers'!$S13,$AS$21:$AS$40,0))="","",INDEX($AV$21:$AV$40,MATCH('02_Buyers'!$S13,$AS$21:$AS$40,0))),"")) | AP16: =IF(OR($AB16="",$AN16="",$AO16=""),"",IF($AN16>$AO16,"국가등급 하향 — 한도 재산정","")) | AQ16: =IF($AH16="선적 보류",COUNTIF($AH$5:$AH16,"선적 보류"),"") | AS16: 사용률 80% 경보(곳) | AT16: =COUNTIF($AM$5:$AM$154,"사용률*")
A17: INV-2609-0102 | B17: B005 | C17: VNM | D17: OA | E17: USD | F17: Y | G17: 46285 | H17: 46375 | I17: 228090 | J17: 228090 | K17: N | L17: 개별 | N17: N | O17: =IF($A17="","",AsOf-$H17) | P17: =IF($A17="","",IF($K17="Y","-",IF($O17>=30,"D+30 최종통지·선적보류",IF($O17>=15,"D+15 단호한 통지",IF($O17>=7,"D+7 친절한 리마인더",IF(AND($O17>=-3,$O17<=-1),"D-3 사전 안내","모니터링")))))) | Q17: =IF($A17="","",EDATE($H17,1)) | R17: =IF($A17="","",$Q17-AsOf) | S17: =IF($A17="","",IF(OR($K17="Y",$F17<>"Y",$O17<=0),"",IF($R17<0,"통지 기한 경과 — 즉시 확인",IF($R17<=NoticeWarnDays,"통지 기한 임박 — 사람 결정","")))) | T17: =IF(OR($A17="",$F17<>"Y"),"",IF(IF($L17="",InsuranceType,$L17)="포괄",DATE(YEAR($G17),MONTH($G17)+1,20),WORKDAY($G17,10))) | U17: =IF(OR($A17="",$M17=""),"",WORKDAY($M17,10)) | V17: =IF($A17="","",IF($N17="Y","사기 의심: 콜백 검증 전 대금 안내 중단","")) | W17: =IF($A17="","",IF(AND($K17="N",$D17<>"LC_SIGHT",$D17<>"LC_USANCE",$D17<>"TT_ADV"),$O17,"")) | X17: =IF($A17="",0,IF(AND($K17="N",$D17<>"LC_SIGHT",$D17<>"LC_USANCE",$D17<>"TT_ADV",$O17>=30),1,0)) | Y17: =IF($A17="","",IF($O17<=0,"미연체",IF($O17<=30,"1-30",IF($O17<=90,"31-90",IF($O17<=180,"91-180",IF($O17<=365,"181-365","365+")))))) | Z17: =IF($S17="통지 기한 임박 — 사람 결정",COUNTIF($S$5:$S17,"통지 기한 임박 — 사람 결정"),"") | AB17: =IF('02_Buyers'!$A14="","",'02_Buyers'!$A14) | AC17: =IF($AB17="","",'02_Buyers'!$AH14) | AD17: =IF($AB17="","",COUNTIFS(inv_buyer,$AB17,inv_paid,"N")) | AE17: =IF($AB17="","",SUMIFS(inv_usd,inv_buyer,$AB17,inv_paid,"N")) | AF17: =IF($AB17="","",_xlfn.MAXIFS(inv_nonlc_dpd,inv_buyer,$AB17)) | AG17: =IF($AB17="","",COUNTIFS(inv_buyer,$AB17,inv_hold30,1)) | AH17: =IF($AB17="","",IF(OR($AC17=1,$AG17>0),"선적 보류","")) | AI17: =IF($AH17<>"선적 보류","","내부 에스컬레이션: 여신 한도 동결 제안(사람 승인)") | AJ17: =IF($AB17="","",COUNTIFS(inv_buyer,$AB17,inv_alert,"통지 기한 임박*")) | AK17: =IF($AB17="","",'10_LimitLP'!$F17) | AL17: =IF(OR($AB17="",$AK17<=0),"",$AE17/$AK17) | AM17: =IF($AL17="","",IF($AL17>=0.8,"사용률 80%↑ — 출고 전 사전승인(제18조)","")) | AN17: =IF($AB17="","",IFERROR(IF(INDEX($AU$21:$AU$40,MATCH('02_Buyers'!$S14,$AS$21:$AS$40,0))="","",INDEX($AU$21:$AU$40,MATCH('02_Buyers'!$S14,$AS$21:$AS$40,0))),"")) | AO17: =IF($AB17="","",IFERROR(IF(INDEX($AV$21:$AV$40,MATCH('02_Buyers'!$S14,$AS$21:$AS$40,0))="","",INDEX($AV$21:$AV$40,MATCH('02_Buyers'!$S14,$AS$21:$AS$40,0))),"")) | AP17: =IF(OR($AB17="",$AN17="",$AO17=""),"",IF($AN17>$AO17,"국가등급 하향 — 한도 재산정","")) | AQ17: =IF($AH17="선적 보류",COUNTIF($AH$5:$AH17,"선적 보류"),"") | AS17: 국가등급 하향(곳) | AT17: =COUNTIF($AP$5:$AP$154,"국가등급*")
